Workbook

Sheet Ventas_odoo Interface
A1: Número | B1: Número_replica | C1: (PE) Document Number | D1: Número de Documento | E1: BUSQUEDA | F1: VAOPE Codigo Evento | G1: Evento | H1: Nombre del contacto a mostrar en la factura | I1: Fecha de factura | J1: Fecha | K1: Fecha de vencimiento | L1: Origen | M1: Referencia de pago | N1: Referencia | O1: Actividades | P1: Empresa | Q1: Importe sin impuestos firmado | R1: Impuesto firmado | S1: Total firmado | T1: Total en divisa firmado | U1: Importe pendiente firmado | V1: Moneda | W1: Por revisar | X1: Estado de pago | Y1: Facturación electrónica | Z1: Nivel de bloqueo de EDI | AA1: Mensaje de error de EDI | AB1: Estado | AC1: Tipo de gasto | AD1: nro_productos | AE1: Nombre Producto | AF1: Distribucion_analitica | AG1: %distribucion | AH1: Nombre Cuenta | AI1: Valor Unitario | AJ1: Precio_Unitario | AK1: Descuento | AL1: Tipo_cambio | AM1: Fecha Evento | AN1: FechaEvento_fechaFactura | AO1: busque
A2: FXP/2025/10/0117 | B2: FXP/2025/10/0117 | C2: E001-00000068 | D2: 02-E001-00000068 | E2: =+IF(C2="",SUBSTITUTE(SUBSTITUTE(SUBSTITUTE(B2,CHAR(160)," ")," -","-"),"- ","-"),SUBSTITUTE(SUBSTITUTE(SUBSTITUTE(C2,CHAR(160)," ")," -","-"),"- ","-")) -> E001-00000068 | F2: 0 | H2: VENTURA SABINO MIGUEL ANGEL | I2: 45944 | J2: 45944 | K2: 45944 | O2: PENDIENTE DE PAGO | P2: COLABORATIVA S.A.C. | Q2: -2170 | S2: -2170 | T2: -2170 | V2: PEN | W2: FALSE | X2: Pagado | AB2: Registrado | AN2: =+IF(AM2<>"",AM2,I2) -> 45944 | AO2: =+VLOOKUP(D2,validaciones_json!$AS:$AS,1,0) -> #N/A
A3: FXP/2025/10/0116 | B3: FXP/2025/10/0116 | C3: F002-00001584 | D3: 01-F002-00001584 | E3: =+IF(C3="",SUBSTITUTE(SUBSTITUTE(SUBSTITUTE(B3,CHAR(160)," ")," -","-"),"- ","-"),SUBSTITUTE(SUBSTITUTE(SUBSTITUTE(C3,CHAR(160)," ")," -","-"),"- ","-")) -> F002-00001584 | F3: 0 | H3: PRAGMATIC S.A.C. | I3: 45943 | J3: 45943 | K3: 45944 | L3: P00289 | N3: F002-00001584 | P3: COLABORATIVA S.A.C. | Q3: -450 | R3: -81 | S3: -531 | T3: -531 | V3: PEN | W3: FALSE | X3: Pagado | AB3: Registrado | AN3: =+IF(AM3<>"",AM3,I3) -> 45943 | AO3: =+VLOOKUP(D3,validaciones_json!$AS:$AS,1,0) -> #N/A
A4: FXP/2025/10/0113 | B4: FXP/2025/10/0113 | C4: E001-00000005 | D4: T-E001-00000005 | E4: =+IF(C4="",SUBSTITUTE(SUBSTITUTE(SUBSTITUTE(B4,CHAR(160)," ")," -","-"),"- ","-"),SUBSTITUTE(SUBSTITUTE(SUBSTITUTE(C4,CHAR(160)," ")," -","-"),"- ","-")) -> E001-00000005 | F4: 0 | H4: GUTIERREZ PETIT MARIA ANGEL | I4: 45943 | J4: 45943 | K4: 45943 | N4: E001-5 | P4: COLABORATIVA S.A.C. | Q4: -3550 | S4: -3550 | T4: -3550 | V4: PEN | W4: FALSE | X4: Pagado | AB4: Registrado | AN4: =+IF(AM4<>"",AM4,I4) -> 45943 | AO4: =+VLOOKUP(D4,validaciones_json!$AS:$AS,1,0) -> #N/A
A5: FXP/2025/10/0109 | B5: FXP/2025/10/0109 | C5: E001-00000039 | D5: 02-E001-00000039 | E5: =+IF(C5="",SUBSTITUTE(SUBSTITUTE(SUBSTITUTE(B5,CHAR(160)," ")," -","-"),"- ","-"),SUBSTITUTE(SUBSTITUTE(SUBSTITUTE(C5,CHAR(160)," ")," -","-"),"- ","-")) -> E001-00000039 | F5: 0 | H5: CARMEN CRUZ MILAGROS ZONALI | I5: 45942 | J5: 45943 | K5: 45942 | L5: P00286 | N5: E001-39 | P5: COLABORATIVA S.A.C. | Q5: -1640 | S5: -1640 | T5: -1640 | V5: PEN | W5: FALSE | X5: Pagado | AB5: Registrado | AN5: =+IF(AM5<>"",AM5,I5) -> 45942 | AO5: =+VLOOKUP(D5,validaciones_json!$AS:$AS,1,0) -> #N/A
A6: FXP/2025/10/0111 | B6: FXP/2025/10/0111 | C6: F052-01689541 | D6: 01-F052-01689541 | E6: =+IF(C6="",SUBSTITUTE(SUBSTITUTE(SUBSTITUTE(B6,CHAR(160)," ")," -","-"),"- ","-"),SUBSTITUTE(SUBSTITUTE(SUBSTITUTE(C6,CHAR(160)," ")," -","-"),"- ","-")) -> F052-01689541 | F6: 0 | H6: MAPFRE PERU S.A. | I6: 45941 | J6: 45941 | K6: 45941 | L6: P00285 | N6: F052-01689541 | P6: COLABORATIVA S.A.C. | Q6: -225 | R6: -40.5 | S6: -265.5 | T6: -265.5 | V6: PEN | W6: FALSE | X6: Pagado | AB6: Registrado | AN6: =+IF(AM6<>"",AM6,I6) -> 45941 | AO6: =+VLOOKUP(D6,validaciones_json!$AS:$AS,1,0) -> #N/A
A7: FXP/2025/10/0112 | B7: FXP/2025/10/0112 | C7: E001- 20 | D7: T-E001- 20 | E7: =+IF(C7="",SUBSTITUTE(SUBSTITUTE(SUBSTITUTE(B7,CHAR(160)," ")," -","-"),"- ","-"),SUBSTITUTE(SUBSTITUTE(SUBSTITUTE(C7,CHAR(160)," ")," -","-"),"- ","-")) -> E001-20 | F7: 0 | H7: VARGAS HUARCAYA DANIELA RUBI | I7: 45940 | J7: 45940 | K7: 45940 | N7: E001- 20 | P7: COLABORATIVA S.A.C. | Q7: -5400 | S7: -5400 | T7: -5400 | V7: PEN | W7: FALSE | X7: Pagado | AB7: Registrado | AN7: =+IF(AM7<>"",AM7,I7) -> 45940 | AO7: =+VLOOKUP(D7,validaciones_json!$AS:$AS,1,0) -> #N/A
A8: FXP/2025/10/0110 | B8: FXP/2025/10/0110 | C8: F250-00000900 | D8: 01-F250-00000900 | E8: =+IF(C8="",SUBSTITUTE(SUBSTITUTE(SUBSTITUTE(B8,CHAR(160)," ")," -","-"),"- ","-"),SUBSTITUTE(SUBSTITUTE(SUBSTITUTE(C8,CHAR(160)," ")," -","-"),"- ","-")) -> F250-00000900 | F8: 0 | H8: DOLCE CAPRICCIO SAC | I8: 45940 | J8: 45940 | K8: 45943 | L8: P00284 | P8: COLABORATIVA S.A.C. | Q8: -101.69 | R8: -18.31 | S8: -120 | T8: -120 | V8: PEN | W8: FALSE | X8: Pagado | AB8: Registrado | AN8: =+IF(AM8<>"",AM8,I8) -> 45940 | AO8: =+VLOOKUP(D8,validaciones_json!$AS:$AS,1,0) -> #N/A
A9: FXP/2025/10/0108 | B9: FXP/2025/10/0108 | C9: E001- 18 | D9: T-E001- 18 | E9: =+IF(C9="",SUBSTITUTE(SUBSTITUTE(SUBSTITUTE(B9,CHAR(160)," ")," -","-"),"- ","-"),SUBSTITUTE(SUBSTITUTE(SUBSTITUTE(C9,CHAR(160)," ")," -","-"),"- ","-")) -> E001-18 | F9: 0 | H9: GALVAN VARGAS DAYANA LIZBETH | I9: 45940 | J9: 45940 | K9: 45940 | N9: E001- 18 | P9: COLABORATIVA S.A.C. | Q9: -7000 | S9: -7000 | T9: -7000 | V9: PEN | W9: FALSE | X9: Pagado | AB9: Registrado | AN9: =+IF(AM9<>"",AM9,I9) -> 45940 | AO9: =+VLOOKUP(D9,validaciones_json!$AS:$AS,1,0) -> #N/A
A10: FXP/2025/10/0106 | B10: FXP/2025/10/0106 | C10: E001-00000057 | D10: 02-E001-00000057 | E10: =+IF(C10="",SUBSTITUTE(SUBSTITUTE(SUBSTITUTE(B10,CHAR(160)," ")," -","-"),"- ","-"),SUBSTITUTE(SUBSTITUTE(SUBSTITUTE(C10,CHAR(160)," ")," -","-"),"- ","-")) -> E001-00000057 | F10: 0 | H10: SOLANO CALDERON JUAN ALONSO | I10: 45940 | J10: 45940 | K10: 45940 | L10: P00283 | P10: COLABORATIVA S.A.C. | Q10: -338.98 | R10: -61.02 | S10: -400 | T10: -400 | V10: PEN | W10: FALSE | X10: Pagado | AB10: Registrado | AN10: =+IF(AM10<>"",AM10,I10) -> 45940 | AO10: =+VLOOKUP(D10,validaciones_json!$AS:$AS,1,0) -> #N/A
A11: FXP/2025/10/0105 | B11: FXP/2025/10/0105 | C11: E001-00000026 | D11: 02-E001-00000026 | E11: =+IF(C11="",SUBSTITUTE(SUBSTITUTE(SUBSTITUTE(B11,CHAR(160)," ")," -","-"),"- ","-"),SUBSTITUTE(SUBSTITUTE(SUBSTITUTE(C11,CHAR(160)," ")," -","-"),"- ","-")) -> E001-00000026 | F11: 0 | H11: ESPINO MORI LEANDRO JOAQUIN | I11: 45940 | J11: 45940 | K11: 45940 | L11: P00282 | P11: COLABORATIVA S.A.C. | Q11: -296.61 | R11: -53.39 | S11: -350 | T11: -350 | V11: PEN | W11: FALSE | X11: Pagado | AB11: Registrado | AN11: =+IF(AM11<>"",AM11,I11) -> 45940 | AO11: =+VLOOKUP(D11,validaciones_json!$AS:$AS,1,0) -> #N/A
A12: FXP/2025/10/0102 | B12: FXP/2025/10/0102 | C12: F030-00008004 | D12: 01-F030-00008004 | E12: =+IF(C12="",SUBSTITUTE(SUBSTITUTE(SUBSTITUTE(B12,CHAR(160)," ")," -","-"),"- ","-"),SUBSTITUTE(SUBSTITUTE(SUBSTITUTE(C12,CHAR(160)," ")," -","-"),"- ","-")) -> F030-00008004 | F12: 0 | H12: PANIFICADORA LA NUEZ SAC | I12: 45931 | J12: 45940 | K12: 45931 | N12: F030-00008004 | P12: COLABORATIVA S.A.C. | Q12: -71.7 | S12: -71.7 | T12: -71.7 | V12: PEN | W12: FALSE | X12: Pagado | AB12: Registrado | AN12: =+IF(AM12<>"",AM12,I12) -> 45931 | AO12: =+VLOOKUP(D12,validaciones_json!$AS:$AS,1,0) -> #N/A
A13: FXP/2025/10/0101 | B13: FXP/2025/10/0101 | C13: F301-00040284 | D13: 01-F301-00040284 | E13: =+IF(C13="",SUBSTITUTE(SUBSTITUTE(SUBSTITUTE(B13,CHAR(160)," ")," -","-"),"- ","-"),SUBSTITUTE(SUBSTITUTE(SUBSTITUTE(C13,CHAR(160)," ")," -","-"),"- ","-")) -> F301-00040284 | F13: 0 | H13: INVERSIONES SAP S.A. | I13: 45937 | J13: 45940 | K13: 45937 | N13: F301-00040284 | P13: COLABORATIVA S.A.C. | Q13: -127.8 | S13: -127.8 | T13: -127.8 | V13: PEN | W13: FALSE | X13: Pagado | AB13: Registrado | AN13: =+IF(AM13<>"",AM13,I13) -> 45937 | AO13: =+VLOOKUP(D13,validaciones_json!$AS:$AS,1,0) -> #N/A
A14: FXP/2025/10/0100 | B14: FXP/2025/10/0100 | C14: F004-00001283 | D14: 01-F004-00001283 | E14: =+IF(C14="",SUBSTITUTE(SUBSTITUTE(SUBSTITUTE(B14,CHAR(160)," ")," -","-"),"- ","-"),SUBSTITUTE(SUBSTITUTE(SUBSTITUTE(C14,CHAR(160)," ")," -","-"),"- ","-")) -> F004-00001283 | F14: 0 | H14: ORIENTAL GOURMET S.A. | I14: 45936 | J14: 45940 | K14: 45936 | N14: F004-1283 | P14: COLABORATIVA S.A.C. | Q14: -64.5 | S14: -64.5 | T14: -64.5 | V14: PEN | W14: FALSE | X14: Pagado | AB14: Registrado | AN14: =+IF(AM14<>"",AM14,I14) -> 45936 | AO14: =+VLOOKUP(D14,validaciones_json!$AS:$AS,1,0) -> #N/A
A15: FXP/2025/10/0099 | B15: FXP/2025/10/0099 | C15: F003-00001183 | D15: 01-F003-00001183 | E15: =+IF(C15="",SUBSTITUTE(SUBSTITUTE(SUBSTITUTE(B15,CHAR(160)," ")," -","-"),"- ","-"),SUBSTITUTE(SUBSTITUTE(SUBSTITUTE(C15,CHAR(160)," ")," -","-"),"- ","-")) -> F003-00001183 | F15: 0 | H15: MALBEC SAC | I15: 45939 | J15: 45940 | K15: 45939 | N15: F003-00001183 | P15: COLABORATIVA S.A.C. | Q15: -462 | S15: -462 | T15: -462 | V15: PEN | W15: FALSE | X15: Pagado | AB15: Registrado | AN15: =+IF(AM15<>"",AM15,I15) -> 45939 | AO15: =+VLOOKUP(D15,validaciones_json!$AS:$AS,1,0) -> #N/A
A16: FXP/2025/10/0107 | B16: FXP/2025/10/0107 | C16: E001-00000013 | D16: 01-E001-00000013 | E16: =+IF(C16="",SUBSTITUTE(SUBSTITUTE(SUBSTITUTE(B16,CHAR(160)," ")," -","-"),"- ","-"),SUBSTITUTE(SUBSTITUTE(SUBSTITUTE(C16,CHAR(160)," ")," -","-"),"- ","-")) -> E001-00000013 | F16: 0 | H16: KUNTUR PRO S.A.C. | I16: 45939 | J16: 45939 | K16: 45940 | P16: COLABORATIVA S.A.C. | Q16: -1000 | R16: -180 | S16: -1180 | T16: -1180 | V16: PEN | W16: FALSE | X16: Pagado | AB16: Registrado | AN16: =+IF(AM16<>"",AM16,I16) -> 45939 | AO16: =+VLOOKUP(D16,validaciones_json!$AS:$AS,1,0) -> #N/A
A17: FXP/2025/10/0096 | B17: FXP/2025/10/0096 | C17: E001-00000493 | D17: 01-E001-00000493 | E17: =+IF(C17="",SUBSTITUTE(SUBSTITUTE(SUBSTITUTE(B17,CHAR(160)," ")," -","-"),"- ","-"),SUBSTITUTE(SUBSTITUTE(SUBSTITUTE(C17,CHAR(160)," ")," -","-"),"- ","-")) -> E001-00000493 | F17: 0 | H17: EURO CARS PERU S.A.C. | I17: 45938 | J17: 45938 | K17: 45939 | L17: P00276 | N17: E001-493 | P17: COLABORATIVA S.A.C. | Q17: -110.17 | R17: -19.84 | S17: -130.01 | T17: -130.01 | V17: PEN | W17: FALSE | X17: Pagado | AB17: Registrado | AN17: =+IF(AM17<>"",AM17,I17) -> 45938 | AO17: =+VLOOKUP(D17,validaciones_json!$AS:$AS,1,0) -> #N/A
A18: FXP/2025/10/0095 | B18: FXP/2025/10/0095 | C18: E001-00000492 | D18: 01-E001-00000492 | E18: =+IF(C18="",SUBSTITUTE(SUBSTITUTE(SUBSTITUTE(B18,CHAR(160)," ")," -","-"),"- ","-"),SUBSTITUTE(SUBSTITUTE(SUBSTITUTE(C18,CHAR(160)," ")," -","-"),"- ","-")) -> E001-00000492 | F18: 0 | H18: EURO CARS PERU S.A.C. | I18: 45938 | J18: 45938 | K18: 45939 | L18: P00277 | N18: E001-492 | P18: COLABORATIVA S.A.C. | Q18: -550.85 | R18: -99.17 | S18: -650.02 | T18: -650.02 | V18: PEN | W18: FALSE | X18: Pagado | AB18: Registrado | AN18: =+IF(AM18<>"",AM18,I18) -> 45938 | AO18: =+VLOOKUP(D18,validaciones_json!$AS:$AS,1,0) -> #N/A
A19: FXP/2025/10/0094 | B19: FXP/2025/10/0094 | C19: E001-00000127 | D19: 01-E001-00000127 | E19: =+IF(C19="",SUBSTITUTE(SUBSTITUTE(SUBSTITUTE(B19,CHAR(160)," ")," -","-"),"- ","-"),SUBSTITUTE(SUBSTITUTE(SUBSTITUTE(C19,CHAR(160)," ")," -","-"),"- ","-")) -> E001-00000127 | F19: 0 | H19: MUÑOZ VERANO JOHN BRACKSON | I19: 45937 | J19: 45937 | K19: 45939 | L19: P00271 | N19: E001-127 | P19: COLABORATIVA S.A.C. | Q19: -1200 | R19: -216 | S19: -1416 | T19: -1416 | V19: PEN | W19: FALSE | X19: Pagado | AB19: Registrado | AN19: =+IF(AM19<>"",AM19,I19) -> 45937 | AO19: =+VLOOKUP(D19,validaciones_json!$AS:$AS,1,0) -> #N/A
A20: FXP/2025/10/0093 | B20: FXP/2025/10/0093 | C20: E001-00000129 | D20: 01-E001-00000129 | E20: =+IF(C20="",SUBSTITUTE(SUBSTITUTE(SUBSTITUTE(B20,CHAR(160)," ")," -","-"),"- ","-"),SUBSTITUTE(SUBSTITUTE(SUBSTITUTE(C20,CHAR(160)," ")," -","-"),"- ","-")) -> E001-00000129 | F20: 0 | H20: MUÑOZ VERANO JOHN BRACKSON | I20: 45937 | J20: 45937 | K20: 45939 | L20: P00272 | N20: E001-129 | P20: COLABORATIVA S.A.C. | Q20: -200 | R20: -36 | S20: -236 | T20: -236 | V20: PEN | W20: FALSE | X20: Pagado | AB20: Registrado | AN20: =+IF(AM20<>"",AM20,I20) -> 45937 | AO20: =+VLOOKUP(D20,validaciones_json!$AS:$AS,1,0) -> #N/A
A21: FXP/2025/10/0089 | B21: FXP/2025/10/0089 | C21: E001-00000128 | D21: 01-E001-00000128 | E21: =+IF(C21="",SUBSTITUTE(SUBSTITUTE(SUBSTITUTE(B21,CHAR(160)," ")," -","-"),"- ","-"),SUBSTITUTE(SUBSTITUTE(SUBSTITUTE(C21,CHAR(160)," ")," -","-"),"- ","-")) -> E001-00000128 | F21: 0 | H21: MUÑOZ VERANO JOHN BRACKSON | I21: 45937 | J21: 45937 | K21: 45937 | L21: P00274 | P21: COLABORATIVA S.A.C. | Q21: -308 | R21: -55.44 | S21: -363.44 | T21: -363.44 | V21: PEN | W21: FALSE | X21: Pagado | AB21: Registrado | AN21: =+IF(AM21<>"",AM21,I21) -> 45937 | AO21: =+VLOOKUP(D21,validaciones_json!$AS:$AS,1,0) -> #N/A
A22: FXP/2025/10/0088 | B22: FXP/2025/10/0088 | C22: E001-00000067 | D22: 02-E001-00000067 | E22: =+IF(C22="",SUBSTITUTE(SUBSTITUTE(SUBSTITUTE(B22,CHAR(160)," ")," -","-"),"- ","-"),SUBSTITUTE(SUBSTITUTE(SUBSTITUTE(C22,CHAR(160)," ")," -","-"),"- ","-")) -> E001-00000067 | F22: 0 | H22: VENTURA SABINO MIGUEL ANGEL | I22: 45937 | J22: 45937 | K22: 45937 | L22: P00273 | P22: COLABORATIVA S.A.C. | Q22: -880 | S22: -880 | T22: -880 | V22: PEN | W22: FALSE | X22: Pagado | AB22: Registrado | AN22: =+IF(AM22<>"",AM22,I22) -> 45937 | AO22: =+VLOOKUP(D22,validaciones_json!$AS:$AS,1,0) -> #N/A
A23: FXP/2025/10/0114 | B23: FXP/2025/10/0114 | C23: E001-00000016 | D23: 02-E001-00000016 | E23: =+IF(C23="",SUBSTITUTE(SUBSTITUTE(SUBSTITUTE(B23,CHAR(160)," ")," -","-"),"- ","-"),SUBSTITUTE(SUBSTITUTE(SUBSTITUTE(C23,CHAR(160)," ")," -","-"),"- ","-")) -> E001-00000016 | F23: 0 | H23: SALVADOR ARNALDO REYES CHUECAS | I23: 45936 | J23: 45936 | K23: 45943 | L23: P00287 | N23: E001-16 | P23: COLABORATIVA S.A.C. | Q23: -600 | S23: -600 | T23: -600 | V23: PEN | W23: FALSE | X23: Pagado | AB23: Registrado | AN23: =+IF(AM23<>"",AM23,I23) -> 45936 | AO23: =+VLOOKUP(D23,validaciones_json!$AS:$AS,1,0) -> #N/A
A24: FXP/2025/10/0097 | B24: FXP/2025/10/0097 | C24: E001 -38 | D24: 02-E001 -38 | E24: =+IF(C24="",SUBSTITUTE(SUBSTITUTE(SUBSTITUTE(B24,CHAR(160)," ")," -","-"),"- ","-"),SUBSTITUTE(SUBSTITUTE(SUBSTITUTE(C24,CHAR(160)," ")," -","-"),"- ","-")) -> E001-38 | F24: 0 | H24: CARMEN CRUZ MILAGROS ZONALI | I24: 45936 | J24: 45936 | K24: 45939 | L24: P00275 | N24: E001-38 | P24: COLABORATIVA S.A.C. | Q24: -160 | S24: -160 | T24: -160 | V24: PEN | W24: FALSE | X24: Pagado | AB24: Registrado | AN24: =+IF(AM24<>"",AM24,I24) -> 45936 | AO24: =+VLOOKUP(D24,validaciones_json!$AS:$AS,1,0) -> #N/A
A25: FXP/2025/10/0092 | B25: FXP/2025/10/0092 | C25: F001-00025751 | D25: 01-F001-00025751 | E25: =+IF(C25="",SUBSTITUTE(SUBSTITUTE(SUBSTITUTE(B25,CHAR(160)," ")," -","-"),"- ","-"),SUBSTITUTE(SUBSTITUTE(SUBSTITUTE(C25,CHAR(160)," ")," -","-"),"- ","-")) -> F001-00025751 | F25: 0 | H25: TECNOLOGIA FLEXOGRAFICA S.A.C - TECFLEX | I25: 45936 | J25: 45936 | K25: 45936 | L25: P00265 | P25: COLABORATIVA S.A.C. | Q25: -2477 | R25: -445.86 | S25: -2922.86 | T25: -2922.86 | V25: PEN | W25: FALSE | X25: Pagado | AB25: Registrado | AN25: =+IF(AM25<>"",AM25,I25) -> 45936 | AO25: =+VLOOKUP(D25,validaciones_json!$AS:$AS,1,0) -> #N/A
A26: FXP/2025/10/0098 | B26: FXP/2025/10/0098 | C26: 544-4458714229 | D26: 01-544-4458714229 | E26: =+IF(C26="",SUBSTITUTE(SUBSTITUTE(SUBSTITUTE(B26,CHAR(160)," ")," -","-"),"- ","-"),SUBSTITUTE(SUBSTITUTE(SUBSTITUTE(C26,CHAR(160)," ")," -","-"),"- ","-")) -> 544-4458714229 | F26: 0 | H26: LATAM AIRLINES PERU S.A. | I26: 45935 | J26: 45935 | K26: 45939 | L26: P00278 | P26: COLABORATIVA S.A.C. | Q26: -132.78 | R26: -23.9 | S26: -156.68 | T26: -156.68 | V26: PEN | W26: FALSE | X26: Pagado | AB26: Registrado | AN26: =+IF(AM26<>"",AM26,I26) -> 45935 | AO26: =+VLOOKUP(D26,validaciones_json!$AS:$AS,1,0) -> #N/A
A27: FXP/2025/10/0091 | B27: FXP/2025/10/0091 | C27: FP03-00001558 | D27: 01-FP03-00001558 | E27: =+IF(C27="",SUBSTITUTE(SUBSTITUTE(SUBSTITUTE(B27,CHAR(160)," ")," -","-"),"- ","-"),SUBSTITUTE(SUBSTITUTE(SUBSTITUTE(C27,CHAR(160)," ")," -","-"),"- ","-")) -> FP03-00001558 | F27: 0 | H27: ROJAS SIESQUEN CARLOS EDGARDO | I27: 45935 | J27: 45935 | K27: 45937 | P27: COLABORATIVA S.A.C. | Q27: -128.81 | R27: -23.19 | S27: -152 | T27: -152 | V27: PEN | W27: FALSE | X27: Pagado | AB27: Registrado | AN27: =+IF(AM27<>"",AM27,I27) -> 45935 | AO27: =+VLOOKUP(D27,validaciones_json!$AS:$AS,1,0) -> #N/A
A28: FXP/2025/10/0090 | B28: FXP/2025/10/0090 | C28: FF13-00000401 | D28: 01-FF13-00000401 | E28: =+IF(C28="",SUBSTITUTE(SUBSTITUTE(SUBSTITUTE(B28,CHAR(160)," ")," -","-"),"- ","-"),SUBSTITUTE(SUBSTITUTE(SUBSTITUTE(C28,CHAR(160)," ")," -","-"),"- ","-")) -> FF13-00000401 | F28: 0 | H28: LATAM PERU S.A.C. | I28: 45935 | J28: 45935 | K28: 45937 | P28: COLABORATIVA S.A.C. | Q28: -50.85 | R28: -9.15 | S28: -60 | T28: -60 | V28: PEN | W28: FALSE | X28: Pagado | AB28: Registrado | AN28: =+IF(AM28<>"",AM28,I28) -> 45935 | AO28: =+VLOOKUP(D28,validaciones_json!$AS:$AS,1,0) -> #N/A
A29: FXP/2025/10/0086 | B29: FXP/2025/10/0086 | C29: E001-00000004 | D29: 02-E001-00000004 | E29: =+IF(C29="",SUBSTITUTE(SUBSTITUTE(SUBSTITUTE(B29,CHAR(160)," ")," -","-"),"- ","-"),SUBSTITUTE(SUBSTITUTE(SUBSTITUTE(C29,CHAR(160)," ")," -","-"),"- ","-")) -> E001-00000004 | F29: 0 | H29: SECLEN ZAMORA JAHAIRA VANESSITA | I29: 45935 | J29: 45935 | K29: 45935 | L29: P00269 | N29: E001-4 | P29: COLABORATIVA S.A.C. | Q29: -220 | S29: -220 | T29: -220 | V29: PEN | W29: FALSE | X29: Pagado | AB29: Registrado | AN29: =+IF(AM29<>"",AM29,I29) -> 45935 | AO29: =+VLOOKUP(D29,validaciones_json!$AS:$AS,1,0) -> #N/A
A30: FXP/2025/10/0084 | B30: FXP/2025/10/0084 | C30: E001-00000015 | D30: 02-E001-00000015 | E30: =+IF(C30="",SUBSTITUTE(SUBSTITUTE(SUBSTITUTE(B30,CHAR(160)," ")," -","-"),"- ","-"),SUBSTITUTE(SUBSTITUTE(SUBSTITUTE(C30,CHAR(160)," ")," -","-"),"- ","-")) -> E001-00000015 | F30: 0 | H30: BRAVO MATOS RICARDO ALEJANDRO | I30: 45935 | J30: 45935 | K30: 45937 | L30: P00270 | M30: Pago Honorarios | P30: COLABORATIVA S.A.C. | Q30: -120 | S30: -120 | T30: -120 | V30: PEN | W30: FALSE | X30: Pagado | AB30: Registrado | AN30: =+IF(AM30<>"",AM30,I30) -> 45935 | AO30: =+VLOOKUP(D30,validaciones_json!$AS:$AS,1,0) -> #N/A
A31: FXP/2025/10/0115 | B31: FXP/2025/10/0115 | C31: SB02-0243453637 | D31: 14-SB02-0243453637 | E31: =+IF(C31="",SUBSTITUTE(SUBSTITUTE(SUBSTITUTE(B31,CHAR(160)," ")," -","-"),"- ","-"),SUBSTITUTE(SUBSTITUTE(SUBSTITUTE(C31,CHAR(160)," ")," -","-"),"- ","-")) -> SB02-0243453637 | F31: 0 | H31: America Móvil Perú S.A.C. | I31: 45934 | J31: 45934 | K31: 45944 | L31: P00288 | O31: PENDIENTE DE PAGO | P31: COLABORATIVA S.A.C. | Q31: -36.04 | R31: -6.49 | S31: -42.53 | T31: -42.53 | U31: -42.53 | V31: PEN | W31: FALSE | X31: Sin pagar | AB31: Registrado | AN31: =+IF(AM31<>"",AM31,I31) -> 45934 | AO31: =+VLOOKUP(D31,validaciones_json!$AS:$AS,1,0) -> #N/A
A32: FXP/2025/10/0078 | B32: FXP/2025/10/0078 | C32: F001-00009665 | D32: 01-F001-00009665 | E32: =+IF(C32="",SUBSTITUTE(SUBSTITUTE(SUBSTITUTE(B32,CHAR(160)," ")," -","-"),"- ","-"),SUBSTITUTE(SUBSTITUTE(SUBSTITUTE(C32,CHAR(160)," ")," -","-"),"- ","-")) -> F001-00009665 | F32: 0 | H32: PRECINTOS PERU E.I.R.L | I32: 45932 | J32: 45932 | K32: 45933 | L32: P00264 | P32: COLABORATIVA S.A.C. | Q32: -2002.56 | R32: -360.44 | S32: -2363 | T32: -2363 | V32: PEN | W32: FALSE | X32: Pagado | AB32: Registrado | AN32: =+IF(AM32<>"",AM32,I32) -> 45932 | AO32: =+VLOOKUP(D32,validaciones_json!$AS:$AS,1,0) -> #N/A
A33: FXP/2025/10/0104 | B33: FXP/2025/10/0104 | C33: FE30-00023585 | D33: 01-FE30-00023585 | E33: =+IF(C33="",SUBSTITUTE(SUBSTITUTE(SUBSTITUTE(B33,CHAR(160)," ")," -","-"),"- ","-"),SUBSTITUTE(SUBSTITUTE(SUBSTITUTE(C33,CHAR(160)," ")," -","-"),"- ","-")) -> FE30-00023585 | F33: 0 | H33: Verisure Peru SAC | I33: 45931 | J33: 45931 | K33: 45940 | P33: COLABORATIVA S.A.C. | Q33: -221.82 | R33: -39.93 | S33: -261.75 | T33: -261.75 | V33: PEN | W33: FALSE | X33: Pagado | AB33: Registrado | AN33: =+IF(AM33<>"",AM33,I33) -> 45931 | AO33: =+VLOOKUP(D33,validaciones_json!$AS:$AS,1,0) -> #N/A
A34: FXP/2025/10/0077 | B34: FXP/2025/10/0077 | C34: F004-00027540 | D34: 01-F004-00027540 | E34: =+IF(C34="",SUBSTITUTE(SUBSTITUTE(SUBSTITUTE(B34,CHAR(160)," ")," -","-"),"- ","-"),SUBSTITUTE(SUBSTITUTE(SUBSTITUTE(C34,CHAR(160)," ")," -","-"),"- ","-")) -> F004-00027540 | F34: 0 | H34: J & V MULTIUTILES PUNTO COM S.A.C. | I34: 45931 | J34: 45931 | K34: 45931 | L34: P00259 | P34: COLABORATIVA S.A.C. | Q34: -125.85 | R34: -22.65 | S34: -148.5 | T34: -148.5 | V34: PEN | W34: FALSE | X34: Pagado | AB34: Registrado | AN34: =+IF(AM34<>"",AM34,I34) -> 45931 | AO34: =+VLOOKUP(D34,validaciones_json!$AS:$AS,1,0) -> #N/A
A35: FXP/2025/10/0076 | B35: FXP/2025/10/0076 | C35: F004-00027539 | D35: 01-F004-00027539 | E35: =+IF(C35="",SUBSTITUTE(SUBSTITUTE(SUBSTITUTE(B35,CHAR(160)," ")," -","-"),"- ","-"),SUBSTITUTE(SUBSTITUTE(SUBSTITUTE(C35,CHAR(160)," ")," -","-"),"- ","-")) -> F004-00027539 | F35: 0 | H35: J & V MULTIUTILES PUNTO COM S.A.C. | I35: 45931 | J35: 45931 | K35: 45933 | L35: P00260 | P35: COLABORATIVA S.A.C. | Q35: -677.97 | R35: -122.03 | S35: -800 | T35: -800 | V35: PEN | W35: FALSE | X35: Pagado | AB35: Registrado | AN35: =+IF(AM35<>"",AM35,I35) -> 45931 | AO35: =+VLOOKUP(D35,validaciones_json!$AS:$AS,1,0) -> #N/A
A36: FXP/2025/10/0067 | B36: FXP/2025/10/0067 | C36: FE30-00023070 | D36: 01-FE30-00023070 | E36: =+IF(C36="",SUBSTITUTE(SUBSTITUTE(SUBSTITUTE(B36,CHAR(160)," ")," -","-"),"- ","-"),SUBSTITUTE(SUBSTITUTE(SUBSTITUTE(C36,CHAR(160)," ")," -","-"),"- ","-")) -> FE30-00023070 | F36: 0 | H36: Verisure Peru SAC | I36: 45931 | J36: 45931 | K36: 45932 | L36: P00262 | P36: COLABORATIVA S.A.C. | Q36: -87.29 | R36: -15.71 | S36: -103 | T36: -103 | V36: PEN | W36: FALSE | X36: Pagado | AB36: Registrado | AN36: =+IF(AM36<>"",AM36,I36) -> 45931 | AO36: =+VLOOKUP(D36,validaciones_json!$AS:$AS,1,0) -> #N/A
A37: FXP/2025/10/0087 | B37: FXP/2025/10/0087 | C37: E001-00000037 | D37: 02-E001-00000037 | E37: =+IF(C37="",SUBSTITUTE(SUBSTITUTE(SUBSTITUTE(B37,CHAR(160)," ")," -","-"),"- ","-"),SUBSTITUTE(SUBSTITUTE(SUBSTITUTE(C37,CHAR(160)," ")," -","-"),"- ","-")) -> E001-00000037 | F37: 0 | H37: CARMEN CRUZ MILAGROS ZONALI | I37: 45924 | J37: 45930 | K37: 45924 | L37: P00243 | N37: E001-37 | P37: COLABORATIVA S.A.C. | Q37: -175 | S37: -175 | T37: -175 | V37: PEN | W37: FALSE | X37: Pagado | AB37: Registrado | AN37: =+IF(AM37<>"",AM37,I37) -> 45924 | AO37: =+VLOOKUP(D37,validaciones_json!$AS:$AS,1,0) -> #N/A
A38: FXP/2025/10/0083 | B38: FXP/2025/10/0083 | C38: S106-0014885947 | D38: 14-S106-0014885947 | E38: =+IF(C38="",SUBSTITUTE(SUBSTITUTE(SUBSTITUTE(B38,CHAR(160)," ")," -","-"),"- ","-"),SUBSTITUTE(SUBSTITUTE(SUBSTITUTE(C38,CHAR(160)," ")," -","-"),"- ","-")) -> S106-0014885947 | F38: 0 | H38: SERVICIO DE AGUA POTABLE Y ALCANTARILLADO DE LIMA | I38: 45920 | J38: 45930 | K38: 45936 | L38: P00268 | P38: COLABORATIVA S.A.C. | Q38: -6.19 | R38: -1.11 | S38: -7.3 | T38: -7.3 | U38: -7.3 | V38: PEN | W38: FALSE | X38: Sin pagar | AB38: Registrado | AN38: =+IF(AM38<>"",AM38,I38) -> 45920 | AO38: =+VLOOKUP(D38,validaciones_json!$AS:$AS,1,0) -> #N/A
A39: FXP/2025/10/0081 | B39: FXP/2025/10/0081 | C39: SB01-0571094872 | D39: 14-SB01-0571094872 | E39: =+IF(C39="",SUBSTITUTE(SUBSTITUTE(SUBSTITUTE(B39,CHAR(160)," ")," -","-"),"- ","-"),SUBSTITUTE(SUBSTITUTE(SUBSTITUTE(C39,CHAR(160)," ")," -","-"),"- ","-")) -> SB01-0571094872 | F39: 0 | H39: America Móvil Perú S.A.C. | I39: 45925 | J39: 45930 | K39: 45936 | L39: P00267 | P39: COLABORATIVA S.A.C. | Q39: -76.76 | R39: -13.82 | S39: -90.58 | T39: -90.58 | U39: -90.58 | V39: PEN | W39: FALSE | X39: Sin pagar | AB39: Registrado | AN39: =+IF(AM39<>"",AM39,I39) -> 45925 | AO39: =+VLOOKUP(D39,validaciones_json!$AS:$AS,1,0) -> #N/A
A40: FXP/2025/10/0080 | B40: FXP/2025/10/0080 | C40: SB01-0571233027 | D40: 14-SB01-0571233027 | E40: =+IF(C40="",SUBSTITUTE(SUBSTITUTE(SUBSTITUTE(B40,CHAR(160)," ")," -","-"),"- ","-"),SUBSTITUTE(SUBSTITUTE(SUBSTITUTE(C40,CHAR(160)," ")," -","-"),"- ","-")) -> SB01-0571233027 | F40: 0 | H40: America Móvil Perú S.A.C. | I40: 45925 | J40: 45930 | K40: 45936 | L40: P00266 | P40: COLABORATIVA S.A.C. | Q40: -26.15 | R40: -4.71 | S40: -30.86 | T40: -30.86 | U40: -30.86 | V40: PEN | W40: FALSE | X40: Sin pagar | AB40: Registrado | AN40: =+IF(AM40<>"",AM40,I40) -> 45925 | AO40: =+VLOOKUP(D40,validaciones_json!$AS:$AS,1,0) -> #N/A
A41: FXP/2025/10/0079 | B41: FXP/2025/10/0079 | C41: FRE1-00007302 | D41: 01-FRE1-00007302 | E41: =+IF(C41="",SUBSTITUTE(SUBSTITUTE(SUBSTITUTE(B41,CHAR(160)," ")," -","-"),"- ","-"),SUBSTITUTE(SUBSTITUTE(SUBSTITUTE(C41,CHAR(160)," ")," -","-"),"- ","-")) -> FRE1-00007302 | F41: 0 | H41: RASH PERU S.R.L | I41: 45925 | J41: 45930 | K41: 45933 | P41: COLABORATIVA S.A.C. | Q41: -9.24 | R41: -1.66 | S41: -10.9 | T41: -10.9 | V41: PEN | W41: FALSE | X41: Pagado | AB41: Registrado | AN41: =+IF(AM41<>"",AM41,I41) -> 45925 | AO41: =+VLOOKUP(D41,validaciones_json!$AS:$AS,1,0) -> #N/A
A42: FXP/2025/10/0074 | B42: FXP/2025/10/0074 | C42: SB01-0569026304 | D42: 14-SB01-0569026304 | E42: =+IF(C42="",SUBSTITUTE(SUBSTITUTE(SUBSTITUTE(B42,CHAR(160)," ")," -","-"),"- ","-"),SUBSTITUTE(SUBSTITUTE(SUBSTITUTE(C42,CHAR(160)," ")," -","-"),"- ","-")) -> SB01-0569026304 | F42: 0 | H42: America Móvil Perú S.A.C. | I42: 45918 | J42: 45930 | K42: 45933 | L42: P00263 | P42: COLABORATIVA S.A.C. | Q42: -33.5 | R42: -6.03 | S42: -39.53 | T42: -39.53 | V42: PEN | W42: FALSE | X42: Pagado | AB42: Registrado | AN42: =+IF(AM42<>"",AM42,I42) -> 45918 | AO42: =+VLOOKUP(D42,validaciones_json!$AS:$AS,1,0) -> #N/A
A43: FXP/2025/10/0073 | B43: FXP/2025/10/0073 | C43: F001-00010802 | D43: 01-F001-00010802 | E43: =+IF(C43="",SUBSTITUTE(SUBSTITUTE(SUBSTITUTE(B43,CHAR(160)," ")," -","-"),"- ","-"),SUBSTITUTE(SUBSTITUTE(SUBSTITUTE(C43,CHAR(160)," ")," -","-"),"- ","-")) -> F001-00010802 | F43: 0 | H43: SANTOFA E.I.R.L. | I43: 45929 | J43: 45930 | K43: 45932 | L43: P00251 | P43: COLABORATIVA S.A.C. | Q43: -88.81 | R43: -15.99 | S43: -104.8 | T43: -104.8 | V43: PEN | W43: FALSE | X43: Pagado | AB43: Registrado | AN43: =+IF(AM43<>"",AM43,I43) -> 45929 | AO43: =+VLOOKUP(D43,validaciones_json!$AS:$AS,1,0) -> #N/A
A44: FXP/2025/10/0069 | B44: FXP/2025/10/0069 | C44: F21U-00028676 | D44: 01-F21U-00028676 | E44: =+IF(C44="",SUBSTITUTE(SUBSTITUTE(SUBSTITUTE(B44,CHAR(160)," ")," -","-"),"- ","-"),SUBSTITUTE(SUBSTITUTE(SUBSTITUTE(C44,CHAR(160)," ")," -","-"),"- ","-")) -> F21U-00028676 | F44: 0 | H44: COESTI SA | I44: 45924 | J44: 45930 | K44: 45924 | N44: F21U-00028676 | P44: COLABORATIVA S.A.C. | Q44: -73.89 | S44: -73.89 | T44: -73.89 | V44: PEN | W44: FALSE | X44: Pagado | AB44: Registrado | AN44: =+IF(AM44<>"",AM44,I44) -> 45924 | AO44: =+VLOOKUP(D44,validaciones_json!$AS:$AS,1,0) -> #N/A
A45: FXP/2025/10/0068 | B45: FXP/2025/10/0068 | C45: F18U-00070549 | D45: 01-F18U-00070549 | E45: =+IF(C45="",SUBSTITUTE(SUBSTITUTE(SUBSTITUTE(B45,CHAR(160)," ")," -","-"),"- ","-"),SUBSTITUTE(SUBSTITUTE(SUBSTITUTE(C45,CHAR(160)," ")," -","-"),"- ","-")) -> F18U-00070549 | F45: 0 | H45: COESTI SA | I45: 45924 | J45: 45930 | K45: 45924 | N45: F18U-00070549 | P45: COLABORATIVA S.A.C. | Q45: -183.65 | S45: -183.65 | T45: -183.65 | V45: PEN | W45: FALSE | X45: Pagado | AB45: Registrado | AN45: =+IF(AM45<>"",AM45,I45) -> 45924 | AO45: =+VLOOKUP(D45,validaciones_json!$AS:$AS,1,0) -> #N/A
A46: FXP/2025/10/0066 | B46: FXP/2025/10/0066 | C46: FS01-00002899 | D46: 01-FS01-00002899 | E46: =+IF(C46="",SUBSTITUTE(SUBSTITUTE(SUBSTITUTE(B46,CHAR(160)," ")," -","-"),"- ","-"),SUBSTITUTE(SUBSTITUTE(SUBSTITUTE(C46,CHAR(160)," ")," -","-"),"- ","-")) -> FS01-00002899 | F46: 0 | H46: TOOL STORE PERU E.I.R.L. | I46: 45929 | J46: 45930 | K46: 45931 | L46: P00255 | P46: COLABORATIVA S.A.C. | Q46: -64.4 | R46: -11.59 | S46: -75.99 | T46: -75.99 | V46: PEN | W46: FALSE | X46: Pagado | AB46: Registrado | AN46: =+IF(AM46<>"",AM46,I46) -> 45929 | AO46: =+VLOOKUP(D46,validaciones_json!$AS:$AS,1,0) -> #N/A
A47: FXP/2025/10/0065 | B47: FXP/2025/10/0065 | C47: F001-00009648 | D47: 01-F001-00009648 | E47: =+IF(C47="",SUBSTITUTE(SUBSTITUTE(SUBSTITUTE(B47,CHAR(160)," ")," -","-"),"- ","-"),SUBSTITUTE(SUBSTITUTE(SUBSTITUTE(C47,CHAR(160)," ")," -","-"),"- ","-")) -> F001-00009648 | F47: 0 | H47: PROLIDER EMPRESARIAL S.AC. | I47: 45918 | J47: 45930 | K47: 45918 | N47: F001-00009648 | P47: COLABORATIVA S.A.C. | Q47: -783.4 | S47: -783.4 | T47: -783.4 | V47: PEN | W47: FALSE | X47: Pagado | AB47: Registrado | AN47: =+IF(AM47<>"",AM47,I47) -> 45918 | AO47: =+VLOOKUP(D47,validaciones_json!$AS:$AS,1,0) -> #N/A
A48: FXP/2025/10/0061 | B48: FXP/2025/10/0061 | C48: F121-00003530 | D48: 01-F121-00003530 | E48: =+IF(C48="",SUBSTITUTE(SUBSTITUTE(SUBSTITUTE(B48,CHAR(160)," ")," -","-"),"- ","-"),SUBSTITUTE(SUBSTITUTE(SUBSTITUTE(C48,CHAR(160)," ")," -","-"),"- ","-")) -> F121-00003530 | F48: 0 | H48: YOPO S.A.C. | I48: 45930 | J48: 45930 | K48: 45930 | P48: COLABORATIVA S.A.C. | Q48: -30 | S48: -30 | T48: -30 | V48: PEN | W48: FALSE | X48: Pagado | AB48: Registrado | AN48: =+IF(AM48<>"",AM48,I48) -> 45930 | AO48: =+VLOOKUP(D48,validaciones_json!$AS:$AS,1,0) -> #N/A
A49: FXP/2025/09/0045 | B49: FXP/2025/09/0045 | C49: F021-00005320 | D49: 01-F021-00005320 | E49: =+IF(C49="",SUBSTITUTE(SUBSTITUTE(SUBSTITUTE(B49,CHAR(160)," ")," -","-"),"- ","-"),SUBSTITUTE(SUBSTITUTE(SUBSTITUTE(C49,CHAR(160)," ")," -","-"),"- ","-")) -> F021-00005320 | F49: 0 | H49: YOPO S.A.C. | I49: 45900 | J49: 45930 | K49: 45900 | N49: F021-00005320 | P49: COLABORATIVA S.A.C. | Q49: -86 | S49: -86 | T49: -86 | V49: PEN | W49: FALSE | X49: Pagado | AB49: Registrado | AN49: =+IF(AM49<>"",AM49,I49) -> 45900 | AO49: =+VLOOKUP(D49,validaciones_json!$AS:$AS,1,0) -> #N/A
A50: FXP/2025/09/0044 | B50: FXP/2025/09/0044 | C50: F001-00007397 | D50: 01-F001-00007397 | E50: =+IF(C50="",SUBSTITUTE(SUBSTITUTE(SUBSTITUTE(B50,CHAR(160)," ")," -","-"),"- ","-"),SUBSTITUTE(SUBSTITUTE(SUBSTITUTE(C50,CHAR(160)," ")," -","-"),"- ","-")) -> F001-00007397 | F50: 0 | H50: SANKY 10 S.A.C | I50: 45918 | J50: 45930 | K50: 45918 | N50: F001-00007397 | P50: COLABORATIVA S.A.C. | Q50: -20.9 | S50: -20.9 | T50: -20.9 | V50: PEN | W50: FALSE | X50: Pagado | AB50: Registrado | AN50: =+IF(AM50<>"",AM50,I50) -> 45918 | AO50: =+VLOOKUP(D50,validaciones_json!$AS:$AS,1,0) -> #N/A
A51: FXP/2025/09/0043 | B51: FXP/2025/09/0043 | C51: F001-00002213 | D51: 01-F001-00002213 | E51: =+IF(C51="",SUBSTITUTE(SUBSTITUTE(SUBSTITUTE(B51,CHAR(160)," ")," -","-"),"- ","-"),SUBSTITUTE(SUBSTITUTE(SUBSTITUTE(C51,CHAR(160)," ")," -","-"),"- ","-")) -> F001-00002213 | F51: 0 | H51: REPRESENTACIONES ALEXIA S.A.C. | I51: 45929 | J51: 45930 | K51: 45929 | N51: F001-2213 | P51: COLABORATIVA S.A.C. | Q51: -104 | S51: -104 | T51: -104 | V51: PEN | W51: FALSE | X51: Pagado | AB51: Registrado | AN51: =+IF(AM51<>"",AM51,I51) -> 45929 | AO51: =+VLOOKUP(D51,validaciones_json!$AS:$AS,1,0) -> #N/A
A52: FXP/2025/09/0042 | B52: FXP/2025/09/0042 | C52: FC03-00086728 | D52: 01-FC03-00086728 | E52: =+IF(C52="",SUBSTITUTE(SUBSTITUTE(SUBSTITUTE(B52,CHAR(160)," ")," -","-"),"- ","-"),SUBSTITUTE(SUBSTITUTE(SUBSTITUTE(C52,CHAR(160)," ")," -","-"),"- ","-")) -> FC03-00086728 | F52: 0 | H52: GRIFO SAN IGNACIO S.A.C. | I52: 45924 | J52: 45930 | K52: 45924 | N52: FC03-0086728 | P52: COLABORATIVA S.A.C. | Q52: -181.26 | S52: -181.26 | T52: -181.26 | V52: PEN | W52: FALSE | X52: Pagado | AB52: Registrado | AN52: =+IF(AM52<>"",AM52,I52) -> 45924 | AO52: =+VLOOKUP(D52,validaciones_json!$AS:$AS,1,0) -> #N/A
A53: FXP/2025/09/0041 | B53: FXP/2025/09/0041 | C53: FC01-00132753 | D53: 01-FC01-00132753 | E53: =+IF(C53="",SUBSTITUTE(SUBSTITUTE(SUBSTITUTE(B53,CHAR(160)," ")," -","-"),"- ","-"),SUBSTITUTE(SUBSTITUTE(SUBSTITUTE(C53,CHAR(160)," ")," -","-"),"- ","-")) -> FC01-00132753 | F53: 0 | H53: GRIFO SAN IGNACIO S.A.C. | I53: 45910 | J53: 45930 | K53: 45910 | N53: FC01-0132753 | P53: COLABORATIVA S.A.C. | Q53: -198.93 | S53: -198.93 | T53: -198.93 | V53: PEN | W53: FALSE | X53: Pagado | AB53: Registrado | AN53: =+IF(AM53<>"",AM53,I53) -> 45910 | AO53: =+VLOOKUP(D53,validaciones_json!$AS:$AS,1,0) -> #N/A
A54: FXP/2025/10/0072 | B54: FXP/2025/10/0072 | C54: E001-00000122 | D54: 01-E001-00000122 | E54: =+IF(C54="",SUBSTITUTE(SUBSTITUTE(SUBSTITUTE(B54,CHAR(160)," ")," -","-"),"- ","-"),SUBSTITUTE(SUBSTITUTE(SUBSTITUTE(C54,CHAR(160)," ")," -","-"),"- ","-")) -> E001-00000122 | F54: 0 | H54: MUÑOZ VERANO JOHN BRACKSON | I54: 45929 | J54: 45929 | K54: 45930 | L54: P00257 | P54: COLABORATIVA S.A.C. | Q54: -2470 | R54: -444.6 | S54: -2914.6 | T54: -2914.6 | V54: PEN | W54: FALSE | X54: Pagado | AB54: Registrado | AN54: =+IF(AM54<>"",AM54,I54) -> 45929 | AO54: =+VLOOKUP(D54,validaciones_json!$AS:$AS,1,0) -> #N/A
A55: FXP/2025/09/0046 | B55: FXP/2025/09/0046 | C55: E001-00000063 | D55: 02-E001-00000063 | E55: =+IF(C55="",SUBSTITUTE(SUBSTITUTE(SUBSTITUTE(B55,CHAR(160)," ")," -","-"),"- ","-"),SUBSTITUTE(SUBSTITUTE(SUBSTITUTE(C55,CHAR(160)," ")," -","-"),"- ","-")) -> E001-00000063 | F55: 0 | H55: VENTURA SABINO MIGUEL ANGEL | I55: 45929 | J55: 45929 | K55: 45929 | L55: P00252 | N55: E001-63 | P55: COLABORATIVA S.A.C. | Q55: -2400 | S55: -2400 | T55: -2400 | V55: PEN | W55: FALSE | X55: Pagado | AB55: Registrado | AN55: =+IF(AM55<>"",AM55,I55) -> 45929 | AO55: =+VLOOKUP(D55,validaciones_json!$AS:$AS,1,0) -> #N/A
A56: FXP/2025/09/0036 | B56: FXP/2025/09/0036 | C56: E001-00000073 | D56: 02-E001-00000073 | E56: =+IF(C56="",SUBSTITUTE(SUBSTITUTE(SUBSTITUTE(B56,CHAR(160)," ")," -","-"),"- ","-"),SUBSTITUTE(SUBSTITUTE(SUBSTITUTE(C56,CHAR(160)," ")," -","-"),"- ","-")) -> E001-00000073 | F56: 0 | H56: MARCAS TUPALAYA VICTOR ALBERTO | I56: 45929 | J56: 45929 | K56: 45930 | L56: P00258 | N56: E001-73 | P56: COLABORATIVA S.A.C. | Q56: -594.59 | R56: 47.57 | S56: -547.02 | T56: -547.02 | V56: PEN | W56: FALSE | X56: Pagado | AB56: Registrado | AN56: =+IF(AM56<>"",AM56,I56) -> 45929 | AO56: =+VLOOKUP(D56,validaciones_json!$AS:$AS,1,0) -> #N/A
A57: FXP/2025/09/0035 | B57: FXP/2025/09/0035 | C57: E001-00000537 | D57: 01-E001-00000537 | E57: =+IF(C57="",SUBSTITUTE(SUBSTITUTE(SUBSTITUTE(B57,CHAR(160)," ")," -","-"),"- ","-"),SUBSTITUTE(SUBSTITUTE(SUBSTITUTE(C57,CHAR(160)," ")," -","-"),"- ","-")) -> E001-00000537 | F57: 0 | H57: CATORCE & SEIS S.A.C. | I57: 45929 | J57: 45929 | K57: 45930 | L57: P00256 | P57: COLABORATIVA S.A.C. | Q57: -12677.65 | R57: -2281.98 | S57: -14959.63 | T57: -14959.63 | V57: PEN | W57: FALSE | X57: Pagado | AB57: Registrado | AN57: =+IF(AM57<>"",AM57,I57) -> 45929 | AO57: =+VLOOKUP(D57,validaciones_json!$AS:$AS,1,0) -> #N/A
A58: FXP/2025/09/0034 | B58: FXP/2025/09/0034 | C58: F017-00003599 | D58: 01-F017-00003599 | E58: =+IF(C58="",SUBSTITUTE(SUBSTITUTE(SUBSTITUTE(B58,CHAR(160)," ")," -","-"),"- ","-"),SUBSTITUTE(SUBSTITUTE(SUBSTITUTE(C58,CHAR(160)," ")," -","-"),"- ","-")) -> F017-00003599 | F58: 0 | H58: DELIBAKERY PERU S.A.C. | I58: 45908 | J58: 45929 | K58: 45908 | N58: F017-3599 | P58: COLABORATIVA S.A.C. | Q58: -141.5 | S58: -141.5 | T58: -141.5 | V58: PEN | W58: FALSE | X58: Pagado | AB58: Registrado | AN58: =+IF(AM58<>"",AM58,I58) -> 45908 | AO58: =+VLOOKUP(D58,validaciones_json!$AS:$AS,1,0) -> #N/A
A59: FXP/2025/09/0033 | B59: FXP/2025/09/0033 | C59: F814-00044499 | D59: 01-F814-00044499 | E59: =+IF(C59="",SUBSTITUTE(SUBSTITUTE(SUBSTITUTE(B59,CHAR(160)," ")," -","-"),"- ","-"),SUBSTITUTE(SUBSTITUTE(SUBSTITUTE(C59,CHAR(160)," ")," -","-"),"- ","-")) -> F814-00044499 | F59: 0 | H59: Repsol Comercial S.A.C. | I59: 45906 | J59: 45929 | K59: 45906 | N59: F814-00044499 | P59: COLABORATIVA S.A.C. | Q59: -241.11 | S59: -241.11 | T59: -241.11 | V59: PEN | W59: FALSE | X59: Pagado | AB59: Registrado | AN59: =+IF(AM59<>"",AM59,I59) -> 45906 | AO59: =+VLOOKUP(D59,validaciones_json!$AS:$AS,1,0) -> #N/A
A60: FXP/2025/09/0032 | B60: FXP/2025/09/0032 | C60: F101-00106453 | D60: 01-F101-00106453 | E60: =+IF(C60="",SUBSTITUTE(SUBSTITUTE(SUBSTITUTE(B60,CHAR(160)," ")," -","-"),"- ","-"),SUBSTITUTE(SUBSTITUTE(SUBSTITUTE(C60,CHAR(160)," ")," -","-"),"- ","-")) -> F101-00106453 | F60: 0 | H60: TERTISA COMBUSTIBLES S.A. | I60: 45906 | J60: 45929 | K60: 45906 | N60: F101-00106453 | P60: COLABORATIVA S.A.C. | Q60: -64 | S60: -64 | T60: -64 | V60: PEN | W60: FALSE | X60: Pagado | AB60: Registrado | AN60: =+IF(AM60<>"",AM60,I60) -> 45906 | AO60: =+VLOOKUP(D60,validaciones_json!$AS:$AS,1,0) -> #N/A
A61: FXP/2025/09/0028 | B61: FXP/2025/09/0028 | C61: FR02-00001013 | D61: 01-FR02-00001013 | E61: =+IF(C61="",SUBSTITUTE(SUBSTITUTE(SUBSTITUTE(B61,CHAR(160)," ")," -","-"),"- ","-"),SUBSTITUTE(SUBSTITUTE(SUBSTITUTE(C61,CHAR(160)," ")," -","-"),"- ","-")) -> FR02-00001013 | F61: 0 | H61: FRANQUICIAS ALIMENTARIAS S.A. | I61: 45915 | J61: 45929 | K61: 45915 | N61: FR02-00001013 | P61: COLABORATIVA S.A.C. | Q61: -59.8 | S61: -59.8 | T61: -59.8 | V61: PEN | W61: FALSE | X61: Pagado | AB61: Registrado | AN61: =+IF(AM61<>"",AM61,I61) -> 45915 | AO61: =+VLOOKUP(D61,validaciones_json!$AS:$AS,1,0) -> #N/A
A62: FXP/2025/09/0027 | B62: FXP/2025/09/0027 | C62: F021-00005380 | D62: 01-F021-00005380 | E62: =+IF(C62="",SUBSTITUTE(SUBSTITUTE(SUBSTITUTE(B62,CHAR(160)," ")," -","-"),"- ","-"),SUBSTITUTE(SUBSTITUTE(SUBSTITUTE(C62,CHAR(160)," ")," -","-"),"- ","-")) -> F021-00005380 | F62: 0 | H62: YOPO S.A.C. | I62: 45910 | J62: 45929 | K62: 45910 | N62: F021-00005380 | P62: COLABORATIVA S.A.C. | Q62: -30 | S62: -30 | T62: -30 | V62: PEN | W62: FALSE | X62: Pagado | AB62: Registrado | AN62: =+IF(AM62<>"",AM62,I62) -> 45910 | AO62: =+VLOOKUP(D62,validaciones_json!$AS:$AS,1,0) -> #N/A
A63: FXP/2025/09/0026 | B63: FXP/2025/09/0026 | C63: F003-00007219 | D63: 01-F003-00007219 | E63: =+IF(C63="",SUBSTITUTE(SUBSTITUTE(SUBSTITUTE(B63,CHAR(160)," ")," -","-"),"- ","-"),SUBSTITUTE(SUBSTITUTE(SUBSTITUTE(C63,CHAR(160)," ")," -","-"),"- ","-")) -> F003-00007219 | F63: 0 | H63: COCINA TRUJILLANA SAC | I63: 45916 | J63: 45929 | K63: 45916 | N63: F003-7219 | P63: COLABORATIVA S.A.C. | Q63: -276 | S63: -276 | T63: -276 | V63: PEN | W63: FALSE | X63: Pagado | AB63: Registrado | AN63: =+IF(AM63<>"",AM63,I63) -> 45916 | AO63: =+VLOOKUP(D63,validaciones_json!$AS:$AS,1,0) -> #N/A
A64: FXP/2025/09/0022 | B64: FXP/2025/09/0022 | C64: FI25-00017305 | D64: 01-FI25-00017305 | E64: =+IF(C64="",SUBSTITUTE(SUBSTITUTE(SUBSTITUTE(B64,CHAR(160)," ")," -","-"),"- ","-"),SUBSTITUTE(SUBSTITUTE(SUBSTITUTE(C64,CHAR(160)," ")," -","-"),"- ","-")) -> FI25-00017305 | F64: 0 | H64: MEMORY KINGS PERU S.A.C | I64: 45926 | J64: 45926 | K64: 45926 | L64: P00247 | P64: COLABORATIVA S.A.C. | Q64: -538.14 | R64: -96.86 | S64: -635 | T64: -635 | V64: PEN | W64: FALSE | X64: Pagado | AB64: Registrado | AN64: =+IF(AM64<>"",AM64,I64) -> 45926 | AO64: =+VLOOKUP(D64,validaciones_json!$AS:$AS,1,0) -> #N/A
A65: FXP/2025/09/0016 | B65: FXP/2025/09/0016 | C65: FF29-00003107 | D65: 01-FF29-00003107 | E65: =+IF(C65="",SUBSTITUTE(SUBSTITUTE(SUBSTITUTE(B65,CHAR(160)," ")," -","-"),"- ","-"),SUBSTITUTE(SUBSTITUTE(SUBSTITUTE(C65,CHAR(160)," ")," -","-"),"- ","-")) -> FF29-00003107 | F65: 0 | H65: Verisure Peru SAC | I65: 45924 | J65: 45926 | K65: 45926 | P65: COLABORATIVA S.A.C. | Q65: -168.64 | R65: -30.36 | S65: -199 | T65: -199 | V65: PEN | W65: FALSE | X65: Pagado | AB65: Registrado | AN65: =+IF(AM65<>"",AM65,I65) -> 45924 | AO65: =+VLOOKUP(D65,validaciones_json!$AS:$AS,1,0) -> #N/A
A66: FXP/2025/09/0015 | B66: FXP/2025/09/0015 | C66: FE29-00025243 | D66: 01-FE29-00025243 | E66: =+IF(C66="",SUBSTITUTE(SUBSTITUTE(SUBSTITUTE(B66,CHAR(160)," ")," -","-"),"- ","-"),SUBSTITUTE(SUBSTITUTE(SUBSTITUTE(C66,CHAR(160)," ")," -","-"),"- ","-")) -> FE29-00025243 | F66: 0 | H66: Verisure Peru SAC | I66: 45924 | J66: 45926 | K66: 45926 | P66: COLABORATIVA S.A.C. | Q66: -87.29 | R66: -15.71 | S66: -103 | T66: -103 | V66: PEN | W66: FALSE | X66: Pagado | AB66: Registrado | AN66: =+IF(AM66<>"",AM66,I66) -> 45924 | AO66: =+VLOOKUP(D66,validaciones_json!$AS:$AS,1,0) -> #N/A
A67: FXP/2025/09/0037 | B67: FXP/2025/09/0037 | C67: E001-00000136 | D67: 01-E001-00000136 | E67: =+IF(C67="",SUBSTITUTE(SUBSTITUTE(SUBSTITUTE(B67,CHAR(160)," ")," -","-"),"- ","-"),SUBSTITUTE(SUBSTITUTE(SUBSTITUTE(C67,CHAR(160)," ")," -","-"),"- ","-")) -> E001-00000136 | F67: 0 | H67: CORPORACION LINCOSUR E.I.R.L. | I67: 45925 | J67: 45925 | K67: 45930 | P67: COLABORATIVA S.A.C. | Q67: -422.88 | R67: -76.12 | S67: -499 | T67: -499 | V67: PEN | W67: FALSE | X67: Pagado | AB67: Registrado | AN67: =+IF(AM67<>"",AM67,I67) -> 45925 | AO67: =+VLOOKUP(D67,validaciones_json!$AS:$AS,1,0) -> #N/A
A68: FXP/2025/09/0018 | B68: FXP/2025/09/0018 | C68: FRE1-00007301 | D68: 01-FRE1-00007301 | E68: =+IF(C68="",SUBSTITUTE(SUBSTITUTE(SUBSTITUTE(B68,CHAR(160)," ")," -","-"),"- ","-"),SUBSTITUTE(SUBSTITUTE(SUBSTITUTE(C68,CHAR(160)," ")," -","-"),"- ","-")) -> FRE1-00007301 | F68: 0 | H68: RASH PERU SRL | I68: 45925 | J68: 45925 | K68: 45926 | P68: COLABORATIVA S.A.C. | Q68: -33.73 | R68: -6.07 | S68: -39.8 | T68: -39.8 | V68: PEN | W68: FALSE | X68: Pagado | AB68: Registrado | AN68: =+IF(AM68<>"",AM68,I68) -> 45925 | AO68: =+VLOOKUP(D68,validaciones_json!$AS:$AS,1,0) -> #N/A
A69: FXP/2025/09/0017 | B69: FXP/2025/09/0017 | C69: F448-00023557 | D69: 01-F448-00023557 | E69: =+IF(C69="",SUBSTITUTE(SUBSTITUTE(SUBSTITUTE(B69,CHAR(160)," ")," -","-"),"- ","-"),SUBSTITUTE(SUBSTITUTE(SUBSTITUTE(C69,CHAR(160)," ")," -","-"),"- ","-")) -> F448-00023557 | F69: 0 | H69: TIENDAS DEL MEJORAMIENTO DEL HOGAR S.A. | I69: 45925 | J69: 45925 | K69: 45926 | P69: COLABORATIVA S.A.C. | Q69: -575.98 | R69: -103.68 | S69: -679.66 | T69: -679.66 | V69: PEN | W69: FALSE | X69: Pagado | AB69: Registrado | AN69: =+IF(AM69<>"",AM69,I69) -> 45925 | AO69: =+VLOOKUP(D69,validaciones_json!$AS:$AS,1,0) -> #N/A
A70: FXP/2025/09/0013 | B70: FXP/2025/09/0013 | C70: F121-00003365 | D70: 01-F121-00003365 | E70: =+IF(C70="",SUBSTITUTE(SUBSTITUTE(SUBSTITUTE(B70,CHAR(160)," ")," -","-"),"- ","-"),SUBSTITUTE(SUBSTITUTE(SUBSTITUTE(C70,CHAR(160)," ")," -","-"),"- ","-")) -> F121-00003365 | F70: 0 | H70: YOPO S.A.C. | I70: 45917 | J70: 45925 | K70: 45917 | N70: F121-00003365 | P70: COLABORATIVA S.A.C. | Q70: -30 | S70: -30 | T70: -30 | V70: PEN | W70: FALSE | X70: Pagado | AB70: Registrado | AN70: =+IF(AM70<>"",AM70,I70) -> 45917 | AO70: =+VLOOKUP(D70,validaciones_json!$AS:$AS,1,0) -> #N/A
A71: FXP/2025/09/0012 | B71: FXP/2025/09/0012 | C71: F121-00003401 | D71: 01-F121-00003401 | E71: =+IF(C71="",SUBSTITUTE(SUBSTITUTE(SUBSTITUTE(B71,CHAR(160)," ")," -","-"),"- ","-"),SUBSTITUTE(SUBSTITUTE(SUBSTITUTE(C71,CHAR(160)," ")," -","-"),"- ","-")) -> F121-00003401 | F71: 0 | H71: YOPO S.A.C. | I71: 45919 | J71: 45925 | K71: 45919 | N71: F121-00003401 | P71: COLABORATIVA S.A.C. | Q71: -30 | S71: -30 | T71: -30 | V71: PEN | W71: FALSE | X71: Pagado | AB71: Registrado | AN71: =+IF(AM71<>"",AM71,I71) -> 45919 | AO71: =+VLOOKUP(D71,validaciones_json!$AS:$AS,1,0) -> #N/A
A72: FXP/2025/09/0010 | B72: FXP/2025/09/0010 | C72: F001-00009925 | D72: 01-F001-00009925 | E72: =+IF(C72="",SUBSTITUTE(SUBSTITUTE(SUBSTITUTE(B72,CHAR(160)," ")," -","-"),"- ","-"),SUBSTITUTE(SUBSTITUTE(SUBSTITUTE(C72,CHAR(160)," ")," -","-"),"- ","-")) -> F001-00009925 | F72: 0 | H72: SP SABORES PERUANOS EIRL | I72: 45919 | J72: 45925 | K72: 45919 | N72: F001-00009925 | P72: COLABORATIVA S.A.C. | Q72: -217 | S72: -217 | T72: -217 | V72: PEN | W72: FALSE | X72: Pagado | AB72: Registrado | AN72: =+IF(AM72<>"",AM72,I72) -> 45919 | AO72: =+VLOOKUP(D72,validaciones_json!$AS:$AS,1,0) -> #N/A
A73: FXP/2025/09/0009 | B73: FXP/2025/09/0009 | C73: F100-00008599 | D73: 01-F100-00008599 | E73: =+IF(C73="",SUBSTITUTE(SUBSTITUTE(SUBSTITUTE(B73,CHAR(160)," ")," -","-"),"- ","-"),SUBSTITUTE(SUBSTITUTE(SUBSTITUTE(C73,CHAR(160)," ")," -","-"),"- ","-")) -> F100-00008599 | F73: 0 | H73: NEGOCIOS GASTRONOMICOS SANTOS EIRL | I73: 45911 | J73: 45925 | K73: 45911 | N73: F100-8599 | P73: COLABORATIVA S.A.C. | Q73: -238.98 | R73: -43.02 | S73: -282 | T73: -282 | V73: PEN | W73: FALSE | X73: Pagado | AB73: Registrado | AN73: =+IF(AM73<>"",AM73,I73) -> 45911 | AO73: =+VLOOKUP(D73,validaciones_json!$AS:$AS,1,0) -> #N/A
A74: FXP/2025/09/0024 | B74: FXP/2025/09/0024 | C74: E001-00000283 | D74: 01-E001-00000283 | E74: =+IF(C74="",SUBSTITUTE(SUBSTITUTE(SUBSTITUTE(B74,CHAR(160)," ")," -","-"),"- ","-"),SUBSTITUTE(SUBSTITUTE(SUBSTITUTE(C74,CHAR(160)," ")," -","-"),"- ","-")) -> E001-00000283 | F74: 0 | H74: JEMKA & ASOCIADOS S.A.C. | I74: 45924 | J74: 45924 | K74: 45926 | L74: P00250 | P74: COLABORATIVA S.A.C. | Q74: -1500 | R74: -270 | S74: -1770 | T74: -1770 | V74: PEN | W74: FALSE | X74: Pagado | AB74: Registrado | AN74: =+IF(AM74<>"",AM74,I74) -> 45924 | AO74: =+VLOOKUP(D74,validaciones_json!$AS:$AS,1,0) -> #N/A
A75: FXP/2025/09/0023 | B75: FXP/2025/09/0023 | C75: E001-00000285 | D75: 01-E001-00000285 | E75: =+IF(C75="",SUBSTITUTE(SUBSTITUTE(SUBSTITUTE(B75,CHAR(160)," ")," -","-"),"- ","-"),SUBSTITUTE(SUBSTITUTE(SUBSTITUTE(C75,CHAR(160)," ")," -","-"),"- ","-")) -> E001-00000285 | F75: 0 | H75: JEMKA & ASOCIADOS S.A.C. | I75: 45924 | J75: 45924 | K75: 45926 | L75: P00249 | P75: COLABORATIVA S.A.C. | Q75: -200 | R75: -36 | S75: -236 | T75: -236 | V75: PEN | W75: FALSE | X75: Pagado | AB75: Registrado | AN75: =+IF(AM75<>"",AM75,I75) -> 45924 | AO75: =+VLOOKUP(D75,validaciones_json!$AS:$AS,1,0) -> #N/A
A76: FXP/2025/09/0004 | B76: FXP/2025/09/0004 | C76: F003-00000798 | D76: 01-F003-00000798 | E76: =+IF(C76="",SUBSTITUTE(SUBSTITUTE(SUBSTITUTE(B76,CHAR(160)," ")," -","-"),"- ","-"),SUBSTITUTE(SUBSTITUTE(SUBSTITUTE(C76,CHAR(160)," ")," -","-"),"- ","-")) -> F003-00000798 | F76: 0 | H76: MALBEC SAC | I76: 45904 | J76: 45924 | K76: 45904 | N76: F003-00000798 | P76: COLABORATIVA S.A.C. | Q76: -444 | S76: -444 | T76: -444 | V76: PEN | W76: FALSE | X76: Pagado | AB76: Registrado | AN76: =+IF(AM76<>"",AM76,I76) -> 45904 | AO76: =+VLOOKUP(D76,validaciones_json!$AS:$AS,1,0) -> #N/A
A77: FXP/2025/09/0003 | B77: FXP/2025/09/0003 | C77: F004-00001249 | D77: 01-F004-00001249 | E77: =+IF(C77="",SUBSTITUTE(SUBSTITUTE(SUBSTITUTE(B77,CHAR(160)," ")," -","-"),"- ","-"),SUBSTITUTE(SUBSTITUTE(SUBSTITUTE(C77,CHAR(160)," ")," -","-"),"- ","-")) -> F004-00001249 | F77: 0 | H77: ORIENTAL GOURMET S.A. | I77: 45923 | J77: 45924 | K77: 45923 | N77: F004-1249 | P77: COLABORATIVA S.A.C. | Q77: -52.97 | R77: -9.53 | S77: -62.5 | T77: -62.5 | V77: PEN | W77: FALSE | X77: Pagado | AB77: Registrado | AN77: =+IF(AM77<>"",AM77,I77) -> 45923 | AO77: =+VLOOKUP(D77,validaciones_json!$AS:$AS,1,0) -> #N/A
A78: FXP/2025/09/0006 | B78: FXP/2025/09/0006 | C78: E001-00000020 | D78: 01-E001-00000020 | E78: =+IF(C78="",SUBSTITUTE(SUBSTITUTE(SUBSTITUTE(B78,CHAR(160)," ")," -","-"),"- ","-"),SUBSTITUTE(SUBSTITUTE(SUBSTITUTE(C78,CHAR(160)," ")," -","-"),"- ","-")) -> E001-00000020 | F78: 0 | H78: PRINTMATE2.0 E.I.R.L. | I78: 45923 | J78: 45923 | K78: 45923 | L78: P00242 | P78: COLABORATIVA S.A.C. | Q78: -456 | R78: -82.08 | S78: -538.08 | T78: -538.08 | V78: PEN | W78: FALSE | X78: Pagado | AB78: Registrado | AN78: =+IF(AM78<>"",AM78,I78) -> 45923 | AO78: =+VLOOKUP(D78,validaciones_json!$AS:$AS,1,0) -> #N/A
A79: FXP/2025/09/0001 | B79: FXP/2025/09/0001 | C79: E001-00000061 | D79: 02-E001-00000061 | E79: =+IF(C79="",SUBSTITUTE(SUBSTITUTE(SUBSTITUTE(B79,CHAR(160)," ")," -","-"),"- ","-"),SUBSTITUTE(SUBSTITUTE(SUBSTITUTE(C79,CHAR(160)," ")," -","-"),"- ","-")) -> E001-00000061 | F79: 0 | H79: VENTURA SABINO MIGUEL ANGEL | I79: 45923 | J79: 45923 | K79: 45923 | L79: P00241 | P79: COLABORATIVA S.A.C. | Q79: -560 | S79: -560 | T79: -560 | V79: PEN | W79: FALSE | X79: Pagado | AB79: Registrado | AN79: =+IF(AM79<>"",AM79,I79) -> 45923 | AO79: =+VLOOKUP(D79,validaciones_json!$AS:$AS,1,0) -> #N/A
A80: R E001-00000015 | B80: R E001-00000015 | D80: 02- | E80: =+IF(C80="",SUBSTITUTE(SUBSTITUTE(SUBSTITUTE(B80,CHAR(160)," ")," -","-"),"- ","-"),SUBSTITUTE(SUBSTITUTE(SUBSTITUTE(C80,CHAR(160)," ")," -","-"),"- ","-")) -> R E001-00000015 | F80: 0 | H80: SALVADOR ARNALDO REYES CHUECAS | I80: 45919 | J80: 45919 | K80: 45919 | L80: P00236 | P80: COLABORATIVA S.A.C. | Q80: -1317.5 | S80: -1317.5 | T80: -1317.5 | U80: -1317.5 | V80: PEN | W80: FALSE | X80: Sin pagar | AB80: Registrado | AN80: =+IF(AM80<>"",AM80,I80) -> 45919 | AO80: =+VLOOKUP(D80,validaciones_json!$AS:$AS,1,0) -> #N/A
A81: FXP/2025/10/0056 | B81: NÂ° F001-00009566 | C81: NÂ° F001-00009566 | D81: 01-N° F001-00009566 | E81: =+IF(C81="",SUBSTITUTE(SUBSTITUTE(SUBSTITUTE(B81,CHAR(160)," ")," -","-"),"- ","-"),SUBSTITUTE(SUBSTITUTE(SUBSTITUTE(C81,CHAR(160)," ")," -","-"),"- ","-")) -> NÂ° F001-00009566 | F81: 0 | H81: PRECINTOS PERU E.I.R.L | I81: 45919 | J81: 45919 | K81: 45919 | L81: P00238 | P81: COLABORATIVA S.A.C. | Q81: -2394.09 | R81: -430.91 | S81: -2825 | T81: -2825 | V81: PEN | W81: FALSE | X81: Pagado | AB81: Registrado | AN81: =+IF(AM81<>"",AM81,I81) -> 45919 | AO81: =+VLOOKUP(D81,validaciones_json!$AS:$AS,1,0) -> #N/A
A82: FXP/2025/09/0005 | B82: FXP/2025/09/0005 | C82: F315-00455032 | D82: 01-F315-00455032 | E82: =+IF(C82="",SUBSTITUTE(SUBSTITUTE(SUBSTITUTE(B82,CHAR(160)," ")," -","-"),"- ","-"),SUBSTITUTE(SUBSTITUTE(SUBSTITUTE(C82,CHAR(160)," ")," -","-"),"- ","-")) -> F315-00455032 | F82: 0 | H82: CENCOSUD RETAIL PERU S.A. | I82: 45919 | J82: 45919 | K82: 45924 | L82: P00244 | P82: COLABORATIVA S.A.C. | Q82: -38.11 | R82: -6.87 | S82: -44.98 | T82: -44.98 | V82: PEN | W82: FALSE | X82: Pagado | AB82: Registrado | AN82: =+IF(AM82<>"",AM82,I82) -> 45919 | AO82: =+VLOOKUP(D82,validaciones_json!$AS:$AS,1,0) -> #N/A
A83: FXP/2025/09/0007 | B83: FXP/2025/09/0007 | C83: E001-00000118 | D83: 01-E001-00000118 | E83: =+IF(C83="",SUBSTITUTE(SUBSTITUTE(SUBSTITUTE(B83,CHAR(160)," ")," -","-"),"- ","-"),SUBSTITUTE(SUBSTITUTE(SUBSTITUTE(C83,CHAR(160)," ")," -","-"),"- ","-")) -> E001-00000118 | F83: 0 | H83: MUÑOZ VERANO JOHN BRACKSON | I83: 45918 | J83: 45918 | K83: 45922 | L83: P00237 | P83: COLABORATIVA S.A.C. | Q83: -240 | R83: -43.2 | S83: -283.2 | T83: -283.2 | V83: PEN | W83: FALSE | X83: Pagado | AB83: Registrado | AN83: =+IF(AM83<>"",AM83,I83) -> 45918 | AO83: =+VLOOKUP(D83,validaciones_json!$AS:$AS,1,0) -> #N/A
A84: F E001-00000293 | B84: F E001-00000293 | D84: 01- | E84: =+IF(C84="",SUBSTITUTE(SUBSTITUTE(SUBSTITUTE(B84,CHAR(160)," ")," -","-"),"- ","-"),SUBSTITUTE(SUBSTITUTE(SUBSTITUTE(C84,CHAR(160)," ")," -","-"),"- ","-")) -> F E001-00000293 | F84: 0 | H84: DANPRINT STUDIO (CINTHIA LISETH LOPEZ INGA) | I84: 45918 | J84: 45918 | K84: 45918 | L84: P00233 | P84: COLABORATIVA S.A.C. | Q84: -2076.27 | R84: -373.73 | S84: -2450 | T84: -2450 | V84: PEN | W84: FALSE | X84: Pagado | AB84: Registrado | AN84: =+IF(AM84<>"",AM84,I84) -> 45918 | AO84: =+VLOOKUP(D84,validaciones_json!$AS:$AS,1,0) -> #N/A
A85: FXP/2025/10/0059 | B85: FXP/2025/10/0059 | C85: F090-00187668 | D85: 01-F090-00187668 | E85: =+IF(C85="",SUBSTITUTE(SUBSTITUTE(SUBSTITUTE(B85,CHAR(160)," ")," -","-"),"- ","-"),SUBSTITUTE(SUBSTITUTE(SUBSTITUTE(C85,CHAR(160)," ")," -","-"),"- ","-")) -> F090-00187668 | F85: 0 | H85: PACIFICO COMPAÑIA DE SEGUROS Y REASEGUROS | I85: 45917 | J85: 45917 | K85: 45923 | P85: COLABORATIVA S.A.C. | Q85: -528.27 | R85: -95.08 | S85: -623.35 | T85: -178.66 | V85: USD | W85: FALSE | X85: Pagado | AB85: Registrado | AN85: =+IF(AM85<>"",AM85,I85) -> 45917 | AO85: =+VLOOKUP(D85,validaciones_json!$AS:$AS,1,0) -> #N/A
A86: FXP/2025/10/0058 | B86: FXP/2025/10/0058 | C86: F090-00187667 | D86: 01-F090-00187667 | E86: =+IF(C86="",SUBSTITUTE(SUBSTITUTE(SUBSTITUTE(B86,CHAR(160)," ")," -","-"),"- ","-"),SUBSTITUTE(SUBSTITUTE(SUBSTITUTE(C86,CHAR(160)," ")," -","-"),"- ","-")) -> F090-00187667 | F86: 0 | H86: PACIFICO COMPAÑIA DE SEGUROS Y REASEGUROS | I86: 45917 | J86: 45917 | K86: 45923 | P86: COLABORATIVA S.A.C. | Q86: -528.03 | R86: -95.04 | S86: -623.07 | T86: -178.58 | V86: USD | W86: FALSE | X86: Pagado | AB86: Registrado | AN86: =+IF(AM86<>"",AM86,I86) -> 45917 | AO86: =+VLOOKUP(D86,validaciones_json!$AS:$AS,1,0) -> #N/A
A87: FXP/2025/10/0057 | B87: FXP/2025/10/0057 | C87: F090-00187665 | D87: 01-F090-00187665 | E87: =+IF(C87="",SUBSTITUTE(SUBSTITUTE(SUBSTITUTE(B87,CHAR(160)," ")," -","-"),"- ","-"),SUBSTITUTE(SUBSTITUTE(SUBSTITUTE(C87,CHAR(160)," ")," -","-"),"- ","-")) -> F090-00187665 | F87: 0 | H87: PACIFICO COMPAÑIA DE SEGUROS Y REASEGUROS | I87: 45917 | J87: 45917 | K87: 45923 | P87: COLABORATIVA S.A.C. | Q87: -528.03 | R87: -95.04 | S87: -623.07 | T87: -178.58 | V87: USD | W87: FALSE | X87: Pagado | AB87: Registrado | AN87: =+IF(AM87<>"",AM87,I87) -> 45917 | AO87: =+VLOOKUP(D87,validaciones_json!$AS:$AS,1,0) -> #N/A
A88: FXP/2025/10/0054 | B88: FXP/2025/10/0054 | C88: F090-00187666 | D88: 01-F090-00187666 | E88: =+IF(C88="",SUBSTITUTE(SUBSTITUTE(SUBSTITUTE(B88,CHAR(160)," ")," -","-"),"- ","-"),SUBSTITUTE(SUBSTITUTE(SUBSTITUTE(C88,CHAR(160)," ")," -","-"),"- ","-")) -> F090-00187666 | F88: 0 | H88: PACIFICO COMPAÑIA DE SEGUROS Y REASEGUROS | I88: 45917 | J88: 45917 | K88: 45923 | L88: P00229 | P88: COLABORATIVA S.A.C. | Q88: -528.03 | R88: -95.04 | S88: -623.07 | T88: -178.58 | V88: USD | W88: FALSE | X88: Pagado | AB88: Registrado | AN88: =+IF(AM88<>"",AM88,I88) -> 45917 | AO88: =+VLOOKUP(D88,validaciones_json!$AS:$AS,1,0) -> #N/A
A89: F F002-00033229 | B89: F F002-00033229 | D89: 01- | E89: =+IF(C89="",SUBSTITUTE(SUBSTITUTE(SUBSTITUTE(B89,CHAR(160)," ")," -","-"),"- ","-"),SUBSTITUTE(SUBSTITUTE(SUBSTITUTE(C89,CHAR(160)," ")," -","-"),"- ","-")) -> F F002-00033229 | F89: 0 | H89: FLINK S.A.C. | I89: 45917 | J89: 45917 | K89: 45932 | L89: P00232 | P89: COLABORATIVA S.A.C. | Q89: -483.05 | R89: -86.95 | S89: -570 | T89: -570 | V89: PEN | W89: FALSE | X89: Pagado | AB89: Registrado | AN89: =+IF(AM89<>"",AM89,I89) -> 45917 | AO89: =+VLOOKUP(D89,validaciones_json!$AS:$AS,1,0) -> #N/A
A90: FXP/2025/10/0053 | B90: FXP/2025/10/0053 | C90: F002-00001533 | D90: 01-F002-00001533 | E90: =+IF(C90="",SUBSTITUTE(SUBSTITUTE(SUBSTITUTE(B90,CHAR(160)," ")," -","-"),"- ","-"),SUBSTITUTE(SUBSTITUTE(SUBSTITUTE(C90,CHAR(160)," ")," -","-"),"- ","-")) -> F002-00001533 | F90: 0 | H90: PRAGMATIC S.A.C. | I90: 45916 | J90: 45916 | K90: 45923 | L90: P00240 | P90: COLABORATIVA S.A.C. | Q90: -2550 | R90: -459 | S90: -3009 | T90: -3009 | V90: PEN | W90: FALSE | X90: Pagado | AB90: Registrado | AN90: =+IF(AM90<>"",AM90,I90) -> 45916 | AO90: =+VLOOKUP(D90,validaciones_json!$AS:$AS,1,0) -> #N/A
A91: F E001-00000038 | B91: F E001-00000038 | D91: 01- | E91: =+IF(C91="",SUBSTITUTE(SUBSTITUTE(SUBSTITUTE(B91,CHAR(160)," ")," -","-"),"- ","-"),SUBSTITUTE(SUBSTITUTE(SUBSTITUTE(C91,CHAR(160)," ")," -","-"),"- ","-")) -> F E001-00000038 | F91: 0 | H91: CANGAHUALA LETONA ELIO HUGO | I91: 45916 | J91: 45916 | K91: 45919 | L91: P00234 | P91: COLABORATIVA S.A.C. | Q91: -972.03 | R91: -174.97 | S91: -1147 | T91: -1147 | V91: PEN | W91: FALSE | X91: Pagado | AB91: Registrado | AN91: =+IF(AM91<>"",AM91,I91) -> 45916 | AO91: =+VLOOKUP(D91,validaciones_json!$AS:$AS,1,0) -> #N/A
A92: FXP/2025/09/0052 | B92: FXP/2025/09/0052 | C92: E001-00000059 | D92: 01-E001-00000059 | E92: =+IF(C92="",SUBSTITUTE(SUBSTITUTE(SUBSTITUTE(B92,CHAR(160)," ")," -","-"),"- ","-"),SUBSTITUTE(SUBSTITUTE(SUBSTITUTE(C92,CHAR(160)," ")," -","-"),"- ","-")) -> E001-00000059 | F92: 0 | H92: GARRIDO ROJAS GREGORY OMAR | I92: 45915 | J92: 45915 | K92: 45915 | L92: P00223 | P92: COLABORATIVA S.A.C. | Q92: -430 | S92: -430 | T92: -430 | V92: PEN | W92: FALSE | X92: Pagado | AB92: Registrado | AN92: =+IF(AM92<>"",AM92,I92) -> 45915 | AO92: =+VLOOKUP(D92,validaciones_json!$AS:$AS,1,0) -> #N/A
A93: FXP/2025/09/0051 | B93: FXP/2025/09/0051 | C93: E001-00000060 | D93: 01-E001-00000060 | E93: =+IF(C93="",SUBSTITUTE(SUBSTITUTE(SUBSTITUTE(B93,CHAR(160)," ")," -","-"),"- ","-"),SUBSTITUTE(SUBSTITUTE(SUBSTITUTE(C93,CHAR(160)," ")," -","-"),"- ","-")) -> E001-00000060 | F93: 0 | H93: VENTURA SABINO MIGUEL ANGEL | I93: 45915 | J93: 45915 | K93: 45915 | L93: P00221 | P93: COLABORATIVA S.A.C. | Q93: -2430 | S93: -2430 | T93: -2430 | V93: PEN | W93: FALSE | X93: Pagado | AB93: Registrado | AN93: =+IF(AM93<>"",AM93,I93) -> 45915 | AO93: =+VLOOKUP(D93,validaciones_json!$AS:$AS,1,0) -> #N/A
A94: R S001-18120090 | B94: R S001-18120090 | D94: 14- | E94: =+IF(C94="",SUBSTITUTE(SUBSTITUTE(SUBSTITUTE(B94,CHAR(160)," ")," -","-"),"- ","-"),SUBSTITUTE(SUBSTITUTE(SUBSTITUTE(C94,CHAR(160)," ")," -","-"),"- ","-")) -> R S001-18120090 | F94: 0 | H94: WI-NET TELECOM S.A.C. | I94: 45914 | J94: 45914 | K94: 45916 | L94: P00227 | P94: COLABORATIVA S.A.C. | Q94: -109.32 | R94: -19.68 | S94: -129 | T94: -129 | V94: PEN | W94: FALSE | X94: Pagado | AB94: Registrado | AN94: =+IF(AM94<>"",AM94,I94) -> 45914 | AO94: =+VLOOKUP(D94,validaciones_json!$AS:$AS,1,0) -> #N/A
A95: R E001- 29 | B95: R E001- 29 | D95: 02- | E95: =+IF(C95="",SUBSTITUTE(SUBSTITUTE(SUBSTITUTE(B95,CHAR(160)," ")," -","-"),"- ","-"),SUBSTITUTE(SUBSTITUTE(SUBSTITUTE(C95,CHAR(160)," ")," -","-"),"- ","-")) -> R E001-29 | F95: 0 | H95: LARREA MEDINA MELVA CIRINA | I95: 45912 | J95: 45912 | K95: 45912 | L95: P00219 | P95: COLABORATIVA S.A.C. | Q95: -400 | S95: -400 | T95: -400 | V95: PEN | W95: FALSE | X95: Pagado | AB95: Registrado | AN95: =+IF(AM95<>"",AM95,I95) -> 45912 | AO95: =+VLOOKUP(D95,validaciones_json!$AS:$AS,1,0) -> #N/A
A96: FXP/2025/09/0050 | B96: FXP/2025/09/0050 | C96: E001-00000117 | D96: 01-E001-00000117 | E96: =+IF(C96="",SUBSTITUTE(SUBSTITUTE(SUBSTITUTE(B96,CHAR(160)," ")," -","-"),"- ","-"),SUBSTITUTE(SUBSTITUTE(SUBSTITUTE(C96,CHAR(160)," ")," -","-"),"- ","-")) -> E001-00000117 | F96: 0 | H96: MUÑOZ VERANO JOHN BRACKSON | I96: 45912 | J96: 45912 | K96: 45912 | L96: P00222 | P96: COLABORATIVA S.A.C. | Q96: -110 | R96: -19.8 | S96: -129.8 | T96: -129.8 | V96: PEN | W96: FALSE | X96: Pagado | AB96: Registrado | AN96: =+IF(AM96<>"",AM96,I96) -> 45912 | AO96: =+VLOOKUP(D96,validaciones_json!$AS:$AS,1,0) -> #N/A
A97: F S108-00389525 | B97: F S108-00389525 | D97: 01- | E97: =+IF(C97="",SUBSTITUTE(SUBSTITUTE(SUBSTITUTE(B97,CHAR(160)," ")," -","-"),"- ","-"),SUBSTITUTE(SUBSTITUTE(SUBSTITUTE(C97,CHAR(160)," ")," -","-"),"- ","-")) -> F S108-00389525 | F97: 0 | H97: LUZ DEL SUR S.A.A. | I97: 45912 | J97: 45912 | K97: 45919 | L97: P00235 | P97: COLABORATIVA S.A.C. | Q97: -626.19 | R97: -112.71 | S97: -738.9 | T97: -738.9 | V97: PEN | W97: FALSE | X97: Pagado | AB97: Registrado | AN97: =+IF(AM97<>"",AM97,I97) -> 45912 | AO97: =+VLOOKUP(D97,validaciones_json!$AS:$AS,1,0) -> #N/A
A98: F FI25-00017049 | B98: F FI25-00017049 | C98: FI25-00017049 | D98: 01-FI25-00017049 | E98: =+IF(C98="",SUBSTITUTE(SUBSTITUTE(SUBSTITUTE(B98,CHAR(160)," ")," -","-"),"- ","-"),SUBSTITUTE(SUBSTITUTE(SUBSTITUTE(C98,CHAR(160)," ")," -","-"),"- ","-")) -> FI25-00017049 | F98: 0 | H98: MEMORY KINGS PERU S.A.C | I98: 45912 | J98: 45912 | K98: 45912 | L98: P00220 | P98: COLABORATIVA S.A.C. | Q98: -169.49 | R98: -30.51 | S98: -200 | T98: -200 | V98: PEN | W98: FALSE | X98: Pagado | AB98: Registrado | AN98: =+IF(AM98<>"",AM98,I98) -> 45912 | AO98: =+VLOOKUP(D98,validaciones_json!$AS:$AS,1,0) -> #N/A
A99: F E001-00000148 | B99: F E001-00000148 | C99: E001-00000148 | D99: 01-E001-00000148 | E99: =+IF(C99="",SUBSTITUTE(SUBSTITUTE(SUBSTITUTE(B99,CHAR(160)," ")," -","-"),"- ","-"),SUBSTITUTE(SUBSTITUTE(SUBSTITUTE(C99,CHAR(160)," ")," -","-"),"- ","-")) -> E001-00000148 | F99: 0 | H99: FERTU S.A.C | I99: 45912 | J99: 45912 | K99: 45915 | L99: P00218 | N99: E001-148 | P99: COLABORATIVA S.A.C. | Q99: -150 | R99: -27 | S99: -177 | T99: -177 | V99: PEN | W99: FALSE | X99: Pagado | AB99: Registrado | AN99: =+IF(AM99<>"",AM99,I99) -> 45912 | AO99: =+VLOOKUP(D99,validaciones_json!$AS:$AS,1,0) -> #N/A
A100: FXP/2025/09/0049 | B100: FXP/2025/09/0049 | C100: FI40-00016363 | D100: 01-FI40-00016363 | E100: =+IF(C100="",SUBSTITUTE(SUBSTITUTE(SUBSTITUTE(B100,CHAR(160)," ")," -","-"),"- ","-"),SUBSTITUTE(SUBSTITUTE(SUBSTITUTE(C100,CHAR(160)," ")," -","-"),"- ","-")) -> FI40-00016363 | F100: 0 | H100: MEMORY KINGS PERU S.A.C | I100: 45911 | J100: 45911 | K100: 45911 | L100: P00214 | P100: COLABORATIVA S.A.C. | Q100: -296.19 | R100: -53.31 | S100: -349.5 | T100: -349.5 | V100: PEN | W100: FALSE | X100: Pagado | AB100: Registrado | AN100: =+IF(AM100<>"",AM100,I100) -> 45911 | AO100: =+VLOOKUP(D100,validaciones_json!$AS:$AS,1,0) -> #N/A
...

Sheet Hoja1
B2: Número
B3: Número de Documento
B4: VAOPE Codigo Evento
B5: Evento
B6: Nombre del contacto a mostrar en la factura
B7: Fecha de factura
B8: Fecha
B9: Fecha de vencimiento
B10: Origen
B11: Referencia de pago
B12: Referencia
B13: Actividades
... B26: Estado

Sheet Validaciones_odooInterface
B6: Nro productos | E6: Importe sin IGV por estado factura | H6: Importe sin IGV por nombre producto | K6: Importe sin IGV por Organizador | Q6: Importe sin IGV por Distribucion analitica | T6: Importe sin IGV por 1.Fecha Evento o 2.Fecha factura | Z6: Importe sin IGV por 1.Fecha Evento o 2.Fecha factura
B8: Etiquetas de fila | C8: Cuenta de Fecha de factura | E8: Etiquetas de fila | F8: Importe sin impuestos firmado | H8: Etiquetas de fila | I8: Importe sin impuestos firmado | K8: Etiquetas de fila | L8: Cuenta de Fecha de factura | M8: Importe sin impuestos firmado | N8: Suma de Impuesto firmado | O8: Suma de Total firmado | Q8: Etiquetas de fila | R8: Importe sin impuestos firmado | T8: Etiquetas de fila | U8: Cuenta de Fecha de factura | V8: Importe sin impuestos firmado | W8: Suma de Impuesto firmado | X8: Suma de Total firmado | Z8: Etiquetas de fila | AA8: Cuenta de Fecha de factura | AB8: Importe sin impuestos firmado | AC8: Suma de Impuesto firmado | AD8: Suma de Total firmado
B9: Registrado | C9: 424 | E9: Registrado | F9: -671100.63 | H9: (en blanco) | I9: -671100.63 | K9: FLINK S.A.C. | L9: 12 | M9: -37067.68 | N9: -6672.32 | O9: -43740 | Q9: (en blanco) | R9: -671100.63 | T9: 45800 | U9: 1 | V9: -2724.59 | W9: -490.41 | X9: -3215 | Z9: FXP/2025/10/0117 | AA9: 1 | AB9: -2170 | AD9: -2170
B10: Total general | C10: 424 | E10: Total general | F10: -671100.63 | H10: Total general | I10: -671100.63 | K10: VENTURA SABINO MIGUEL ANGEL | L10: 11 | M10: -17409.49 | N10: -30.51 | O10: -17440 | Q10: Total general | R10: -671100.63 | T10: 45810 | U10: 5 | V10: -11226.43 | W10: -1993.77 | X10: -13220.2 | Z10: FXP/2025/10/0116 | AA10: 1 | AB10: -450 | AC10: -81 | AD10: -531
K11: PRAGMATIC S.A.C. | L11: 10 | M11: -11190 | N11: -2014.2 | O11: -13204.2 | T11: 45812 | U11: 4 | V11: -7486.7 | W11: -217.83 | X11: -7704.53 | Z11: FXP/2025/10/0113 | AA11: 1 | AB11: -3550 | AD11: -3550
K12: GUTIERREZ PETIT MARIA ANGEL | L12: 1 | M12: -3550 | O12: -3550 | T12: 45821 | U12: 4 | V12: -993.85 | W12: -177.65 | X12: -1171.5 | Z12: FXP/2025/10/0109 | AA12: 1 | AB12: -1640 | AD12: -1640
K13: CARMEN CRUZ MILAGROS ZONALI | L13: 5 | M13: -2402.37 | N13: -52.63 | O13: -2455 | T13: 45831 | U13: 2 | V13: -700 | W13: -126 | X13: -826 | Z13: FXP/2025/10/0111 | AA13: 1 | AB13: -225 | AC13: -40.5 | AD13: -265.5
K14: MAPFRE PERU S.A. | L14: 6 | M14: -850 | N14: -153 | O14: -1003 | T14: 45944 | U14: 1 | V14: -2170 | X14: -2170 | Z14: FXP/2025/10/0112 | AA14: 1 | AB14: -5400 | AD14: -5400
E15: Importe sin IGV por estado factura | K15: VARGAS HUARCAYA DANIELA RUBI | L15: 1 | M15: -5400 | O15: -5400 | T15: 45943 | U15: 2 | V15: -4000 | W15: -81 | X15: -4081 | Z15: FXP/2025/10/0110 | AA15: 1 | AB15: -101.69 | AC15: -18.31 | AD15: -120
K16: DOLCE CAPRICCIO SAC | L16: 2 | M16: -196.69 | N16: -18.31 | O16: -215 | T16: 45942 | U16: 1 | V16: -1640 | X16: -1640 | Z16: FXP/2025/10/0108 | AA16: 1 | AB16: -7000 | AD16: -7000
E17: Etiquetas de fila | F17: Suma de Impuesto firmado | K17: GALVAN VARGAS DAYANA LIZBETH | L17: 1 | M17: -7000 | O17: -7000 | T17: 45941 | U17: 1 | V17: -225 | W17: -40.5 | X17: -265.5 | Z17: FXP/2025/10/0106 | AA17: 1 | AB17: -338.98 | AC17: -61.02 | AD17: -400
E18: Registrado | F18: -100981.32 | K18: SOLANO CALDERON JUAN ALONSO | L18: 2 | M18: -738.98 | N18: -61.02 | O18: -800 | T18: 45940 | U18: 5 | V18: -13137.28 | W18: -132.72 | X18: -13270 | Z18: FXP/2025/10/0105 | AA18: 1 | AB18: -296.61 | AC18: -53.39 | AD18: -350
E19: Total general | F19: -100981.32 | K19: ESPINO MORI LEANDRO JOAQUIN | L19: 7 | M19: -3106.61 | N19: -53.39 | O19: -3160 | T19: 45931 | U19: 5 | V19: -1184.63 | W19: -200.32 | X19: -1384.95 | Z19: FXP/2025/10/0102 | AA19: 1 | AB19: -71.7 | AD19: -71.7
K20: PANIFICADORA LA NUEZ SAC | L20: 1 | M20: -71.7 | O20: -71.7 | T20: 45937 | U20: 5 | V20: -2715.8 | W20: -307.44 | X20: -3023.24 | Z20: FXP/2025/10/0101 | AA20: 1 | AB20: -127.8 | AD20: -127.8
K21: INVERSIONES SAP S.A. | L21: 1 | M21: -127.8 | O21: -127.8 | T21: 45936 | U21: 4 | V21: -3301.5 | W21: -445.86 | X21: -3747.36 | Z21: FXP/2025/10/0100 | AA21: 1 | AB21: -64.5 | AD21: -64.5
K22: ORIENTAL GOURMET S.A. | L22: 2 | M22: -117.47 | N22: -9.53 | O22: -127 | T22: 45939 | U22: 2 | V22: -1462 | W22: -180 | X22: -1642 | Z22: FXP/2025/10/0099 | AA22: 1 | AB22: -462 | AD22: -462
E23: Importe sin IGV por estado factura | K23: MALBEC SAC | L23: 2 | M23: -906 | O23: -906 | T23: 45938 | U23: 2 | V23: -661.02 | W23: -119.01 | X23: -780.03 | Z23: FXP/2025/10/0107 | AA23: 1 | AB23: -1000 | AC23: -180 | AD23: -1180
K24: KUNTUR PRO S.A.C. | L24: 2 | M24: -6050 | N24: -1089 | O24: -7139 | T24: 45935 | U24: 5 | V24: -652.44 | W24: -56.24 | X24: -708.68 | Z24: FXP/2025/10/0096 | AA24: 1 | AB24: -110.17 | AC24: -19.84 | AD24: -130.01
E25: Etiquetas de fila | F25: Suma de Total firmado | K25: EURO CARS PERU S.A.C. | L25: 2 | M25: -661.02 | N25: -119.01 | O25: -780.03 | T25: 45934 | U25: 1 | V25: -36.04 | W25: -6.49 | X25: -42.53 | Z25: FXP/2025/10/0095 | AA25: 1 | AB25: -550.85 | AC25: -99.17 | AD25: -650.02
E26: Registrado | F26: -772081.95 | K26: MUÑOZ VERANO JOHN BRACKSON | L26: 38 | M26: -46586 | N26: -8234.28 | O26: -54820.28 | T26: 45932 | U26: 1 | V26: -2002.56 | W26: -360.44 | X26: -2363 | Z26: FXP/2025/10/0094 | AA26: 1 | AB26: -1200 | AC26: -216 | AD26: -1416
E27: Total general | F27: -772081.95 | K27: SALVADOR ARNALDO REYES CHUECAS | L27: 4 | M27: -2883.59 | O27: -2883.59 | T27: 45924 | U27: 8 | V27: -2569.73 | W27: -352.07 | X27: -2921.8 | Z27: FXP/2025/10/0093 | AA27: 1 | AB27: -200 | AC27: -36 | AD27: -236
K28: TECNOLOGIA FLEXOGRAFICA S.A.C - TECFLEX | L28: 13 | M28: -16433.6 | N28: -2958.04 | O28: -19391.64 | T28: 45920 | U28: 1 | V28: -6.19 | W28: -1.11 | X28: -7.3 | Z28: FXP/2025/10/0089 | AA28: 1 | AB28: -308 | AC28: -55.44 | AD28: -363.44
K29: LATAM AIRLINES PERU S.A. | L29: 4 | M29: -2415.3 | N29: -434.75 | O29: -2850.05 | T29: 45925 | U29: 6 | V29: -1144.74 | W29: -206.06 | X29: -1350.8 | Z29: FXP/2025/10/0088 | AA29: 1 | AB29: -880 | AD29: -880
K30: ROJAS SIESQUEN CARLOS EDGARDO | L30: 1 | M30: -128.81 | N30: -23.19 | O30: -152 | T30: 45918 | U30: 5 | V30: -3154.07 | W30: -422.96 | X30: -3577.03 | Z30: FXP/2025/10/0114 | AA30: 1 | AB30: -600 | AD30: -600
K31: LATAM PERU S.A.C. | L31: 1 | M31: -50.85 | N31: -9.15 | O31: -60 | T31: 45929 | U31: 7 | V31: -18399.45 | W31: -2706.59 | X31: -21106.04 | Z31: FXP/2025/10/0097 | AA31: 1 | AB31: -160 | AD31: -160
K32: SECLEN ZAMORA JAHAIRA VANESSITA | L32: 1 | M32: -220 | O32: -220 | T32: 45930 | U32: 1 | V32: -30 | X32: -30 | Z32: FXP/2025/10/0092 | AA32: 1 | AB32: -2477 | AC32: -445.86 | AD32: -2922.86
K33: BRAVO MATOS RICARDO ALEJANDRO | L33: 1 | M33: -120 | O33: -120 | T33: 45900 | U33: 1 | V33: -86 | X33: -86 | Z33: FXP/2025/10/0098 | AA33: 1 | AB33: -132.78 | AC33: -23.9 | AD33: -156.68
K34: America Móvil Perú S.A.C. | L34: 13 | M34: -469.57 | N34: -84.54 | O34: -554.11 | T34: 45910 | U34: 3 | V34: -378.93 | W34: -27 | X34: -405.93 | Z34: FXP/2025/10/0091 | AA34: 1 | AB34: -128.81 | AC34: -23.19 | AD34: -152
K35: PRECINTOS PERU E.I.R.L | L35: 15 | M35: -61487.25 | N35: -11067.75 | O35: -72555 | T35: 45908 | U35: 2 | V35: -3367.73 | W35: -580.77 | X35: -3948.5 | Z35: FXP/2025/10/0090 | AA35: 1 | AB35: -50.85 | AC35: -9.15 | AD35: -60
K36: Verisure Peru SAC | L36: 11 | M36: -2071.94 | N36: -325.84 | O36: -2397.78 | T36: 45906 | U36: 3 | V36: -358.11 | W36: -9.54 | X36: -367.65 | Z36: FXP/2025/10/0086 | AA36: 1 | AB36: -220 | AD36: -220
K37: J & V MULTIUTILES PUNTO COM S.A.C. | L37: 5 | M37: -1063.57 | N37: -191.43 | O37: -1255 | T37: 45915 | U37: 3 | V37: -2919.8 | X37: -2919.8 | Z37: FXP/2025/10/0084 | AA37: 1 | AB37: -120 | AD37: -120
K38: SERVICIO DE AGUA POTABLE Y ALCANTARILLADO DE LIMA | L38: 3 | M38: -18.73 | N38: -3.37 | O38: -22.1 | T38: 45916 | U38: 3 | V38: -3798.03 | W38: -633.97 | X38: -4432 | Z38: FXP/2025/10/0115 | AA38: 1 | AB38: -36.04 | AC38: -6.49 | AD38: -42.53
K39: RASH PERU S.R.L | L39: 2 | M39: -653.99 | N39: -117.71 | O39: -771.7 | T39: 45926 | U39: 1 | V39: -538.14 | W39: -96.86 | X39: -635 | Z39: FXP/2025/10/0078 | AA39: 1 | AB39: -2002.56 | AC39: -360.44 | AD39: -2363
K40: SANTOFA E.I.R.L. | L40: 1 | M40: -88.81 | N40: -15.99 | O40: -104.8 | T40: 45917 | U40: 6 | V40: -2625.41 | W40: -467.15 | X40: -3092.56 | Z40: FXP/2025/10/0104 | AA40: 1 | AB40: -221.82 | AC40: -39.93 | AD40: -261.75
K41: COESTI SA | L41: 4 | M41: -512.36 | N41: -11.59 | O41: -523.95 | T41: 45919 | U41: 5 | V41: -3996.7 | W41: -437.78 | X41: -4434.48 | Z41: FXP/2025/10/0077 | AA41: 1 | AB41: -125.85 | AC41: -22.65 | AD41: -148.5
K42: TOOL STORE PERU E.I.R.L. | L42: 1 | M42: -64.4 | N42: -11.59 | O42: -75.99 | T42: 45911 | U42: 6 | V42: -1878.95 | W42: -321.35 | X42: -2200.3 | Z42: FXP/2025/10/0076 | AA42: 1 | AB42: -677.97 | AC42: -122.03 | AD42: -800
K43: PROLIDER EMPRESARIAL S.AC. | L43: 2 | M43: -1433.41 | N43: -116.99 | O43: -1550.4 | T43: 45904 | U43: 8 | V43: -1636.4 | W43: -214.63 | X43: -1851.03 | Z43: FXP/2025/10/0067 | AA43: 1 | AB43: -87.29 | AC43: -15.71 | AD43: -103
K44: YOPO S.A.C. | L44: 6 | M44: -292.44 | N44: -15.56 | O44: -308 | T44: 45923 | U44: 3 | V44: -1068.97 | W44: -91.61 | X44: -1160.58 | Z44: FXP/2025/10/0087 | AA44: 1 | AB44: -175 | AD44: -175
K45: SANKY 10 S.A.C | L45: 1 | M45: -20.9 | O45: -20.9 | T45: 45914 | U45: 1 | V45: -109.32 | W45: -19.68 | X45: -129 | Z45: FXP/2025/10/0083 | AA45: 1 | AB45: -6.19 | AC45: -1.11 | AD45: -7.3
K46: REPRESENTACIONES ALEXIA S.A.C. | L46: 2 | M46: -185.36 | N46: -14.64 | O46: -200 | T46: 45912 | U46: 5 | V46: -1455.68 | W46: -190.02 | X46: -1645.7 | Z46: FXP/2025/10/0081 | AA46: 1 | AB46: -76.76 | AC46: -13.82 | AD46: -90.58
K47: GRIFO SAN IGNACIO S.A.C. | L47: 3 | M47: -575.24 | O47: -575.24 | T47: 45909 | U47: 5 | V47: -6600.33 | W47: -653.47 | X47: -7253.8 | Z47: FXP/2025/10/0080 | AA47: 1 | AB47: -26.15 | AC47: -4.71 | AD47: -30.86
K48: MARCAS TUPALAYA VICTOR ALBERTO | L48: 5 | M48: -3702.22 | N48: -106.8 | O48: -3809.02 | T48: 45905 | U48: 1 | V48: -21373.67 | W48: -3847.26 | X48: -25220.93 | Z48: FXP/2025/10/0079 | AA48: 1 | AB48: -9.24 | AC48: -1.66 | AD48: -10.9
K49: CATORCE & SEIS S.A.C. | L49: 16 | M49: -241857.72 | N49: -43534.39 | O49: -285392.11 | T49: 45903 | U49: 1 | V49: -3669.15 | W49: -660.45 | X49: -4329.6 | Z49: FXP/2025/10/0074 | AA49: 1 | AB49: -33.5 | AC49: -6.03 | AD49: -39.53
K50: DELIBAKERY PERU S.A.C. | L50: 1 | M50: -141.5 | O50: -141.5 | T50: 45902 | U50: 4 | V50: -2775 | W50: -7.2 | X50: -2782.2 | Z50: FXP/2025/10/0073 | AA50: 1 | AB50: -88.81 | AC50: -15.99 | AD50: -104.8
K51: Repsol Comercial S.A.C. | L51: 2 | M51: -491.14 | O51: -491.14 | T51: 45901 | U51: 2 | V51: -3061.82 | W51: -551.13 | X51: -3612.95 | Z51: FXP/2025/10/0069 | AA51: 1 | AB51: -73.89 | AD51: -73.89
K52: TERTISA COMBUSTIBLES S.A. | L52: 1 | M52: -64 | O52: -64 | T52: 45871 | U52: 3 | V52: -261.71 | W52: -20.29 | X52: -282 | Z52: FXP/2025/10/0068 | AA52: 1 | AB52: -183.65 | AD52: -183.65
K53: FRANQUICIAS ALIMENTARIAS S.A. | L53: 1 | M53: -59.8 | O53: -59.8 | T53: 45899 | U53: 3 | V53: -31139.53 | W53: -5605.11 | X53: -36744.64 | Z53: FXP/2025/10/0066 | AA53: 1 | AB53: -64.4 | AC53: -11.59 | AD53: -75.99
K54: COCINA TRUJILLANA SAC | L54: 2 | M54: -537.86 | N54: -47.14 | O54: -585 | T54: 45898 | U54: 5 | V54: -6606.97 | W54: -1154.13 | X54: -7761.1 | Z54: FXP/2025/10/0065 | AA54: 1 | AB54: -783.4 | AD54: -783.4
K55: MEMORY KINGS PERU S.A.C | L55: 9 | M55: -7154.75 | N55: -1287.85 | O55: -8442.6 | T55: 45897 | U55: 1 | V55: -238.98 | W55: -43.02 | X55: -282 | Z55: FXP/2025/10/0061 | AA55: 1 | AB55: -30 | AD55: -30
K56: CORPORACION LINCOSUR E.I.R.L. | L56: 1 | M56: -422.88 | N56: -76.12 | O56: -499 | T56: 45896 | U56: 5 | V56: -7314.27 | W56: -1316.57 | X56: -8630.84 | Z56: FXP/2025/09/0045 | AA56: 1 | AB56: -86 | AD56: -86
K57: RASH PERU SRL | L57: 1 | M57: -33.73 | N57: -6.07 | O57: -39.8 | T57: 45894 | U57: 1 | V57: -8855.88 | W57: -1594.12 | X57: -10450 | Z57: FXP/2025/09/0044 | AA57: 1 | AB57: -20.9 | AD57: -20.9
K58: TIENDAS DEL MEJORAMIENTO DEL HOGAR S.A. | L58: 1 | M58: -575.98 | N58: -103.68 | O58: -679.66 | T58: 45891 | U58: 5 | V58: -4869.32 | W58: -723.49 | X58: -5592.81 | Z58: FXP/2025/09/0043 | AA58: 1 | AB58: -104 | AD58: -104
K59: SP SABORES PERUANOS EIRL | L59: 1 | M59: -217 | O59: -217 | T59: 45890 | U59: 1 | V59: -2450 | X59: -2450 | Z59: FXP/2025/09/0042 | AA59: 1 | AB59: -181.26 | AD59: -181.26
K60: NEGOCIOS GASTRONOMICOS SANTOS EIRL | L60: 2 | M60: -511.01 | N60: -91.99 | O60: -603 | T60: 45889 | U60: 2 | V60: -5262.09 | W60: -947.18 | X60: -6209.27 | Z60: FXP/2025/09/0041 | AA60: 1 | AB60: -198.93 | AD60: -198.93
K61: JEMKA & ASOCIADOS S.A.C. | L61: 6 | M61: -6480.34 | N61: -1166.46 | O61: -7646.8 | T61: 45888 | U61: 4 | V61: -1876.51 | W61: -281.89 | X61: -2158.4 | Z61: FXP/2025/10/0072 | AA61: 1 | AB61: -2470 | AC61: -444.6 | AD61: -2914.6
K62: PRINTMATE2.0 E.I.R.L. | L62: 1 | M62: -456 | N62: -82.08 | O62: -538.08 | T62: 45887 | U62: 4 | V62: -4498.95 | W62: -707.23 | X62: -5206.18 | Z62: FXP/2025/09/0046 | AA62: 1 | AB62: -2400 | AD62: -2400
K63: CENCOSUD RETAIL PERU S.A. | L63: 1 | M63: -38.11 | N63: -6.87 | O63: -44.98 | T63: 45884 | U63: 4 | V63: -5833.73 | W63: -75.07 | X63: -5908.8 | Z63: FXP/2025/09/0036 | AA63: 1 | AB63: -594.59 | AC63: 47.57 | AD63: -547.02
K64: DANPRINT STUDIO (CINTHIA LISETH LOPEZ INGA) | L64: 13 | M64: -23467.48 | N64: -4224.16 | O64: -27691.64 | T64: 45883 | U64: 3 | V64: -1076.27 | W64: -193.73 | X64: -1270 | Z64: FXP/2025/09/0035 | AA64: 1 | AB64: -12677.65 | AC64: -2281.98 | AD64: -14959.63
K65: PACIFICO COMPAÑIA DE SEGUROS Y REASEGUROS | L65: 4 | M65: -2112.36 | N65: -380.2 | O65: -2492.56 | T65: 45882 | U65: 1 | V65: -142 | W65: -25.55 | X65: -167.55 | Z65: FXP/2025/09/0034 | AA65: 1 | AB65: -141.5 | AD65: -141.5
K66: CANGAHUALA LETONA ELIO HUGO | L66: 1 | M66: -972.03 | N66: -174.97 | O66: -1147 | T66: 45881 | U66: 3 | V66: -1022.05 | W66: -58.35 | X66: -1080.4 | Z66: FXP/2025/09/0033 | AA66: 1 | AB66: -241.11 | AD66: -241.11
K67: GARRIDO ROJAS GREGORY OMAR | L67: 5 | M67: -980 | O67: -980 | T67: 45880 | U67: 2 | V67: -910.5 | W67: -11.59 | X67: -922.09 | Z67: FXP/2025/09/0032 | AA67: 1 | AB67: -64 | AD67: -64
K68: WI-NET TELECOM S.A.C. | L68: 2 | M68: -218.64 | N68: -39.36 | O68: -258 | T68: 45876 | U68: 2 | V68: -935.08 | W68: -168.32 | X68: -1103.4 | Z68: FXP/2025/09/0028 | AA68: 1 | AB68: -59.8 | AD68: -59.8
K69: LARREA MEDINA MELVA CIRINA | L69: 1 | M69: -400 | O69: -400 | T69: 45873 | U69: 5 | V69: -10532.62 | W69: -1519.72 | X69: -12052.34 | Z69: FXP/2025/09/0027 | AA69: 1 | AB69: -30 | AD69: -30
K70: LUZ DEL SUR S.A.A. | L70: 6 | M70: -3415.1 | N70: -357.5 | O70: -3772.6 | T70: 45872 | U70: 1 | V70: -101.69 | W70: -18.31 | X70: -120 | Z70: FXP/2025/09/0026 | AA70: 1 | AB70: -276 | AD70: -276
K71: FERTU S.A.C | L71: 2 | M71: -300 | N71: -54 | O71: -354 | T71: 45870 | U71: 7 | V71: -4409.98 | W71: -746.68 | X71: -5156.66 | Z71: FXP/2025/09/0022 | AA71: 1 | AB71: -538.14 | AC71: -96.86 | AD71: -635
K72: GLOBAL FUEL SOCIEDAD ANONIMA | L72: 2 | M72: -173.11 | N72: -14.29 | O72: -187.4 | T72: 45869 | U72: 9 | V72: -23550.74 | W72: -2350.55 | X72: -25901.29 | Z72: FXP/2025/09/0016 | AA72: 1 | AB72: -168.64 | AC72: -30.36 | AD72: -199
K73: VILCA SILVA JOHAN ALDAIR | L73: 6 | M73: -1400 | N73: -252 | O73: -1652 | T73: 45841 | U73: 4 | V73: -991.18 | W73: -133.41 | X73: -1124.59 | Z73: FXP/2025/09/0015 | AA73: 1 | AB73: -87.29 | AC73: -15.71 | AD73: -103
K74: DEVERCOMP TECHNOLOGY S.A.C. | L74: 2 | M74: -693.13 | N74: -124.77 | O74: -817.9 | T74: 45868 | U74: 3 | V74: -35482.03 | W74: -6386.76 | X74: -41868.79 | Z74: FXP/2025/09/0037 | AA74: 1 | AB74: -422.88 | AC74: -76.12 | AD74: -499
K75: SAGA FALABELLA S.A. | L75: 2 | M75: -2705.85 | N75: -487.05 | O75: -3192.9 | T75: 45866 | U75: 2 | V75: -473.72 | W75: -85.28 | X75: -559 | Z75: FXP/2025/09/0018 | AA75: 1 | AB75: -33.73 | AC75: -6.07 | AD75: -39.8
K76: ROJAS CASTILLO SUSANA | L76: 3 | M76: -3780 | N76: -680.4 | O76: -4460.4 | T76: 45865 | U76: 1 | V76: -292.37 | W76: -52.63 | X76: -345 | Z76: FXP/2025/09/0017 | AA76: 1 | AB76: -575.98 | AC76: -103.68 | AD76: -679.66
K77: #3ERA ESTACION E.I.R.L. - 20605029851 | L77: 1 | M77: -53 | N77: -9.54 | O77: -62.54 | T77: 45864 | U77: 1 | V77: -59.32 | W77: -10.68 | X77: -70 | Z77: FXP/2025/09/0013 | AA77: 1 | AB77: -30 | AD77: -30
K78: N.B. TEALDO & CO. S.A. | L78: 2 | M78: -454.1 | N78: -81.74 | O78: -535.84 | T78: 45863 | U78: 1 | V78: -381.36 | W78: -68.64 | X78: -450 | Z78: FXP/2025/09/0012 | AA78: 1 | AB78: -30 | AD78: -30
K79: ECODYL S.A.C. | L79: 1 | M79: -101.7 | N79: -18.31 | O79: -120.01 | T79: 45862 | U79: 6 | V79: -3214.86 | W79: -578.68 | X79: -3793.54 | Z79: FXP/2025/09/0010 | AA79: 1 | AB79: -217 | AD79: -217
K80: THE ZABO COMPANY SAC | L80: 1 | M80: -71.19 | N80: -12.81 | O80: -84 | T80: 45860 | U80: 3 | V80: -1606.27 | W80: -271.13 | X80: -1877.4 | Z80: FXP/2025/09/0009 | AA80: 1 | AB80: -238.98 | AC80: -43.02 | AD80: -282
K81: PAPACHOS RESTAURANTES S.A.C. | L81: 1 | M81: -88 | O81: -88 | T81: 45859 | U81: 7 | V81: -3149.88 | W81: -566.95 | X81: -3716.83 | Z81: FXP/2025/09/0024 | AA81: 1 | AB81: -1500 | AC81: -270 | AD81: -1770
K82: LINARES DE LA CRUZ MARTINA | L82: 1 | T82: 45857 | U82: 1 | V82: -101.69 | W82: -18.31 | X82: -120 | Z82: FXP/2025/09/0023 | AA82: 1 | AB82: -200 | AC82: -36 | AD82: -236
K83: SERVIM LOGISTIC S.A.C. | L83: 1 | M83: -335 | N83: -60.3 | O83: -395.3 | T83: 45856 | U83: 2 | V83: -221.09 | W83: -39.81 | X83: -260.9 | Z83: FXP/2025/09/0004 | AA83: 1 | AB83: -444 | AD83: -444
K84: DOLPHIN EVOLUTION E.I.R.L. | L84: 1 | M84: -150 | N84: -27 | O84: -177 | T84: 45855 | U84: 4 | V84: -2166.89 | W84: -390.01 | X84: -2556.9 | Z84: FXP/2025/09/0003 | AA84: 1 | AB84: -52.97 | AC84: -9.53 | AD84: -62.5
K85: Compañía Food Retail S.A.C. | L85: 1 | M85: -238.98 | N85: -43.02 | O85: -282 | T85: 45854 | U85: 5 | V85: -5746.18 | W85: -1034.31 | X85: -6780.49 | Z85: FXP/2025/09/0006 | AA85: 1 | AB85: -456 | AC85: -82.08 | AD85: -538.08
K86: Entel Peru S.A. | L86: 1 | M86: -100.27 | N86: -18.06 | O86: -118.33 | T86: 45853 | U86: 2 | V86: -3276.75 | W86: -589.82 | X86: -3866.57 | Z86: FXP/2025/09/0001 | AA86: 1 | AB86: -560 | AD86: -560
K87: RIMAC SEGUROS Y REASEGUROS | L87: 1 | M87: -2081.3 | N87: -374.63 | O87: -2455.93 | T87: 45852 | U87: 1 | V87: -211.87 | W87: -38.14 | X87: -250.01 | Z87: R E001-00000015 | AA87: 1 | AB87: -1317.5 | AD87: -1317.5
K88: DIMERC PERU S.A.C. | L88: 4 | M88: -994.46 | N88: -178.96 | O88: -1173.42 | T88: 45850 | U88: 2 | V88: -40621.97 | W88: -7311.95 | X88: -47933.92 | Z88: FXP/2025/10/0056 | AA88: 1 | AB88: -2394.09 | AC88: -430.91 | AD88: -2825
K89: GARRIDO ROJAS MARISABEL | L89: 3 | M89: -15532.37 | N89: -1756.05 | O89: -17288.42 | T89: 45849 | U89: 3 | V89: -8194.95 | W89: -1475.15 | X89: -9670.1 | Z89: FXP/2025/09/0005 | AA89: 1 | AB89: -38.11 | AC89: -6.87 | AD89: -44.98
K90: ESET - NOD32 | L90: 1 | M90: -214.9 | N90: -38.68 | O90: -253.58 | T90: 45848 | U90: 2 | V90: -1989.83 | W90: -358.17 | X90: -2348 | Z90: FXP/2025/09/0007 | AA90: 1 | AB90: -240 | AC90: -43.2 | AD90: -283.2
K91: CHUECA OSTOLAZA MARIA PATRICIA MILAGROS | L91: 1 | M91: -3750 | N91: 300 | O91: -3450 | T91: 45845 | U91: 8 | V91: -7936.5 | W91: -1411.46 | X91: -9347.96 | Z91: F E001-00000293 | AA91: 1 | AB91: -2076.27 | AC91: -373.73 | AD91: -2450
K92: MENDOZA GUERRA FELIX ANTONIO | L92: 4 | M92: -2470 | N92: -444.6 | O92: -2914.6 | T92: 45844 | U92: 1 | V92: -1283.9 | W92: -231.1 | X92: -1515 | Z92: FXP/2025/10/0059 | AA92: 1 | AB92: -528.27 | AC92: -95.08 | AD92: -623.35
K93: REUSCHE CALLUPE ANTHONY ALAN | L93: 1 | M93: -950 | N93: -171 | O93: -1121 | T93: 45842 | U93: 2 | V93: -3969.8 | W93: -714.56 | X93: -4684.36 | Z93: FXP/2025/10/0058 | AA93: 1 | AB93: -528.03 | AC93: -95.04 | AD93: -623.07
K94: MAPFRE PERU COMPAÑIA DE SEGUROS Y REASEGUROS | L94: 1 | M94: -100 | N94: -18 | O94: -118 | T94: 45840 | U94: 4 | V94: -7877.43 | W94: -508.57 | X94: -8386 | Z94: FXP/2025/10/0057 | AA94: 1 | AB94: -528.03 | AC94: -95.04 | AD94: -623.07
K95: JL ELECTRICIDAD S.A.C. | L95: 2 | M95: -440 | N95: -79.2 | O95: -519.2 | T95: 45839 | U95: 4 | V95: -4405.35 | W95: -792.96 | X95: -5198.31 | Z95: FXP/2025/10/0054 | AA95: 1 | AB95: -528.03 | AC95: -95.04 | AD95: -623.07
K96: GIURA MORI GABRIELA NORIKO | L96: 4 | M96: -4380 | O96: -4380 | T96: 45838 | U96: 2 | V96: -1560 | W96: -280.8 | X96: -1840.8 | Z96: F F002-00033229 | AA96: 1 | AB96: -483.05 | AC96: -86.95 | AD96: -570
K97: IVANKAA HOSTEL TRAVEL E.I.R.L. | L97: 1 | M97: -101.69 | N97: -18.31 | O97: -120 | T97: 45837 | U97: 1 | V97: -78.39 | W97: -14.11 | X97: -92.5 | Z97: FXP/2025/10/0053 | AA97: 1 | AB97: -2550 | AC97: -459 | AD97: -3009
K98: LA CROSSARIOLE S.A.C. | L98: 1 | M98: -61 | O98: -61 | T98: 45835 | U98: 3 | V98: -2869.46 | W98: -273.5 | X98: -3142.96 | Z98: F E001-00000038 | AA98: 1 | AB98: -972.03 | AC98: -174.97 | AD98: -1147
K99: MATUTE DIAZ VASTI VANESA | L99: 1 | M99: -112.71 | N99: -20.29 | O99: -133 | T99: 45834 | U99: 3 | V99: -2050 | W99: -64.8 | X99: -2114.8 | Z99: FXP/2025/09/0052 | AA99: 1 | AB99: -430 | AD99: -430
K100: L & R TURISMO Y COMERCIO SAC | L100: 2 | M100: -711.86 | N100: -128.14 | O100: -840 | T100: 45833 | U100: 5 | V100: -8875.22 | W100: -1597.58 | X100: -10472.8 | Z100: FXP/2025/09/0051 | AA100: 1 | AB100: -2430 | AD100: -2430
K101: EVIDENT S.A - Ruc: 20389601137 | L101: 1 | M101: -124 | N101: -22.32 | O101: -146.32 | T101: 45832 | U101: 5 | V101: -3972.66 | W101: -391.08 | X101: -4363.74 | Z101: R S001-18120090 | AA101: 1 | AB101: -109.32 | AC101: -19.68 | AD101: -129
K102: VASQUEZ SANTILLAN ETTY JHOSELLING | L102: 1 | M102: -565 | O102: -565 | T102: 45846 | U102: 2 | V102: -515.08 | W102: -63.92 | X102: -579 | Z102: R E001- 29 | AA102: 1 | AB102: -400 | AD102: -400
K103: ORBIS VENTURES S.A.C | L103: 1 | M103: -9627.19 | O103: -9627.19 | T103: 45827 | U103: 1 | V103: -110 | X103: -110 | Z103: FXP/2025/09/0050 | AA103: 1 | AB103: -110 | AC103: -19.8 | AD103: -129.8
K104: INSTITUTO PACIFICO S.A.C | L104: 3 | M104: -427.12 | N104: -22.88 | O104: -450 | T104: 45826 | U104: 2 | V104: -341.8 | W104: -61.52 | X104: -403.32 | Z104: F S108-00389525 | AA104: 1 | AB104: -626.19 | AC104: -112.71 | AD104: -738.9
K105: GRUPO MAUVE E.I.R.L | L105: 1 | M105: -593.22 | N105: -106.78 | O105: -700 | T105: 45825 | U105: 2 | V105: -697.5 | W105: -125.55 | X105: -823.05 | Z105: F FI25-00017049 | AA105: 1 | AB105: -169.49 | AC105: -30.51 | AD105: -200
K106: UPWARDS STUDIO S.A.C. | L106: 2 | M106: -780 | N106: -140.4 | O106: -920.4 | T106: 45824 | U106: 2 | V106: -4736.43 | W106: -753.57 | X106: -5490 | Z106: F E001-00000148 | AA106: 1 | AB106: -150 | AC106: -27 | AD106: -177
...

Sheet facturas_con_items_json
A1: serie_correlativo | B1: numero | C1: nombre_empresa | D1: fecha_de_emision | E1: hora_de_emision | F1: nom_proveedor | G1: cat_proveedor | H1: tipo_documento | I1: doc_proveedor | J1: items | K1: factura.fecha_emision | L1: factura.cliente | M1: factura.id_cliente | N1: factura.total | O1: factura.moneda | P1: factura.estado | Q1: item.codigo_producto | R1: item.cantidad | S1: item.valor_unitario | T1: item.precio_unitario | U1: item.descuento | V1: item.subtotal | W1: item.porcentaje_de_igv | X1: item.igv | Y1: item.total | Z1: item.moneda | AA1: item.tipo_de_cambio | AB1: item.id_tipo_gasto | AC1: item.nom_tipo_gasto | AD1: item.id_proveedor | AE1: item.id_producto | AF1: item.nom_producto | AG1: item.categoria_producto | AH1: item.id_estado | AI1: item.nombre_estado | AJ1: item.id_cuenta | AK1: item.nom_cuenta | AL1: item.distribucion_analitica | AM1: item.evento.id_evento | AN1: item.evento.nom_evento | AO1: item.evento.fecha_hora_ini_event | AP1: item.evento.fecha_hora_fin_event | AQ1: item.evento.id_organizador | AR1: item.evento.nom_organizador | AS1: item.evento.tipo_organizador | AT1: UNIFICADO | AU1: CONVERSION.item.subtotal | AV1: CONVERSION.item.igv | AW1: CONVERSION.item.total
A2: E001 | B2: 00000068 | C2: COLABORATIVA S.A.C. | D2: 45944 | E2: 45957.499 | F2: VENTURA SABINO MIGUEL ANGEL | H2: RUC | J2: [{'codigo_producto': 2292, 'cantidad': '1', 'valor_unitario': 2170.0, 'precio_unitario': 2170.0, 'descuento': 0.0, 'subtotal': 2170.0, 'porcentaje_de_igv': '0.00', 'igv': 0.0, 'total': 2170.0, 'moneda': '1', 'tipo_de_cambio': 1.0, 'id_tipo_gasto': 5, 'nom_tipo_gasto': 'Otros', 'id_proveedor': 1806, 'id_producto': 31117, 'nom_producto': 'CARPINTERIA', 'categoria_producto': 'EVENTOS', 'id_estado': 'paid', 'nombre_estado': 'Pagado', 'evento': {'id_evento': '', 'nom_evento': '', 'fecha_hora_ini_event': '', 'fecha_hora_fin_event': '', 'id_organizador': '', 'nom_organizador': '', 'tipo_organizador': ''}, 'id_cuenta': 6743, 'nom_cuenta': '6329102 SERVICIOS DIVERSOS', 'distribucion_analitica': [[{'codigo': 138, 'nom_distribucion': 'Administrativo', 'sub_categoria': 'Acondicionamiento', 'porcentaje': '100.00'}]]}] | K2: 45944 | Q2: 2292 | R2: 1 | S2: 2170 | T2: 2170 | U2: 0 | V2: 2170 | W2: 0 | X2: 0 | Y2: 2170 | Z2: 1 | AA2: 1 | AB2: 5 | AC2: Otros | AD2: 1806 | AE2: 31117 | AF2: CARPINTERIA | AG2: EVENTOS | AH2: paid | AI2: Pagado | AJ2: 6743 | AK2: 6329102 SERVICIOS DIVERSOS | AL2: [[{'codigo': 138, 'nom_distribucion': 'Administrativo', 'sub_categoria': 'Acondicionamiento', 'porcentaje': '100.00'}]] | AT2: =+CONCATENATE(A2,"-",B2) -> E001-00000068 | AU2: =+IF(Z2=1,V2,IF(Z2=2,V2*AA2)) -> 2170 | AV2: =+IF(Z2=1,X2,IF(Z2=2,X2*AA2)) -> 0 | AW2: =+IF(Z2=1,Y2,IF(Z2=2,Y2*AA2)) -> 2170
A3: F002 | B3: 00001584 | C3: COLABORATIVA S.A.C. | D3: 45944 | E3: 45957.432 | F3: PRAGMATIC S.A.C. | G3: Proveedor | H3: RUC | I3: 20607097039 | J3: [{'codigo_producto': 1956, 'cantidad': '1', 'valor_unitario': 450.0, 'precio_unitario': 531.0, 'descuento': 0.0, 'subtotal': 450.0, 'porcentaje_de_igv': '18.00', 'igv': 81.0, 'total': 531.0, 'moneda': '1', 'tipo_de_cambio': 1.0, 'id_tipo_gasto': 2, 'nom_tipo_gasto': 'Servicios', 'id_proveedor': 565, 'id_producto': 31114, 'nom_producto': 'SERVICIO DE CAPACITACION', 'categoria_producto': 'EVENTOS', 'id_estado': 'paid', 'nombre_estado': 'Pagado', 'evento': {'id_evento': '', 'nom_evento': '', 'fecha_hora_ini_event': '', 'fecha_hora_fin_event': '', 'id_organizador': '', 'nom_organizador': '', 'tipo_organizador': ''}, 'id_cuenta': 6740, 'nom_cuenta': '6327106 SERVICIOS INFORMATICOS', 'distribucion_analitica': [[{'codigo': '', 'nom_distribucion': '', 'sub_categoria': '', 'porcentaje': '100.00'}]]}] | K3: 45944 | Q3: 1956 | R3: 1 | S3: 450 | T3: 531 | U3: 0 | V3: 450 | W3: 18 | X3: 81 | Y3: 531 | Z3: 1 | AA3: 1 | AB3: 2 | AC3: Servicios | AD3: 565 | AE3: 31114 | AF3: SERVICIO DE CAPACITACION | AG3: EVENTOS | AH3: paid | AI3: Pagado | AJ3: 6740 | AK3: 6327106 SERVICIOS INFORMATICOS | AL3: [[{'codigo': '', 'nom_distribucion': '', 'sub_categoria': '', 'porcentaje': '100.00'}]] | AT3: =+CONCATENATE(A3,"-",B3) -> F002-00001584 | AU3: =+IF(Z3=1,V3,IF(Z3=2,V3*AA3)) -> 450 | AV3: =+IF(Z3=1,X3,IF(Z3=2,X3*AA3)) -> 81 | AW3: =+IF(Z3=1,Y3,IF(Z3=2,Y3*AA3)) -> 531
A4: E001 | B4: 00000005 | C4: COLABORATIVA S.A.C. | D4: 45943 | E4: 45957.529 | F4: GUTIERREZ PETIT MARIA ANGEL | H4: DNI | I4: 61455425 | J4: [{'codigo_producto': 2029, 'cantidad': '1', 'valor_unitario': 3550.0, 'precio_unitario': 3550.0, 'descuento': 0.0, 'subtotal': 3550.0, 'porcentaje_de_igv': '0.00', 'igv': 0.0, 'total': 3550.0, 'moneda': '1', 'tipo_de_cambio': 1.0, 'id_tipo_gasto': 2, 'nom_tipo_gasto': 'Servicios', 'id_proveedor': 6473, 'id_producto': 31041, 'nom_producto': 'Servicio de movilidad', 'categoria_producto': 'EVENTOS', 'id_estado': 'paid', 'nombre_estado': 'Pagado', 'evento': {'id_evento': '', 'nom_evento': '', 'fecha_hora_ini_event': '', 'fecha_hora_fin_event': '', 'id_organizador': '', 'nom_organizador': '', 'tipo_organizador': ''}, 'id_cuenta': 6723, 'nom_cuenta': '6311200 MOVILIDAD', 'distribucion_analitica': [[{'codigo': '', 'nom_distribucion': '', 'sub_categoria': '', 'porcentaje': '100.00'}]]}] | K4: 45943 | Q4: 2029 | R4: 1 | S4: 3550 | T4: 3550 | U4: 0 | V4: 3550 | W4: 0 | X4: 0 | Y4: 3550 | Z4: 1 | AA4: 1 | AB4: 2 | AC4: Servicios | AD4: 6473 | AE4: 31041 | AF4: Servicio de movilidad | AG4: EVENTOS | AH4: paid | AI4: Pagado | AJ4: 6723 | AK4: 6311200 MOVILIDAD | AL4: [[{'codigo': '', 'nom_distribucion': '', 'sub_categoria': '', 'porcentaje': '100.00'}]] | AT4: =+CONCATENATE(A4,"-",B4) -> E001-00000005 | AU4: =+IF(Z4=1,V4,IF(Z4=2,V4*AA4)) -> 3550 | AV4: =+IF(Z4=1,X4,IF(Z4=2,X4*AA4)) -> 0 | AW4: =+IF(Z4=1,Y4,IF(Z4=2,Y4*AA4)) -> 3550
A5: E001 | B5: 00000039 | C5: COLABORATIVA S.A.C. | D5: 45943 | E5: 45957.396 | F5: CARMEN CRUZ MILAGROS ZONALI | H5: RUC | I5: 10767791416 | J5: [{'codigo_producto': 2258, 'cantidad': '1', 'valor_unitario': 1640.0, 'precio_unitario': 1640.0, 'descuento': 0.0, 'subtotal': 1640.0, 'porcentaje_de_igv': '0.00', 'igv': 0.0, 'total': 1640.0, 'moneda': '1', 'tipo_de_cambio': 1.0, 'id_tipo_gasto': 2, 'nom_tipo_gasto': 'Servicios', 'id_proveedor': 1553, 'id_producto': 31013, 'nom_producto': 'SERV VALIDADORES ', 'categoria_producto': 'SERVICIOS', 'id_estado': 'paid', 'nombre_estado': 'Pagado', 'evento': {'id_evento': '', 'nom_evento': '', 'fecha_hora_ini_event': '', 'fecha_hora_fin_event': '', 'id_organizador': '', 'nom_organizador': '', 'tipo_organizador': ''}, 'id_cuenta': 6743, 'nom_cuenta': '6329102 SERVICIOS DIVERSOS', 'distribucion_analitica': [[{'codigo': 103, 'nom_distribucion': 'Validadores', 'sub_categoria': 'Personal temporal', 'porcentaje': '100.00'}]]}] | K5: 45943 | Q5: 2258 | R5: 1 | S5: 1640 | T5: 1640 | U5: 0 | V5: 1640 | W5: 0 | X5: 0 | Y5: 1640 | Z5: 1 | AA5: 1 | AB5: 2 | AC5: Servicios | AD5: 1553 | AE5: 31013 | AF5: SERV VALIDADORES | AG5: SERVICIOS | AH5: paid | AI5: Pagado | AJ5: 6743 | AK5: 6329102 SERVICIOS DIVERSOS | AL5: [[{'codigo': 103, 'nom_distribucion': 'Validadores', 'sub_categoria': 'Personal temporal', 'porcentaje': '100.00'}]] | AT5: =+CONCATENATE(A5,"-",B5) -> E001-00000039 | AU5: =+IF(Z5=1,V5,IF(Z5=2,V5*AA5)) -> 1640 | AV5: =+IF(Z5=1,X5,IF(Z5=2,X5*AA5)) -> 0 | AW5: =+IF(Z5=1,Y5,IF(Z5=2,Y5*AA5)) -> 1640
A6: F052 | B6: 01689541 | C6: COLABORATIVA S.A.C. | D6: 45943 | E6: 45957.517 | F6: MAPFRE PERU S.A. | G6: Proveedor | H6: RUC | I6: 20517182673 | J6: [{'codigo_producto': 1857, 'cantidad': '4', 'valor_unitario': 56.25, 'precio_unitario': 66.375, 'descuento': 0.0, 'subtotal': 225.0, 'porcentaje_de_igv': '18.00', 'igv': 40.5, 'total': 265.5, 'moneda': '1', 'tipo_de_cambio': 1.0, 'id_tipo_gasto': 5, 'nom_tipo_gasto': 'Otros', 'id_proveedor': 529, 'id_producto': 31036, 'nom_producto': 'SCTR', 'categoria_producto': 'EVENTOS', 'id_estado': 'paid', 'nombre_estado': 'Pagado', 'evento': {'id_evento': '', 'nom_evento': '', 'fecha_hora_ini_event': '', 'fecha_hora_fin_event': '', 'id_organizador': '', 'nom_organizador': '', 'tipo_organizador': ''}, 'id_cuenta': 6797, 'nom_cuenta': '6511101 SEGURO SCTR', 'distribucion_analitica': [[{'codigo': 130, 'nom_distribucion': 'RR.HH', 'sub_categoria': 'Seguridad y salud laboral', 'porcentaje': '100.00'}]]}] | K6: 45943 | Q6: 1857 | R6: 4 | S6: 56.25 | T6: 66.375 | U6: 0 | V6: 225 | W6: 18 | X6: 40.5 | Y6: 265.5 | Z6: 1 | AA6: 1 | AB6: 5 | AC6: Otros | AD6: 529 | AE6: 31036 | AF6: SCTR | AG6: EVENTOS | AH6: paid | AI6: Pagado | AJ6: 6797 | AK6: 6511101 SEGURO SCTR | AL6: [[{'codigo': 130, 'nom_distribucion': 'RR.HH', 'sub_categoria': 'Seguridad y salud laboral', 'porcentaje': '100.00'}]] | AT6: =+CONCATENATE(A6,"-",B6) -> F052-01689541 | AU6: =+IF(Z6=1,V6,IF(Z6=2,V6*AA6)) -> 225 | AV6: =+IF(Z6=1,X6,IF(Z6=2,X6*AA6)) -> 40.5 | AW6: =+IF(Z6=1,Y6,IF(Z6=2,Y6*AA6)) -> 265.5
A7: F250 | B7: 00000900 | C7: COLABORATIVA S.A.C. | D7: 45943 | E7: 45957.441 | F7: DOLCE CAPRICCIO SAC | G7: Proveedor | H7: RUC | I7: 20475815247 | J7: [{'codigo_producto': 1957, 'cantidad': '1', 'valor_unitario': 101.69, 'precio_unitario': 120.0, 'descuento': 0.0, 'subtotal': 101.69, 'porcentaje_de_igv': '18.01', 'igv': 18.310000000000002, 'total': 120.0, 'moneda': '1', 'tipo_de_cambio': 1.0, 'id_tipo_gasto': 5, 'nom_tipo_gasto': 'Otros', 'id_proveedor': 514, 'id_producto': 31017, 'nom_producto': 'TORTA', 'categoria_producto': 'EVENTOS', 'id_estado': 'paid', 'nombre_estado': 'Pagado', 'evento': {'id_evento': '', 'nom_evento': '', 'fecha_hora_ini_event': '', 'fecha_hora_fin_event': '', 'id_organizador': '', 'nom_organizador': '', 'tipo_organizador': ''}, 'id_cuenta': 6726, 'nom_cuenta': '6314100 AlimentaciÃ³n', 'distribucion_analitica': [[{'codigo': 97, 'nom_distribucion': 'RR.HH', 'sub_categoria': 'Bienestar', 'porcentaje': '100.00'}]]}] | K7: 45943 | Q7: 1957 | R7: 1 | S7: 101.69 | T7: 120 | U7: 0 | V7: 101.69 | W7: 18.01 | X7: 18.31 | Y7: 120 | Z7: 1 | AA7: 1 | AB7: 5 | AC7: Otros | AD7: 514 | AE7: 31017 | AF7: TORTA | AG7: EVENTOS | AH7: paid | AI7: Pagado | AJ7: 6726 | AK7: 6314100 AlimentaciÃ³n | AL7: [[{'codigo': 97, 'nom_distribucion': 'RR.HH', 'sub_categoria': 'Bienestar', 'porcentaje': '100.00'}]] | AT7: =+CONCATENATE(A7,"-",B7) -> F250-00000900 | AU7: =+IF(Z7=1,V7,IF(Z7=2,V7*AA7)) -> 101.69 | AV7: =+IF(Z7=1,X7,IF(Z7=2,X7*AA7)) -> 18.31 | AW7: =+IF(Z7=1,Y7,IF(Z7=2,Y7*AA7)) -> 120
A8: E001 | B8: 20 | C8: COLABORATIVA S.A.C. | D8: 45943 | E8: 45957.521 | F8: VARGAS HUARCAYA DANIELA RUBI | H8: DNI | I8: 75871275 | J8: [{'codigo_producto': 1939, 'cantidad': '1', 'valor_unitario': 5400.0, 'precio_unitario': 5400.0, 'descuento': 0.0, 'subtotal': 5400.0, 'porcentaje_de_igv': '0.00', 'igv': 0.0, 'total': 5400.0, 'moneda': '1', 'tipo_de_cambio': 1.0, 'id_tipo_gasto': 2, 'nom_tipo_gasto': 'Servicios', 'id_proveedor': 6339, 'id_producto': 31001, 'nom_producto': 'SERVICIO DE SUPERVISION', 'categoria_producto': 'EVENTOS', 'id_estado': 'paid', 'nombre_estado': 'Pagado', 'evento': {'id_evento': '', 'nom_evento': '', 'fecha_hora_ini_event': '', 'fecha_hora_fin_event': '', 'id_organizador': '', 'nom_organizador': '', 'tipo_organizador': ''}, 'id_cuenta': 6743, 'nom_cuenta': '6329102 SERVICIOS DIVERSOS', 'distribucion_analitica': [[{'codigo': 103, 'nom_distribucion': 'Validadores', 'sub_categoria': 'Personal temporal', 'porcentaje': '100.00'}]]}] | K8: 45943 | Q8: 1939 | R8: 1 | S8: 5400 | T8: 5400 | U8: 0 | V8: 5400 | W8: 0 | X8: 0 | Y8: 5400 | Z8: 1 | AA8: 1 | AB8: 2 | AC8: Servicios | AD8: 6339 | AE8: 31001 | AF8: SERVICIO DE SUPERVISION | AG8: EVENTOS | AH8: paid | AI8: Pagado | AJ8: 6743 | AK8: 6329102 SERVICIOS DIVERSOS | AL8: [[{'codigo': 103, 'nom_distribucion': 'Validadores', 'sub_categoria': 'Personal temporal', 'porcentaje': '100.00'}]] | AT8: =+CONCATENATE(A8,"-",B8) -> E001-20 | AU8: =+IF(Z8=1,V8,IF(Z8=2,V8*AA8)) -> 5400 | AV8: =+IF(Z8=1,X8,IF(Z8=2,X8*AA8)) -> 0 | AW8: =+IF(Z8=1,Y8,IF(Z8=2,Y8*AA8)) -> 5400
A9: E001 | B9: 18 | C9: COLABORATIVA S.A.C. | D9: 45940 | E9: 45957.747 | F9: GALVAN VARGAS DAYANA LIZBETH | H9: DNI | I9: 60680641 | J9: [{'codigo_producto': 1939, 'cantidad': '1', 'valor_unitario': 7000.0, 'precio_unitario': 7000.0, 'descuento': 0.0, 'subtotal': 7000.0, 'porcentaje_de_igv': '0.00', 'igv': 0.0, 'total': 7000.0, 'moneda': '1', 'tipo_de_cambio': 1.0, 'id_tipo_gasto': 2, 'nom_tipo_gasto': 'Servicios', 'id_proveedor': 6338, 'id_producto': 30999, 'nom_producto': 'SERVICIO DE SUPERVISION', 'categoria_producto': 'EVENTOS', 'id_estado': 'paid', 'nombre_estado': 'Pagado', 'evento': {'id_evento': '', 'nom_evento': '', 'fecha_hora_ini_event': '', 'fecha_hora_fin_event': '', 'id_organizador': '', 'nom_organizador': '', 'tipo_organizador': ''}, 'id_cuenta': 6743, 'nom_cuenta': '6329102 SERVICIOS DIVERSOS', 'distribucion_analitica': [[{'codigo': 103, 'nom_distribucion': 'Validadores', 'sub_categoria': 'Personal temporal', 'porcentaje': '100.00'}]]}] | K9: 45940 | Q9: 1939 | R9: 1 | S9: 7000 | T9: 7000 | U9: 0 | V9: 7000 | W9: 0 | X9: 0 | Y9: 7000 | Z9: 1 | AA9: 1 | AB9: 2 | AC9: Servicios | AD9: 6338 | AE9: 30999 | AF9: SERVICIO DE SUPERVISION | AG9: EVENTOS | AH9: paid | AI9: Pagado | AJ9: 6743 | AK9: 6329102 SERVICIOS DIVERSOS | AL9: [[{'codigo': 103, 'nom_distribucion': 'Validadores', 'sub_categoria': 'Personal temporal', 'porcentaje': '100.00'}]] | AT9: =+CONCATENATE(A9,"-",B9) -> E001-18 | AU9: =+IF(Z9=1,V9,IF(Z9=2,V9*AA9)) -> 7000 | AV9: =+IF(Z9=1,X9,IF(Z9=2,X9*AA9)) -> 0 | AW9: =+IF(Z9=1,Y9,IF(Z9=2,Y9*AA9)) -> 7000
A10: E001 | B10: 00000057 | C10: COLABORATIVA S.A.C. | D10: 45940 | E10: 45957.49 | F10: SOLANO CALDERON JUAN ALONSO | H10: RUC | I10: 10708131917 | J10: [{'codigo_producto': 1808, 'cantidad': '1', 'valor_unitario': 338.98, 'precio_unitario': 400.0, 'descuento': 0.0, 'subtotal': 338.98, 'porcentaje_de_igv': '18.00', 'igv': 61.01999999999998, 'total': 400.0, 'moneda': '1', 'tipo_de_cambio': 1.0, 'id_tipo_gasto': 2, 'nom_tipo_gasto': 'Servicios', 'id_proveedor': 1816, 'id_producto': 30981, 'nom_producto': 'Asesoria legal', 'categoria_producto': 'SERVICIOS', 'id_estado': 'paid', 'nombre_estado': 'Pagado', 'evento': {'id_evento': '', 'nom_evento': '', 'fecha_hora_ini_event': '', 'fecha_hora_fin_event': '', 'id_organizador': '', 'nom_organizador': '', 'tipo_organizador': ''}, 'id_cuenta': 877, 'nom_cuenta': '6329000 AsesorÃ­a y consultorÃ­a - Otros', 'distribucion_analitica': [[{'codigo': 57, 'nom_distribucion': 'Administrativo', 'sub_categoria': 'Legal', 'porcentaje': '100.00'}]]}] | K10: 45940 | Q10: 1808 | R10: 1 | S10: 338.98 | T10: 400 | U10: 0 | V10: 338.98 | W10: 18 | X10: 61.02 | Y10: 400 | Z10: 1 | AA10: 1 | AB10: 2 | AC10: Servicios | AD10: 1816 | AE10: 30981 | AF10: Asesoria legal | AG10: SERVICIOS | AH10: paid | AI10: Pagado | AJ10: 877 | AK10: 6329000 AsesorÃ­a y consultorÃ­a - Otros | AL10: [[{'codigo': 57, 'nom_distribucion': 'Administrativo', 'sub_categoria': 'Legal', 'porcentaje': '100.00'}]] | AT10: =+CONCATENATE(A10,"-",B10) -> E001-00000057 | AU10: =+IF(Z10=1,V10,IF(Z10=2,V10*AA10)) -> 338.98 | AV10: =+IF(Z10=1,X10,IF(Z10=2,X10*AA10)) -> 61.02 | AW10: =+IF(Z10=1,Y10,IF(Z10=2,Y10*AA10)) -> 400
A11: E001 | B11: 00000026 | C11: COLABORATIVA S.A.C. | D11: 45940 | E11: 45957.489 | F11: ESPINO MORI LEANDRO JOAQUIN | H11: RUC | I11: 10712300251 | J11: [{'codigo_producto': 1808, 'cantidad': '1', 'valor_unitario': 296.61, 'precio_unitario': 350.0, 'descuento': 0.0, 'subtotal': 296.61, 'porcentaje_de_igv': '18.00', 'igv': 53.389999999999986, 'total': 350.0, 'moneda': '1', 'tipo_de_cambio': 1.0, 'id_tipo_gasto': 2, 'nom_tipo_gasto': 'Servicios', 'id_proveedor': 1642, 'id_producto': 30978, 'nom_producto': 'Asesoria legal', 'categoria_producto': 'SERVICIOS', 'id_estado': 'paid', 'nombre_estado': 'Pagado', 'evento': {'id_evento': '', 'nom_evento': '', 'fecha_hora_ini_event': '', 'fecha_hora_fin_event': '', 'id_organizador': '', 'nom_organizador': '', 'tipo_organizador': ''}, 'id_cuenta': 877, 'nom_cuenta': '6329000 AsesorÃ­a y consultorÃ­a - Otros', 'distribucion_analitica': [[{'codigo': 57, 'nom_distribucion': 'Administrativo', 'sub_categoria': 'Legal', 'porcentaje': '100.00'}]]}] | K11: 45940 | Q11: 1808 | R11: 1 | S11: 296.61 | T11: 350 | U11: 0 | V11: 296.61 | W11: 18 | X11: 53.39 | Y11: 350 | Z11: 1 | AA11: 1 | AB11: 2 | AC11: Servicios | AD11: 1642 | AE11: 30978 | AF11: Asesoria legal | AG11: SERVICIOS | AH11: paid | AI11: Pagado | AJ11: 877 | AK11: 6329000 AsesorÃ­a y consultorÃ­a - Otros | AL11: [[{'codigo': 57, 'nom_distribucion': 'Administrativo', 'sub_categoria': 'Legal', 'porcentaje': '100.00'}]] | AT11: =+CONCATENATE(A11,"-",B11) -> E001-00000026 | AU11: =+IF(Z11=1,V11,IF(Z11=2,V11*AA11)) -> 296.61 | AV11: =+IF(Z11=1,X11,IF(Z11=2,X11*AA11)) -> 53.39 | AW11: =+IF(Z11=1,Y11,IF(Z11=2,Y11*AA11)) -> 350
A12: E001 | B12: 00000013 | C12: COLABORATIVA S.A.C. | D12: 45940 | E12: 45957.536 | F12: KUNTUR PRO S.A.C. | H12: RUC | I12: 20614142651 | J12: [{'codigo_producto': 2313, 'cantidad': '1', 'valor_unitario': 1000.0, 'precio_unitario': 1180.0, 'descuento': 0.0, 'subtotal': 1000.0, 'porcentaje_de_igv': '18.00', 'igv': 180.0, 'total': 1180.0, 'moneda': '1', 'tipo_de_cambio': 1.0, 'id_tipo_gasto': 5, 'nom_tipo_gasto': 'Otros', 'id_proveedor': 2741, 'id_producto': 30984, 'nom_producto': 'PRODUCCION', 'categoria_producto': 'EVENTOS', 'id_estado': 'paid', 'nombre_estado': 'Pagado', 'evento': {'id_evento': '', 'nom_evento': '', 'fecha_hora_ini_event': '', 'fecha_hora_fin_event': '', 'id_organizador': '', 'nom_organizador': '', 'tipo_organizador': ''}, 'id_cuenta': 6743, 'nom_cuenta': '6329102 SERVICIOS DIVERSOS', 'distribucion_analitica': [[{'codigo': 96, 'nom_distribucion': 'RR.HH', 'sub_categoria': 'Act. de IntegraciÃ³n', 'porcentaje': '100.00'}]]}] | K12: 45940 | Q12: 2313 | R12: 1 | S12: 1000 | T12: 1180 | U12: 0 | V12: 1000 | W12: 18 | X12: 180 | Y12: 1180 | Z12: 1 | AA12: 1 | AB12: 5 | AC12: Otros | AD12: 2741 | AE12: 30984 | AF12: PRODUCCION | AG12: EVENTOS | AH12: paid | AI12: Pagado | AJ12: 6743 | AK12: 6329102 SERVICIOS DIVERSOS | AL12: [[{'codigo': 96, 'nom_distribucion': 'RR.HH', 'sub_categoria': 'Act. de IntegraciÃ³n', 'porcentaje': '100.00'}]] | AT12: =+CONCATENATE(A12,"-",B12) -> E001-00000013 | AU12: =+IF(Z12=1,V12,IF(Z12=2,V12*AA12)) -> 1000 | AV12: =+IF(Z12=1,X12,IF(Z12=2,X12*AA12)) -> 180 | AW12: =+IF(Z12=1,Y12,IF(Z12=2,Y12*AA12)) -> 1180
A13: F003 | B13: 00001183 | C13: COLABORATIVA S.A.C. | D13: 45940 | E13: 45957.395 | F13: MALBEC SAC | H13: RUC | I13: 20606014113 | J13: [{'codigo_producto': 1912, 'cantidad': '1', 'valor_unitario': 462.0, 'precio_unitario': 462.0, 'descuento': 0.0, 'subtotal': 462.0, 'porcentaje_de_igv': '0.00', 'igv': 0.0, 'total': 462.0, 'moneda': '1', 'tipo_de_cambio': 1.0, 'id_tipo_gasto': 5, 'nom_tipo_gasto': 'Otros', 'id_proveedor': 1529, 'id_producto': 30953, 'nom_producto': 'ALMUERZO', 'categoria_producto': 'EVENTOS', 'id_estado': 'paid', 'nombre_estado': 'Pagado', 'evento': {'id_evento': '', 'nom_evento': '', 'fecha_hora_ini_event': '', 'fecha_hora_fin_event': '', 'id_organizador': '', 'nom_organizador': '', 'tipo_organizador': ''}, 'id_cuenta': 6726, 'nom_cuenta': '6314100 AlimentaciÃ³n', 'distribucion_analitica': [[{'codigo': 145, 'nom_distribucion': 'Administrativo', 'sub_categoria': 'Gerencia', 'porcentaje': '100.00'}]]}] | K13: 45940 | Q13: 1912 | R13: 1 | S13: 462 | T13: 462 | U13: 0 | V13: 462 | W13: 0 | X13: 0 | Y13: 462 | Z13: 1 | AA13: 1 | AB13: 5 | AC13: Otros | AD13: 1529 | AE13: 30953 | AF13: ALMUERZO | AG13: EVENTOS | AH13: paid | AI13: Pagado | AJ13: 6726 | AK13: 6314100 AlimentaciÃ³n | AL13: [[{'codigo': 145, 'nom_distribucion': 'Administrativo', 'sub_categoria': 'Gerencia', 'porcentaje': '100.00'}]] | AT13: =+CONCATENATE(A13,"-",B13) -> F003-00001183 | AU13: =+IF(Z13=1,V13,IF(Z13=2,V13*AA13)) -> 462 | AV13: =+IF(Z13=1,X13,IF(Z13=2,X13*AA13)) -> 0 | AW13: =+IF(Z13=1,Y13,IF(Z13=2,Y13*AA13)) -> 462
A14: E001 | B14: 00000493 | C14: COLABORATIVA S.A.C. | D14: 45939 | E14: 45957.447 | F14: EURO CARS PERU S.A.C. | H14: RUC | I14: 20608892215 | J14: [{'codigo_producto': 2026, 'cantidad': '1', 'valor_unitario': 84.75, 'precio_unitario': 100.01, 'descuento': 0.0, 'subtotal': 84.75, 'porcentaje_de_igv': '18.01', 'igv': 15.260000000000005, 'total': 100.01, 'moneda': '1', 'tipo_de_cambio': 1.0, 'id_tipo_gasto': 5, 'nom_tipo_gasto': 'Otros', 'id_proveedor': 1579, 'id_producto': 30926, 'nom_producto': 'SERVICIO DE MANTENIMIENTO', 'categoria_producto': 'EVENTOS', 'id_estado': 'paid', 'nombre_estado': 'Pagado', 'evento': {'id_evento': '', 'nom_evento': '', 'fecha_hora_ini_event': '', 'fecha_hora_fin_event': '', 'id_organizador': '', 'nom_organizador': '', 'tipo_organizador': ''}, 'id_cuenta': 877, 'nom_cuenta': '6329000 AsesorÃ­a y consultorÃ­a - Otros', 'distribucion_analitica': [[{'codigo': '', 'nom_distribucion': '', 'sub_categoria': '', 'porcentaje': '100.00'}]]}, {'codigo_producto': 2026, 'cantidad': '1', 'valor_unitario': 25.42, 'precio_unitario': 30.0, 'descuento': 0.0, 'subtotal': 25.42, 'porcentaje_de_igv': '18.02', 'igv': 4.579999999999998, 'total': 30.0, 'moneda': '1', 'tipo_de_cambio': 1.0, 'id_tipo_gasto': 2, 'nom_tipo_gasto': 'Servicios', 'id_proveedor': 1579, 'id_producto': 30927, 'nom_producto': 'SERVICIO DE MANTENIMIENTO', 'categoria_producto': 'EVENTOS', 'id_estado': 'paid', 'nombre_estado': 'Pagado', 'evento': {'id_evento': '', 'nom_evento': '', 'fecha_hora_ini_event': '', 'fecha_hora_fin_event': '', 'id_organizador': '', 'nom_organizador': '', 'tipo_organizador': ''}, 'id_cuenta': 877, 'nom_cuenta': '6329000 AsesorÃ­a y consultorÃ­a - Otros', 'distribucion_analitica': [[{'codigo': '', 'nom_distribucion': '', 'sub_categoria': '', 'porcentaje': '100.00'}]]}] | K14: 45939 | Q14: 2026 | R14: 1 | S14: 84.75 | T14: 100.01 | U14: 0 | V14: 84.75 | W14: 18.01 | X14: 15.26 | Y14: 100.01 | Z14: 1 | AA14: 1 | AB14: 5 | AC14: Otros | AD14: 1579 | AE14: 30926 | AF14: SERVICIO DE MANTENIMIENTO | AG14: EVENTOS | AH14: paid | AI14: Pagado | AJ14: 877 | AK14: 6329000 AsesorÃ­a y consultorÃ­a - Otros | AL14: [[{'codigo': '', 'nom_distribucion': '', 'sub_categoria': '', 'porcentaje': '100.00'}]] | AT14: =+CONCATENATE(A14,"-",B14) -> E001-00000493 | AU14: =+IF(Z14=1,V14,IF(Z14=2,V14*AA14)) -> 84.75 | AV14: =+IF(Z14=1,X14,IF(Z14=2,X14*AA14)) -> 15.26 | AW14: =+IF(Z14=1,Y14,IF(Z14=2,Y14*AA14)) -> 100.01
A15: E001 | B15: 00000493 | C15: COLABORATIVA S.A.C. | D15: 45939 | E15: 45957.447 | F15: EURO CARS PERU S.A.C. | H15: RUC | I15: 20608892215 | J15: [{'codigo_producto': 2026, 'cantidad': '1', 'valor_unitario': 84.75, 'precio_unitario': 100.01, 'descuento': 0.0, 'subtotal': 84.75, 'porcentaje_de_igv': '18.01', 'igv': 15.260000000000005, 'total': 100.01, 'moneda': '1', 'tipo_de_cambio': 1.0, 'id_tipo_gasto': 5, 'nom_tipo_gasto': 'Otros', 'id_proveedor': 1579, 'id_producto': 30926, 'nom_producto': 'SERVICIO DE MANTENIMIENTO', 'categoria_producto': 'EVENTOS', 'id_estado': 'paid', 'nombre_estado': 'Pagado', 'evento': {'id_evento': '', 'nom_evento': '', 'fecha_hora_ini_event': '', 'fecha_hora_fin_event': '', 'id_organizador': '', 'nom_organizador': '', 'tipo_organizador': ''}, 'id_cuenta': 877, 'nom_cuenta': '6329000 AsesorÃ­a y consultorÃ­a - Otros', 'distribucion_analitica': [[{'codigo': '', 'nom_distribucion': '', 'sub_categoria': '', 'porcentaje': '100.00'}]]}, {'codigo_producto': 2026, 'cantidad': '1', 'valor_unitario': 25.42, 'precio_unitario': 30.0, 'descuento': 0.0, 'subtotal': 25.42, 'porcentaje_de_igv': '18.02', 'igv': 4.579999999999998, 'total': 30.0, 'moneda': '1', 'tipo_de_cambio': 1.0, 'id_tipo_gasto': 2, 'nom_tipo_gasto': 'Servicios', 'id_proveedor': 1579, 'id_producto': 30927, 'nom_producto': 'SERVICIO DE MANTENIMIENTO', 'categoria_producto': 'EVENTOS', 'id_estado': 'paid', 'nombre_estado': 'Pagado', 'evento': {'id_evento': '', 'nom_evento': '', 'fecha_hora_ini_event': '', 'fecha_hora_fin_event': '', 'id_organizador': '', 'nom_organizador': '', 'tipo_organizador': ''}, 'id_cuenta': 877, 'nom_cuenta': '6329000 AsesorÃ­a y consultorÃ­a - Otros', 'distribucion_analitica': [[{'codigo': '', 'nom_distribucion': '', 'sub_categoria': '', 'porcentaje': '100.00'}]]}] | K15: 45939 | Q15: 2026 | R15: 1 | S15: 25.42 | T15: 30 | U15: 0 | V15: 25.42 | W15: 18.02 | X15: 4.58 | Y15: 30 | Z15: 1 | AA15: 1 | AB15: 2 | AC15: Servicios | AD15: 1579 | AE15: 30927 | AF15: SERVICIO DE MANTENIMIENTO | AG15: EVENTOS | AH15: paid | AI15: Pagado | AJ15: 877 | AK15: 6329000 AsesorÃ­a y consultorÃ­a - Otros | AL15: [[{'codigo': '', 'nom_distribucion': '', 'sub_categoria': '', 'porcentaje': '100.00'}]] | AT15: =+CONCATENATE(A15,"-",B15) -> E001-00000493 | AU15: =+IF(Z15=1,V15,IF(Z15=2,V15*AA15)) -> 25.42 | AV15: =+IF(Z15=1,X15,IF(Z15=2,X15*AA15)) -> 4.58 | AW15: =+IF(Z15=1,Y15,IF(Z15=2,Y15*AA15)) -> 30
A16: E001 | B16: 00000492 | C16: COLABORATIVA S.A.C. | D16: 45939 | E16: 45957.445 | F16: EURO CARS PERU S.A.C. | H16: RUC | I16: 20608892215 | J16: [{'codigo_producto': 2026, 'cantidad': '1', 'valor_unitario': 186.44, 'precio_unitario': 220.0, 'descuento': 0.0, 'subtotal': 186.44, 'porcentaje_de_igv': '18.00', 'igv': 33.56, 'total': 220.0, 'moneda': '1', 'tipo_de_cambio': 1.0, 'id_tipo_gasto': 5, 'nom_tipo_gasto': 'Otros', 'id_proveedor': 1579, 'id_producto': 30915, 'nom_producto': 'SERVICIO DE MANTENIMIENTO', 'categoria_producto': 'EVENTOS', 'id_estado': 'paid', 'nombre_estado': 'Pagado', 'evento': {'id_evento': '', 'nom_evento': '', 'fecha_hora_ini_event': '', 'fecha_hora_fin_event': '', 'id_organizador': '', 'nom_organizador': '', 'tipo_organizador': ''}, 'id_cuenta': 877, 'nom_cuenta': '6329000 AsesorÃ­a y consultorÃ­a - Otros', 'distribucion_analitica': [[{'codigo': '', 'nom_distribucion': '', 'sub_categoria': '', 'porcentaje': '100.00'}]]}, {'codigo_producto': 2026, 'cantidad': '1', 'valor_unitario': 1.7, 'precio_unitario': 2.01, 'descuento': 0.0, 'subtotal': 1.7, 'porcentaje_de_igv': '18.24', 'igv': 0.30999999999999983, 'total': 2.01, 'moneda': '1', 'tipo_de_cambio': 1.0, 'id_tipo_gasto': 5, 'nom_tipo_gasto': 'Otros', 'id_proveedor': 1579, 'id_producto': 30916, 'nom_producto': 'SERVICIO DE MANTENIMIENTO', 'categoria_producto': 'EVENTOS', 'id_estado': 'paid', 'nombre_estado': 'Pagado', 'evento': {'id_evento': '', 'nom_evento': '', 'fecha_hora_ini_event': '', 'fecha_hora_fin_event': '', 'id_organizador': '', 'nom_organizador': '', 'tipo_organizador': ''}, 'id_cuenta': 877, 'nom_cuenta': '6329000 AsesorÃ­a y consultorÃ­a - Otros', 'distribucion_analitica': [[{'codigo': '', 'nom_distribucion': '', 'sub_categoria': '', 'porcentaje': '100.00'}]]}, {'codigo_producto': 2026, 'cantidad': '1', 'valor_unitario': 22.03, 'precio_unitario': 26.0, 'descuento': 0.0, 'subtotal': 22.03, 'porcentaje_de_igv': '18.02', 'igv': 3.969999999999999, 'total': 26.0, 'moneda': '1', 'tipo_de_cambio': 1.0, 'id_tipo_gasto': 5, 'nom_tipo_gasto': 'Otros', 'id_proveedor': 1579, 'id_producto': 30917, 'nom_producto': 'SERVICIO DE MANTENIMIENTO', 'categoria_producto': 'EVENTOS', 'id_estado': 'paid', 'nombre_estado': 'Pagado', 'evento': {'id_evento': '', 'nom_evento': '', 'fecha_hora_ini_event': '', 'fecha_hora_fin_event': '', 'id_organizador': '', 'nom_organizador': '', 'tipo_organizador': ''}, 'id_cuenta': 877, 'nom_cuenta': '6329000 AsesorÃ­a y consultorÃ­a - Otros', 'distribucion_analitica': [[{'codigo': '', 'nom_distribucion': '', 'sub_categoria': '', 'porcentaje': '100.00'}]]}, {'codigo_producto': 2026, 'cantidad': '1', 'valor_unitario': 42.37, 'precio_unitario': 50.0, 'descuento': 0.0, 'subtotal': 42.37, 'porcentaje_de_igv': '18.01', 'igv': 7.630000000000003, 'total': 50.0, 'moneda': '1', 'tipo_de_cambio': 1.0, 'id_tipo_gasto': 5, 'nom_tipo_gasto': 'Otros', 'id_proveedor': 1579, 'id_producto': 30918, 'nom_producto': 'SERVICIO DE MANTENIMIENTO', 'categoria_producto': 'EVENTOS', 'id_estado': 'paid', 'nombre_estado': 'Pagado', 'evento': {'id_evento': '', 'nom_evento': '', 'fecha_hora_ini_event': '', 'fecha_hora_fin_event': '', 'id_organizador': '', 'nom_organizador': '', 'tipo_organizador': ''}, 'id_cuenta': 877, 'nom_cuenta': '6329000 AsesorÃ­a y consultorÃ­a - Otros', 'distribucion_analitica': [[{'codigo': '', 'nom_distribucion': '', 'sub_categoria': '', 'porcentaje': '100.00'}]]}, {'codigo_producto': 2026, 'cantidad': '1', 'valor_unitario': 23.73, 'precio_unitario': 28.0, 'descuento': 0.0, 'subtotal': 23.73, 'porcentaje_de_igv': '17.99', 'igv': 4.27, 'total': 28.0, 'moneda': '1', 'tipo_de_cambio': 1.0, 'id_tipo_gasto': 5, 'nom_tipo_gasto': 'Otros', 'id_proveedor': 1579, 'id_producto': 30919, 'nom_producto': 'SERVICIO DE MANTENIMIENTO', 'categoria_producto': 'EVENTOS', 'id_estado': 'paid', 'nombre_estado': 'Pagado', 'evento': {'id_evento': '', 'nom_evento': '', 'fecha_hora_ini_event': '', 'fecha_hora_fin_event': '', 'id_organizador': '', 'nom_organizador': '', 'tipo_organizador': ''}, 'id_cuenta': 877, 'nom_cuenta': '6329000 AsesorÃ­a y consultorÃ­a - Otros', 'distribucion_analitica': [[{'codigo': '', 'nom_distribucion': '', 'sub_categoria': '', 'porcentaje': '100.00'}]]}, {'codigo_producto': 2026, 'cantidad': '1', 'valor_unitario': 5.93, 'precio_unitario': 7.0, 'descuento': 0.0, 'subtotal': 5.93, 'porcentaje_de_igv': '18.04', 'igv': 1.0700000000000003, 'total': 7.0, 'moneda': '1', 'tipo_de_cambio': 1.0, 'id_tipo_gasto': 5, 'nom_tipo_gasto': 'Otros', 'id_proveedor': 1579, 'id_producto': 30920, 'nom_producto': 'SERVICIO DE MANTENIMIENTO', 'categoria_producto': 'EVENTOS', 'id_estado': 'paid', 'nombre_estado': 'Pagado', 'evento': {'id_evento': '', 'nom_evento': '', 'fecha_hora_ini_event': '', 'fecha_hora_fin_event': '', 'id_organizador': '', 'nom_organizador': '', 'tipo_organizador': ''}, 'id_cuenta': 877, 'nom_cuenta': '6329000 AsesorÃ­a y consultorÃ­a - Otros', 'distribucion_analitica': [[{'codigo': '', 'nom_distribucion': '', 'sub_categoria': '', 'porcentaje': '100.00'}]]}, {'codigo_producto': 2026, 'cantidad': '1', 'valor_unitario': 50.85, 'precio_unitario': 60.0, 'descuento': 0.0, 'subtotal': 50.85, 'porcentaje_de_igv': '17.99', 'igv': 9.149999999999999, 'total': 60.0, 'moneda': '1', 'tipo_de_cambio': 1.0, 'id_tipo_gasto': 5, 'nom_tipo_gasto': 'Otros', 'id_proveedor': 1579, 'id_producto': 30921, 'nom_producto': 'SERVICIO DE MANTENIMIENTO', 'categoria_producto': 'EVENTOS', 'id_estado': 'paid', 'nombre_estado': 'Pagado', 'evento': {'id_evento': '', 'nom_evento': '', 'fecha_hora_ini_event': '', 'fecha_hora_fin_event': '', 'id_organizador': '', 'nom_organizador': '', 'tipo_organizador': ''}, 'id_cuenta': 877, 'nom_cuenta': '6329000 AsesorÃ­a y consultorÃ­a - Otros', 'distribucion_analitica': [[{'codigo': '', 'nom_distribucion': '', 'sub_categoria': '', 'porcentaje': '100.00'}]]}, {'codigo_producto': 2026, 'cantidad': '1', 'valor_unitario': 22.88, 'precio_unitario': 27.0, 'descuento': 0.0, 'subtotal': 22.88, 'porcentaje_de_igv': '18.01', 'igv': 4.120000000000001, 'total': 27.0, 'moneda': '1', 'tipo_de_cambio': 1.0, 'id_tipo_gasto': 5, 'nom_tipo_gasto': 'Otros', 'id_proveedor': 1579, 'id_producto': 30922, 'nom_producto': 'SERVICIO DE MANTENIMIENTO', 'categoria_producto': 'EVENTOS', 'id_estado': 'paid', 'nombre_estado': 'Pagado', 'evento': {'id_evento': '', 'nom_evento': '', 'fecha_hora_ini_event': '', 'fecha_hora_fin_event': '', 'id_organizador': '', 'nom_organizador': '', 'tipo_organizador': ''}, 'id_cuenta': 877, 'nom_cuenta': '6329000 AsesorÃ­a y consultorÃ­a - Otros', 'distribucion_analitica': [[{'codigo': '', 'nom_distribucion': '', 'sub_categoria': '', 'porcentaje': '100.00'}]]}, {'codigo_producto': 2026, 'cantidad': '1', 'valor_unitario': 194.92, 'precio_unitario': 230.01, 'descuento': 0.0, 'subtotal': 194.92, 'porcentaje_de_igv': '18.00', 'igv': 35.09, 'total': 230.01, 'moneda': '1', 'tipo_de_cambio': 1.0, 'id_tipo_gasto': 2, 'nom_tipo_gasto': 'Servicios', 'id_proveedor': 1579, 'id_producto': 30923, 'nom_producto': 'SERVICIO DE MANTENIMIENTO', 'categoria_producto': 'EVENTOS', 'id_estado': 'paid', 'nombre_estado': 'Pagado', 'evento': {'id_evento': '', 'nom_evento': '', 'fecha_hora_ini_event': '', 'fecha_hora_fin_event': '', 'id_organizador': '', 'nom_organizador': '', 'tipo_organizador': ''}, 'id_cuenta': 877, 'nom_cuenta': '6329000 AsesorÃ­a y consultorÃ­a - Otros', 'distribucion_analitica': [[{'codigo': '', 'nom_distribucion': '', 'sub_categoria': '', 'porcentaje': '100.00'}]]}] | K16: 45939 | Q16: 2026 | R16: 1 | S16: 186.44 | T16: 220 | U16: 0 | V16: 186.44 | W16: 18 | X16: 33.56 | Y16: 220 | Z16: 1 | AA16: 1 | AB16: 5 | AC16: Otros | AD16: 1579 | AE16: 30915 | AF16: SERVICIO DE MANTENIMIENTO | AG16: EVENTOS | AH16: paid | AI16: Pagado | AJ16: 877 | AK16: 6329000 AsesorÃ­a y consultorÃ­a - Otros | AL16: [[{'codigo': '', 'nom_distribucion': '', 'sub_categoria': '', 'porcentaje': '100.00'}]] | AT16: =+CONCATENATE(A16,"-",B16) -> E001-00000492 | AU16: =+IF(Z16=1,V16,IF(Z16=2,V16*AA16)) -> 186.44 | AV16: =+IF(Z16=1,X16,IF(Z16=2,X16*AA16)) -> 33.56 | AW16: =+IF(Z16=1,Y16,IF(Z16=2,Y16*AA16)) -> 220
A17: E001 | B17: 00000492 | C17: COLABORATIVA S.A.C. | D17: 45939 | E17: 45957.445 | F17: EURO CARS PERU S.A.C. | H17: RUC | I17: 20608892215 | J17: [{'codigo_producto': 2026, 'cantidad': '1', 'valor_unitario': 186.44, 'precio_unitario': 220.0, 'descuento': 0.0, 'subtotal': 186.44, 'porcentaje_de_igv': '18.00', 'igv': 33.56, 'total': 220.0, 'moneda': '1', 'tipo_de_cambio': 1.0, 'id_tipo_gasto': 5, 'nom_tipo_gasto': 'Otros', 'id_proveedor': 1579, 'id_producto': 30915, 'nom_producto': 'SERVICIO DE MANTENIMIENTO', 'categoria_producto': 'EVENTOS', 'id_estado': 'paid', 'nombre_estado': 'Pagado', 'evento': {'id_evento': '', 'nom_evento': '', 'fecha_hora_ini_event': '', 'fecha_hora_fin_event': '', 'id_organizador': '', 'nom_organizador': '', 'tipo_organizador': ''}, 'id_cuenta': 877, 'nom_cuenta': '6329000 AsesorÃ­a y consultorÃ­a - Otros', 'distribucion_analitica': [[{'codigo': '', 'nom_distribucion': '', 'sub_categoria': '', 'porcentaje': '100.00'}]]}, {'codigo_producto': 2026, 'cantidad': '1', 'valor_unitario': 1.7, 'precio_unitario': 2.01, 'descuento': 0.0, 'subtotal': 1.7, 'porcentaje_de_igv': '18.24', 'igv': 0.30999999999999983, 'total': 2.01, 'moneda': '1', 'tipo_de_cambio': 1.0, 'id_tipo_gasto': 5, 'nom_tipo_gasto': 'Otros', 'id_proveedor': 1579, 'id_producto': 30916, 'nom_producto': 'SERVICIO DE MANTENIMIENTO', 'categoria_producto': 'EVENTOS', 'id_estado': 'paid', 'nombre_estado': 'Pagado', 'evento': {'id_evento': '', 'nom_evento': '', 'fecha_hora_ini_event': '', 'fecha_hora_fin_event': '', 'id_organizador': '', 'nom_organizador': '', 'tipo_organizador': ''}, 'id_cuenta': 877, 'nom_cuenta': '6329000 AsesorÃ­a y consultorÃ­a - Otros', 'distribucion_analitica': [[{'codigo': '', 'nom_distribucion': '', 'sub_categoria': '', 'porcentaje': '100.00'}]]}, {'codigo_producto': 2026, 'cantidad': '1', 'valor_unitario': 22.03, 'precio_unitario': 26.0, 'descuento': 0.0, 'subtotal': 22.03, 'porcentaje_de_igv': '18.02', 'igv': 3.969999999999999, 'total': 26.0, 'moneda': '1', 'tipo_de_cambio': 1.0, 'id_tipo_gasto': 5, 'nom_tipo_gasto': 'Otros', 'id_proveedor': 1579, 'id_producto': 30917, 'nom_producto': 'SERVICIO DE MANTENIMIENTO', 'categoria_producto': 'EVENTOS', 'id_estado': 'paid', 'nombre_estado': 'Pagado', 'evento': {'id_evento': '', 'nom_evento': '', 'fecha_hora_ini_event': '', 'fecha_hora_fin_event': '', 'id_organizador': '', 'nom_organizador': '', 'tipo_organizador': ''}, 'id_cuenta': 877, 'nom_cuenta': '6329000 AsesorÃ­a y consultorÃ­a - Otros', 'distribucion_analitica': [[{'codigo': '', 'nom_distribucion': '', 'sub_categoria': '', 'porcentaje': '100.00'}]]}, {'codigo_producto': 2026, 'cantidad': '1', 'valor_unitario': 42.37, 'precio_unitario': 50.0, 'descuento': 0.0, 'subtotal': 42.37, 'porcentaje_de_igv': '18.01', 'igv': 7.630000000000003, 'total': 50.0, 'moneda': '1', 'tipo_de_cambio': 1.0, 'id_tipo_gasto': 5, 'nom_tipo_gasto': 'Otros', 'id_proveedor': 1579, 'id_producto': 30918, 'nom_producto': 'SERVICIO DE MANTENIMIENTO', 'categoria_producto': 'EVENTOS', 'id_estado': 'paid', 'nombre_estado': 'Pagado', 'evento': {'id_evento': '', 'nom_evento': '', 'fecha_hora_ini_event': '', 'fecha_hora_fin_event': '', 'id_organizador': '', 'nom_organizador': '', 'tipo_organizador': ''}, 'id_cuenta': 877, 'nom_cuenta': '6329000 AsesorÃ­a y consultorÃ­a - Otros', 'distribucion_analitica': [[{'codigo': '', 'nom_distribucion': '', 'sub_categoria': '', 'porcentaje': '100.00'}]]}, {'codigo_producto': 2026, 'cantidad': '1', 'valor_unitario': 23.73, 'precio_unitario': 28.0, 'descuento': 0.0, 'subtotal': 23.73, 'porcentaje_de_igv': '17.99', 'igv': 4.27, 'total': 28.0, 'moneda': '1', 'tipo_de_cambio': 1.0, 'id_tipo_gasto': 5, 'nom_tipo_gasto': 'Otros', 'id_proveedor': 1579, 'id_producto': 30919, 'nom_producto': 'SERVICIO DE MANTENIMIENTO', 'categoria_producto': 'EVENTOS', 'id_estado': 'paid', 'nombre_estado': 'Pagado', 'evento': {'id_evento': '', 'nom_evento': '', 'fecha_hora_ini_event': '', 'fecha_hora_fin_event': '', 'id_organizador': '', 'nom_organizador': '', 'tipo_organizador': ''}, 'id_cuenta': 877, 'nom_cuenta': '6329000 AsesorÃ­a y consultorÃ­a - Otros', 'distribucion_analitica': [[{'codigo': '', 'nom_distribucion': '', 'sub_categoria': '', 'porcentaje': '100.00'}]]}, {'codigo_producto': 2026, 'cantidad': '1', 'valor_unitario': 5.93, 'precio_unitario': 7.0, 'descuento': 0.0, 'subtotal': 5.93, 'porcentaje_de_igv': '18.04', 'igv': 1.0700000000000003, 'total': 7.0, 'moneda': '1', 'tipo_de_cambio': 1.0, 'id_tipo_gasto': 5, 'nom_tipo_gasto': 'Otros', 'id_proveedor': 1579, 'id_producto': 30920, 'nom_producto': 'SERVICIO DE MANTENIMIENTO', 'categoria_producto': 'EVENTOS', 'id_estado': 'paid', 'nombre_estado': 'Pagado', 'evento': {'id_evento': '', 'nom_evento': '', 'fecha_hora_ini_event': '', 'fecha_hora_fin_event': '', 'id_organizador': '', 'nom_organizador': '', 'tipo_organizador': ''}, 'id_cuenta': 877, 'nom_cuenta': '6329000 AsesorÃ­a y consultorÃ­a - Otros', 'distribucion_analitica': [[{'codigo': '', 'nom_distribucion': '', 'sub_categoria': '', 'porcentaje': '100.00'}]]}, {'codigo_producto': 2026, 'cantidad': '1', 'valor_unitario': 50.85, 'precio_unitario': 60.0, 'descuento': 0.0, 'subtotal': 50.85, 'porcentaje_de_igv': '17.99', 'igv': 9.149999999999999, 'total': 60.0, 'moneda': '1', 'tipo_de_cambio': 1.0, 'id_tipo_gasto': 5, 'nom_tipo_gasto': 'Otros', 'id_proveedor': 1579, 'id_producto': 30921, 'nom_producto': 'SERVICIO DE MANTENIMIENTO', 'categoria_producto': 'EVENTOS', 'id_estado': 'paid', 'nombre_estado': 'Pagado', 'evento': {'id_evento': '', 'nom_evento': '', 'fecha_hora_ini_event': '', 'fecha_hora_fin_event': '', 'id_organizador': '', 'nom_organizador': '', 'tipo_organizador': ''}, 'id_cuenta': 877, 'nom_cuenta': '6329000 AsesorÃ­a y consultorÃ­a - Otros', 'distribucion_analitica': [[{'codigo': '', 'nom_distribucion': '', 'sub_categoria': '', 'porcentaje': '100.00'}]]}, {'codigo_producto': 2026, 'cantidad': '1', 'valor_unitario': 22.88, 'precio_unitario': 27.0, 'descuento': 0.0, 'subtotal': 22.88, 'porcentaje_de_igv': '18.01', 'igv': 4.120000000000001, 'total': 27.0, 'moneda': '1', 'tipo_de_cambio': 1.0, 'id_tipo_gasto': 5, 'nom_tipo_gasto': 'Otros', 'id_proveedor': 1579, 'id_producto': 30922, 'nom_producto': 'SERVICIO DE MANTENIMIENTO', 'categoria_producto': 'EVENTOS', 'id_estado': 'paid', 'nombre_estado': 'Pagado', 'evento': {'id_evento': '', 'nom_evento': '', 'fecha_hora_ini_event': '', 'fecha_hora_fin_event': '', 'id_organizador': '', 'nom_organizador': '', 'tipo_organizador': ''}, 'id_cuenta': 877, 'nom_cuenta': '6329000 AsesorÃ­a y consultorÃ­a - Otros', 'distribucion_analitica': [[{'codigo': '', 'nom_distribucion': '', 'sub_categoria': '', 'porcentaje': '100.00'}]]}, {'codigo_producto': 2026, 'cantidad': '1', 'valor_unitario': 194.92, 'precio_unitario': 230.01, 'descuento': 0.0, 'subtotal': 194.92, 'porcentaje_de_igv': '18.00', 'igv': 35.09, 'total': 230.01, 'moneda': '1', 'tipo_de_cambio': 1.0, 'id_tipo_gasto': 2, 'nom_tipo_gasto': 'Servicios', 'id_proveedor': 1579, 'id_producto': 30923, 'nom_producto': 'SERVICIO DE MANTENIMIENTO', 'categoria_producto': 'EVENTOS', 'id_estado': 'paid', 'nombre_estado': 'Pagado', 'evento': {'id_evento': '', 'nom_evento': '', 'fecha_hora_ini_event': '', 'fecha_hora_fin_event': '', 'id_organizador': '', 'nom_organizador': '', 'tipo_organizador': ''}, 'id_cuenta': 877, 'nom_cuenta': '6329000 AsesorÃ­a y consultorÃ­a - Otros', 'distribucion_analitica': [[{'codigo': '', 'nom_distribucion': '', 'sub_categoria': '', 'porcentaje': '100.00'}]]}] | K17: 45939 | Q17: 2026 | R17: 1 | S17: 1.7 | T17: 2.01 | U17: 0 | V17: 1.7 | W17: 18.24 | X17: 0.31 | Y17: 2.01 | Z17: 1 | AA17: 1 | AB17: 5 | AC17: Otros | AD17: 1579 | AE17: 30916 | AF17: SERVICIO DE MANTENIMIENTO | AG17: EVENTOS | AH17: paid | AI17: Pagado | AJ17: 877 | AK17: 6329000 AsesorÃ­a y consultorÃ­a - Otros | AL17: [[{'codigo': '', 'nom_distribucion': '', 'sub_categoria': '', 'porcentaje': '100.00'}]] | AT17: =+CONCATENATE(A17,"-",B17) -> E001-00000492 | AU17: =+IF(Z17=1,V17,IF(Z17=2,V17*AA17)) -> 1.7 | AV17: =+IF(Z17=1,X17,IF(Z17=2,X17*AA17)) -> 0.31 | AW17: =+IF(Z17=1,Y17,IF(Z17=2,Y17*AA17)) -> 2.01
A18: E001 | B18: 00000492 | C18: COLABORATIVA S.A.C. | D18: 45939 | E18: 45957.445 | F18: EURO CARS PERU S.A.C. | H18: RUC | I18: 20608892215 | J18: [{'codigo_producto': 2026, 'cantidad': '1', 'valor_unitario': 186.44, 'precio_unitario': 220.0, 'descuento': 0.0, 'subtotal': 186.44, 'porcentaje_de_igv': '18.00', 'igv': 33.56, 'total': 220.0, 'moneda': '1', 'tipo_de_cambio': 1.0, 'id_tipo_gasto': 5, 'nom_tipo_gasto': 'Otros', 'id_proveedor': 1579, 'id_producto': 30915, 'nom_producto': 'SERVICIO DE MANTENIMIENTO', 'categoria_producto': 'EVENTOS', 'id_estado': 'paid', 'nombre_estado': 'Pagado', 'evento': {'id_evento': '', 'nom_evento': '', 'fecha_hora_ini_event': '', 'fecha_hora_fin_event': '', 'id_organizador': '', 'nom_organizador': '', 'tipo_organizador': ''}, 'id_cuenta': 877, 'nom_cuenta': '6329000 AsesorÃ­a y consultorÃ­a - Otros', 'distribucion_analitica': [[{'codigo': '', 'nom_distribucion': '', 'sub_categoria': '', 'porcentaje': '100.00'}]]}, {'codigo_producto': 2026, 'cantidad': '1', 'valor_unitario': 1.7, 'precio_unitario': 2.01, 'descuento': 0.0, 'subtotal': 1.7, 'porcentaje_de_igv': '18.24', 'igv': 0.30999999999999983, 'total': 2.01, 'moneda': '1', 'tipo_de_cambio': 1.0, 'id_tipo_gasto': 5, 'nom_tipo_gasto': 'Otros', 'id_proveedor': 1579, 'id_producto': 30916, 'nom_producto': 'SERVICIO DE MANTENIMIENTO', 'categoria_producto': 'EVENTOS', 'id_estado': 'paid', 'nombre_estado': 'Pagado', 'evento': {'id_evento': '', 'nom_evento': '', 'fecha_hora_ini_event': '', 'fecha_hora_fin_event': '', 'id_organizador': '', 'nom_organizador': '', 'tipo_organizador': ''}, 'id_cuenta': 877, 'nom_cuenta': '6329000 AsesorÃ­a y consultorÃ­a - Otros', 'distribucion_analitica': [[{'codigo': '', 'nom_distribucion': '', 'sub_categoria': '', 'porcentaje': '100.00'}]]}, {'codigo_producto': 2026, 'cantidad': '1', 'valor_unitario': 22.03, 'precio_unitario': 26.0, 'descuento': 0.0, 'subtotal': 22.03, 'porcentaje_de_igv': '18.02', 'igv': 3.969999999999999, 'total': 26.0, 'moneda': '1', 'tipo_de_cambio': 1.0, 'id_tipo_gasto': 5, 'nom_tipo_gasto': 'Otros', 'id_proveedor': 1579, 'id_producto': 30917, 'nom_producto': 'SERVICIO DE MANTENIMIENTO', 'categoria_producto': 'EVENTOS', 'id_estado': 'paid', 'nombre_estado': 'Pagado', 'evento': {'id_evento': '', 'nom_evento': '', 'fecha_hora_ini_event': '', 'fecha_hora_fin_event': '', 'id_organizador': '', 'nom_organizador': '', 'tipo_organizador': ''}, 'id_cuenta': 877, 'nom_cuenta': '6329000 AsesorÃ­a y consultorÃ­a - Otros', 'distribucion_analitica': [[{'codigo': '', 'nom_distribucion': '', 'sub_categoria': '', 'porcentaje': '100.00'}]]}, {'codigo_producto': 2026, 'cantidad': '1', 'valor_unitario': 42.37, 'precio_unitario': 50.0, 'descuento': 0.0, 'subtotal': 42.37, 'porcentaje_de_igv': '18.01', 'igv': 7.630000000000003, 'total': 50.0, 'moneda': '1', 'tipo_de_cambio': 1.0, 'id_tipo_gasto': 5, 'nom_tipo_gasto': 'Otros', 'id_proveedor': 1579, 'id_producto': 30918, 'nom_producto': 'SERVICIO DE MANTENIMIENTO', 'categoria_producto': 'EVENTOS', 'id_estado': 'paid', 'nombre_estado': 'Pagado', 'evento': {'id_evento': '', 'nom_evento': '', 'fecha_hora_ini_event': '', 'fecha_hora_fin_event': '', 'id_organizador': '', 'nom_organizador': '', 'tipo_organizador': ''}, 'id_cuenta': 877, 'nom_cuenta': '6329000 AsesorÃ­a y consultorÃ­a - Otros', 'distribucion_analitica': [[{'codigo': '', 'nom_distribucion': '', 'sub_categoria': '', 'porcentaje': '100.00'}]]}, {'codigo_producto': 2026, 'cantidad': '1', 'valor_unitario': 23.73, 'precio_unitario': 28.0, 'descuento': 0.0, 'subtotal': 23.73, 'porcentaje_de_igv': '17.99', 'igv': 4.27, 'total': 28.0, 'moneda': '1', 'tipo_de_cambio': 1.0, 'id_tipo_gasto': 5, 'nom_tipo_gasto': 'Otros', 'id_proveedor': 1579, 'id_producto': 30919, 'nom_producto': 'SERVICIO DE MANTENIMIENTO', 'categoria_producto': 'EVENTOS', 'id_estado': 'paid', 'nombre_estado': 'Pagado', 'evento': {'id_evento': '', 'nom_evento': '', 'fecha_hora_ini_event': '', 'fecha_hora_fin_event': '', 'id_organizador': '', 'nom_organizador': '', 'tipo_organizador': ''}, 'id_cuenta': 877, 'nom_cuenta': '6329000 AsesorÃ­a y consultorÃ­a - Otros', 'distribucion_analitica': [[{'codigo': '', 'nom_distribucion': '', 'sub_categoria': '', 'porcentaje': '100.00'}]]}, {'codigo_producto': 2026, 'cantidad': '1', 'valor_unitario': 5.93, 'precio_unitario': 7.0, 'descuento': 0.0, 'subtotal': 5.93, 'porcentaje_de_igv': '18.04', 'igv': 1.0700000000000003, 'total': 7.0, 'moneda': '1', 'tipo_de_cambio': 1.0, 'id_tipo_gasto': 5, 'nom_tipo_gasto': 'Otros', 'id_proveedor': 1579, 'id_producto': 30920, 'nom_producto': 'SERVICIO DE MANTENIMIENTO', 'categoria_producto': 'EVENTOS', 'id_estado': 'paid', 'nombre_estado': 'Pagado', 'evento': {'id_evento': '', 'nom_evento': '', 'fecha_hora_ini_event': '', 'fecha_hora_fin_event': '', 'id_organizador': '', 'nom_organizador': '', 'tipo_organizador': ''}, 'id_cuenta': 877, 'nom_cuenta': '6329000 AsesorÃ­a y consultorÃ­a - Otros', 'distribucion_analitica': [[{'codigo': '', 'nom_distribucion': '', 'sub_categoria': '', 'porcentaje': '100.00'}]]}, {'codigo_producto': 2026, 'cantidad': '1', 'valor_unitario': 50.85, 'precio_unitario': 60.0, 'descuento': 0.0, 'subtotal': 50.85, 'porcentaje_de_igv': '17.99', 'igv': 9.149999999999999, 'total': 60.0, 'moneda': '1', 'tipo_de_cambio': 1.0, 'id_tipo_gasto': 5, 'nom_tipo_gasto': 'Otros', 'id_proveedor': 1579, 'id_producto': 30921, 'nom_producto': 'SERVICIO DE MANTENIMIENTO', 'categoria_producto': 'EVENTOS', 'id_estado': 'paid', 'nombre_estado': 'Pagado', 'evento': {'id_evento': '', 'nom_evento': '', 'fecha_hora_ini_event': '', 'fecha_hora_fin_event': '', 'id_organizador': '', 'nom_organizador': '', 'tipo_organizador': ''}, 'id_cuenta': 877, 'nom_cuenta': '6329000 AsesorÃ­a y consultorÃ­a - Otros', 'distribucion_analitica': [[{'codigo': '', 'nom_distribucion': '', 'sub_categoria': '', 'porcentaje': '100.00'}]]}, {'codigo_producto': 2026, 'cantidad': '1', 'valor_unitario': 22.88, 'precio_unitario': 27.0, 'descuento': 0.0, 'subtotal': 22.88, 'porcentaje_de_igv': '18.01', 'igv': 4.120000000000001, 'total': 27.0, 'moneda': '1', 'tipo_de_cambio': 1.0, 'id_tipo_gasto': 5, 'nom_tipo_gasto': 'Otros', 'id_proveedor': 1579, 'id_producto': 30922, 'nom_producto': 'SERVICIO DE MANTENIMIENTO', 'categoria_producto': 'EVENTOS', 'id_estado': 'paid', 'nombre_estado': 'Pagado', 'evento': {'id_evento': '', 'nom_evento': '', 'fecha_hora_ini_event': '', 'fecha_hora_fin_event': '', 'id_organizador': '', 'nom_organizador': '', 'tipo_organizador': ''}, 'id_cuenta': 877, 'nom_cuenta': '6329000 AsesorÃ­a y consultorÃ­a - Otros', 'distribucion_analitica': [[{'codigo': '', 'nom_distribucion': '', 'sub_categoria': '', 'porcentaje': '100.00'}]]}, {'codigo_producto': 2026, 'cantidad': '1', 'valor_unitario': 194.92, 'precio_unitario': 230.01, 'descuento': 0.0, 'subtotal': 194.92, 'porcentaje_de_igv': '18.00', 'igv': 35.09, 'total': 230.01, 'moneda': '1', 'tipo_de_cambio': 1.0, 'id_tipo_gasto': 2, 'nom_tipo_gasto': 'Servicios', 'id_proveedor': 1579, 'id_producto': 30923, 'nom_producto': 'SERVICIO DE MANTENIMIENTO', 'categoria_producto': 'EVENTOS', 'id_estado': 'paid', 'nombre_estado': 'Pagado', 'evento': {'id_evento': '', 'nom_evento': '', 'fecha_hora_ini_event': '', 'fecha_hora_fin_event': '', 'id_organizador': '', 'nom_organizador': '', 'tipo_organizador': ''}, 'id_cuenta': 877, 'nom_cuenta': '6329000 AsesorÃ­a y consultorÃ­a - Otros', 'distribucion_analitica': [[{'codigo': '', 'nom_distribucion': '', 'sub_categoria': '', 'porcentaje': '100.00'}]]}] | K18: 45939 | Q18: 2026 | R18: 1 | S18: 22.03 | T18: 26 | U18: 0 | V18: 22.03 | W18: 18.02 | X18: 3.97 | Y18: 26 | Z18: 1 | AA18: 1 | AB18: 5 | AC18: Otros | AD18: 1579 | AE18: 30917 | AF18: SERVICIO DE MANTENIMIENTO | AG18: EVENTOS | AH18: paid | AI18: Pagado | AJ18: 877 | AK18: 6329000 AsesorÃ­a y consultorÃ­a - Otros | AL18: [[{'codigo': '', 'nom_distribucion': '', 'sub_categoria': '', 'porcentaje': '100.00'}]] | AT18: =+CONCATENATE(A18,"-",B18) -> E001-00000492 | AU18: =+IF(Z18=1,V18,IF(Z18=2,V18*AA18)) -> 22.03 | AV18: =+IF(Z18=1,X18,IF(Z18=2,X18*AA18)) -> 3.97 | AW18: =+IF(Z18=1,Y18,IF(Z18=2,Y18*AA18)) -> 26
A19: E001 | B19: 00000492 | C19: COLABORATIVA S.A.C. | D19: 45939 | E19: 45957.445 | F19: EURO CARS PERU S.A.C. | H19: RUC | I19: 20608892215 | J19: [{'codigo_producto': 2026, 'cantidad': '1', 'valor_unitario': 186.44, 'precio_unitario': 220.0, 'descuento': 0.0, 'subtotal': 186.44, 'porcentaje_de_igv': '18.00', 'igv': 33.56, 'total': 220.0, 'moneda': '1', 'tipo_de_cambio': 1.0, 'id_tipo_gasto': 5, 'nom_tipo_gasto': 'Otros', 'id_proveedor': 1579, 'id_producto': 30915, 'nom_producto': 'SERVICIO DE MANTENIMIENTO', 'categoria_producto': 'EVENTOS', 'id_estado': 'paid', 'nombre_estado': 'Pagado', 'evento': {'id_evento': '', 'nom_evento': '', 'fecha_hora_ini_event': '', 'fecha_hora_fin_event': '', 'id_organizador': '', 'nom_organizador': '', 'tipo_organizador': ''}, 'id_cuenta': 877, 'nom_cuenta': '6329000 AsesorÃ­a y consultorÃ­a - Otros', 'distribucion_analitica': [[{'codigo': '', 'nom_distribucion': '', 'sub_categoria': '', 'porcentaje': '100.00'}]]}, {'codigo_producto': 2026, 'cantidad': '1', 'valor_unitario': 1.7, 'precio_unitario': 2.01, 'descuento': 0.0, 'subtotal': 1.7, 'porcentaje_de_igv': '18.24', 'igv': 0.30999999999999983, 'total': 2.01, 'moneda': '1', 'tipo_de_cambio': 1.0, 'id_tipo_gasto': 5, 'nom_tipo_gasto': 'Otros', 'id_proveedor': 1579, 'id_producto': 30916, 'nom_producto': 'SERVICIO DE MANTENIMIENTO', 'categoria_producto': 'EVENTOS', 'id_estado': 'paid', 'nombre_estado': 'Pagado', 'evento': {'id_evento': '', 'nom_evento': '', 'fecha_hora_ini_event': '', 'fecha_hora_fin_event': '', 'id_organizador': '', 'nom_organizador': '', 'tipo_organizador': ''}, 'id_cuenta': 877, 'nom_cuenta': '6329000 AsesorÃ­a y consultorÃ­a - Otros', 'distribucion_analitica': [[{'codigo': '', 'nom_distribucion': '', 'sub_categoria': '', 'porcentaje': '100.00'}]]}, {'codigo_producto': 2026, 'cantidad': '1', 'valor_unitario': 22.03, 'precio_unitario': 26.0, 'descuento': 0.0, 'subtotal': 22.03, 'porcentaje_de_igv': '18.02', 'igv': 3.969999999999999, 'total': 26.0, 'moneda': '1', 'tipo_de_cambio': 1.0, 'id_tipo_gasto': 5, 'nom_tipo_gasto': 'Otros', 'id_proveedor': 1579, 'id_producto': 30917, 'nom_producto': 'SERVICIO DE MANTENIMIENTO', 'categoria_producto': 'EVENTOS', 'id_estado': 'paid', 'nombre_estado': 'Pagado', 'evento': {'id_evento': '', 'nom_evento': '', 'fecha_hora_ini_event': '', 'fecha_hora_fin_event': '', 'id_organizador': '', 'nom_organizador': '', 'tipo_organizador': ''}, 'id_cuenta': 877, 'nom_cuenta': '6329000 AsesorÃ­a y consultorÃ­a - Otros', 'distribucion_analitica': [[{'codigo': '', 'nom_distribucion': '', 'sub_categoria': '', 'porcentaje': '100.00'}]]}, {'codigo_producto': 2026, 'cantidad': '1', 'valor_unitario': 42.37, 'precio_unitario': 50.0, 'descuento': 0.0, 'subtotal': 42.37, 'porcentaje_de_igv': '18.01', 'igv': 7.630000000000003, 'total': 50.0, 'moneda': '1', 'tipo_de_cambio': 1.0, 'id_tipo_gasto': 5, 'nom_tipo_gasto': 'Otros', 'id_proveedor': 1579, 'id_producto': 30918, 'nom_producto': 'SERVICIO DE MANTENIMIENTO', 'categoria_producto': 'EVENTOS', 'id_estado': 'paid', 'nombre_estado': 'Pagado', 'evento': {'id_evento': '', 'nom_evento': '', 'fecha_hora_ini_event': '', 'fecha_hora_fin_event': '', 'id_organizador': '', 'nom_organizador': '', 'tipo_organizador': ''}, 'id_cuenta': 877, 'nom_cuenta': '6329000 AsesorÃ­a y consultorÃ­a - Otros', 'distribucion_analitica': [[{'codigo': '', 'nom_distribucion': '', 'sub_categoria': '', 'porcentaje': '100.00'}]]}, {'codigo_producto': 2026, 'cantidad': '1', 'valor_unitario': 23.73, 'precio_unitario': 28.0, 'descuento': 0.0, 'subtotal': 23.73, 'porcentaje_de_igv': '17.99', 'igv': 4.27, 'total': 28.0, 'moneda': '1', 'tipo_de_cambio': 1.0, 'id_tipo_gasto': 5, 'nom_tipo_gasto': 'Otros', 'id_proveedor': 1579, 'id_producto': 30919, 'nom_producto': 'SERVICIO DE MANTENIMIENTO', 'categoria_producto': 'EVENTOS', 'id_estado': 'paid', 'nombre_estado': 'Pagado', 'evento': {'id_evento': '', 'nom_evento': '', 'fecha_hora_ini_event': '', 'fecha_hora_fin_event': '', 'id_organizador': '', 'nom_organizador': '', 'tipo_organizador': ''}, 'id_cuenta': 877, 'nom_cuenta': '6329000 AsesorÃ­a y consultorÃ­a - Otros', 'distribucion_analitica': [[{'codigo': '', 'nom_distribucion': '', 'sub_categoria': '', 'porcentaje': '100.00'}]]}, {'codigo_producto': 2026, 'cantidad': '1', 'valor_unitario': 5.93, 'precio_unitario': 7.0, 'descuento': 0.0, 'subtotal': 5.93, 'porcentaje_de_igv': '18.04', 'igv': 1.0700000000000003, 'total': 7.0, 'moneda': '1', 'tipo_de_cambio': 1.0, 'id_tipo_gasto': 5, 'nom_tipo_gasto': 'Otros', 'id_proveedor': 1579, 'id_producto': 30920, 'nom_producto': 'SERVICIO DE MANTENIMIENTO', 'categoria_producto': 'EVENTOS', 'id_estado': 'paid', 'nombre_estado': 'Pagado', 'evento': {'id_evento': '', 'nom_evento': '', 'fecha_hora_ini_event': '', 'fecha_hora_fin_event': '', 'id_organizador': '', 'nom_organizador': '', 'tipo_organizador': ''}, 'id_cuenta': 877, 'nom_cuenta': '6329000 AsesorÃ­a y consultorÃ­a - Otros', 'distribucion_analitica': [[{'codigo': '', 'nom_distribucion': '', 'sub_categoria': '', 'porcentaje': '100.00'}]]}, {'codigo_producto': 2026, 'cantidad': '1', 'valor_unitario': 50.85, 'precio_unitario': 60.0, 'descuento': 0.0, 'subtotal': 50.85, 'porcentaje_de_igv': '17.99', 'igv': 9.149999999999999, 'total': 60.0, 'moneda': '1', 'tipo_de_cambio': 1.0, 'id_tipo_gasto': 5, 'nom_tipo_gasto': 'Otros', 'id_proveedor': 1579, 'id_producto': 30921, 'nom_producto': 'SERVICIO DE MANTENIMIENTO', 'categoria_producto': 'EVENTOS', 'id_estado': 'paid', 'nombre_estado': 'Pagado', 'evento': {'id_evento': '', 'nom_evento': '', 'fecha_hora_ini_event': '', 'fecha_hora_fin_event': '', 'id_organizador': '', 'nom_organizador': '', 'tipo_organizador': ''}, 'id_cuenta': 877, 'nom_cuenta': '6329000 AsesorÃ­a y consultorÃ­a - Otros', 'distribucion_analitica': [[{'codigo': '', 'nom_distribucion': '', 'sub_categoria': '', 'porcentaje': '100.00'}]]}, {'codigo_producto': 2026, 'cantidad': '1', 'valor_unitario': 22.88, 'precio_unitario': 27.0, 'descuento': 0.0, 'subtotal': 22.88, 'porcentaje_de_igv': '18.01', 'igv': 4.120000000000001, 'total': 27.0, 'moneda': '1', 'tipo_de_cambio': 1.0, 'id_tipo_gasto': 5, 'nom_tipo_gasto': 'Otros', 'id_proveedor': 1579, 'id_producto': 30922, 'nom_producto': 'SERVICIO DE MANTENIMIENTO', 'categoria_producto': 'EVENTOS', 'id_estado': 'paid', 'nombre_estado': 'Pagado', 'evento': {'id_evento': '', 'nom_evento': '', 'fecha_hora_ini_event': '', 'fecha_hora_fin_event': '', 'id_organizador': '', 'nom_organizador': '', 'tipo_organizador': ''}, 'id_cuenta': 877, 'nom_cuenta': '6329000 AsesorÃ­a y consultorÃ­a - Otros', 'distribucion_analitica': [[{'codigo': '', 'nom_distribucion': '', 'sub_categoria': '', 'porcentaje': '100.00'}]]}, {'codigo_producto': 2026, 'cantidad': '1', 'valor_unitario': 194.92, 'precio_unitario': 230.01, 'descuento': 0.0, 'subtotal': 194.92, 'porcentaje_de_igv': '18.00', 'igv': 35.09, 'total': 230.01, 'moneda': '1', 'tipo_de_cambio': 1.0, 'id_tipo_gasto': 2, 'nom_tipo_gasto': 'Servicios', 'id_proveedor': 1579, 'id_producto': 30923, 'nom_producto': 'SERVICIO DE MANTENIMIENTO', 'categoria_producto': 'EVENTOS', 'id_estado': 'paid', 'nombre_estado': 'Pagado', 'evento': {'id_evento': '', 'nom_evento': '', 'fecha_hora_ini_event': '', 'fecha_hora_fin_event': '', 'id_organizador': '', 'nom_organizador': '', 'tipo_organizador': ''}, 'id_cuenta': 877, 'nom_cuenta': '6329000 AsesorÃ­a y consultorÃ­a - Otros', 'distribucion_analitica': [[{'codigo': '', 'nom_distribucion': '', 'sub_categoria': '', 'porcentaje': '100.00'}]]}] | K19: 45939 | Q19: 2026 | R19: 1 | S19: 42.37 | T19: 50 | U19: 0 | V19: 42.37 | W19: 18.01 | X19: 7.63 | Y19: 50 | Z19: 1 | AA19: 1 | AB19: 5 | AC19: Otros | AD19: 1579 | AE19: 30918 | AF19: SERVICIO DE MANTENIMIENTO | AG19: EVENTOS | AH19: paid | AI19: Pagado | AJ19: 877 | AK19: 6329000 AsesorÃ­a y consultorÃ­a - Otros | AL19: [[{'codigo': '', 'nom_distribucion': '', 'sub_categoria': '', 'porcentaje': '100.00'}]] | AT19: =+CONCATENATE(A19,"-",B19) -> E001-00000492 | AU19: =+IF(Z19=1,V19,IF(Z19=2,V19*AA19)) -> 42.37 | AV19: =+IF(Z19=1,X19,IF(Z19=2,X19*AA19)) -> 7.63 | AW19: =+IF(Z19=1,Y19,IF(Z19=2,Y19*AA19)) -> 50
A20: E001 | B20: 00000492 | C20: COLABORATIVA S.A.C. | D20: 45939 | E20: 45957.445 | F20: EURO CARS PERU S.A.C. | H20: RUC | I20: 20608892215 | J20: [{'codigo_producto': 2026, 'cantidad': '1', 'valor_unitario': 186.44, 'precio_unitario': 220.0, 'descuento': 0.0, 'subtotal': 186.44, 'porcentaje_de_igv': '18.00', 'igv': 33.56, 'total': 220.0, 'moneda': '1', 'tipo_de_cambio': 1.0, 'id_tipo_gasto': 5, 'nom_tipo_gasto': 'Otros', 'id_proveedor': 1579, 'id_producto': 30915, 'nom_producto': 'SERVICIO DE MANTENIMIENTO', 'categoria_producto': 'EVENTOS', 'id_estado': 'paid', 'nombre_estado': 'Pagado', 'evento': {'id_evento': '', 'nom_evento': '', 'fecha_hora_ini_event': '', 'fecha_hora_fin_event': '', 'id_organizador': '', 'nom_organizador': '', 'tipo_organizador': ''}, 'id_cuenta': 877, 'nom_cuenta': '6329000 AsesorÃ­a y consultorÃ­a - Otros', 'distribucion_analitica': [[{'codigo': '', 'nom_distribucion': '', 'sub_categoria': '', 'porcentaje': '100.00'}]]}, {'codigo_producto': 2026, 'cantidad': '1', 'valor_unitario': 1.7, 'precio_unitario': 2.01, 'descuento': 0.0, 'subtotal': 1.7, 'porcentaje_de_igv': '18.24', 'igv': 0.30999999999999983, 'total': 2.01, 'moneda': '1', 'tipo_de_cambio': 1.0, 'id_tipo_gasto': 5, 'nom_tipo_gasto': 'Otros', 'id_proveedor': 1579, 'id_producto': 30916, 'nom_producto': 'SERVICIO DE MANTENIMIENTO', 'categoria_producto': 'EVENTOS', 'id_estado': 'paid', 'nombre_estado': 'Pagado', 'evento': {'id_evento': '', 'nom_evento': '', 'fecha_hora_ini_event': '', 'fecha_hora_fin_event': '', 'id_organizador': '', 'nom_organizador': '', 'tipo_organizador': ''}, 'id_cuenta': 877, 'nom_cuenta': '6329000 AsesorÃ­a y consultorÃ­a - Otros', 'distribucion_analitica': [[{'codigo': '', 'nom_distribucion': '', 'sub_categoria': '', 'porcentaje': '100.00'}]]}, {'codigo_producto': 2026, 'cantidad': '1', 'valor_unitario': 22.03, 'precio_unitario': 26.0, 'descuento': 0.0, 'subtotal': 22.03, 'porcentaje_de_igv': '18.02', 'igv': 3.969999999999999, 'total': 26.0, 'moneda': '1', 'tipo_de_cambio': 1.0, 'id_tipo_gasto': 5, 'nom_tipo_gasto': 'Otros', 'id_proveedor': 1579, 'id_producto': 30917, 'nom_producto': 'SERVICIO DE MANTENIMIENTO', 'categoria_producto': 'EVENTOS', 'id_estado': 'paid', 'nombre_estado': 'Pagado', 'evento': {'id_evento': '', 'nom_evento': '', 'fecha_hora_ini_event': '', 'fecha_hora_fin_event': '', 'id_organizador': '', 'nom_organizador': '', 'tipo_organizador': ''}, 'id_cuenta': 877, 'nom_cuenta': '6329000 AsesorÃ­a y consultorÃ­a - Otros', 'distribucion_analitica': [[{'codigo': '', 'nom_distribucion': '', 'sub_categoria': '', 'porcentaje': '100.00'}]]}, {'codigo_producto': 2026, 'cantidad': '1', 'valor_unitario': 42.37, 'precio_unitario': 50.0, 'descuento': 0.0, 'subtotal': 42.37, 'porcentaje_de_igv': '18.01', 'igv': 7.630000000000003, 'total': 50.0, 'moneda': '1', 'tipo_de_cambio': 1.0, 'id_tipo_gasto': 5, 'nom_tipo_gasto': 'Otros', 'id_proveedor': 1579, 'id_producto': 30918, 'nom_producto': 'SERVICIO DE MANTENIMIENTO', 'categoria_producto': 'EVENTOS', 'id_estado': 'paid', 'nombre_estado': 'Pagado', 'evento': {'id_evento': '', 'nom_evento': '', 'fecha_hora_ini_event': '', 'fecha_hora_fin_event': '', 'id_organizador': '', 'nom_organizador': '', 'tipo_organizador': ''}, 'id_cuenta': 877, 'nom_cuenta': '6329000 AsesorÃ­a y consultorÃ­a - Otros', 'distribucion_analitica': [[{'codigo': '', 'nom_distribucion': '', 'sub_categoria': '', 'porcentaje': '100.00'}]]}, {'codigo_producto': 2026, 'cantidad': '1', 'valor_unitario': 23.73, 'precio_unitario': 28.0, 'descuento': 0.0, 'subtotal': 23.73, 'porcentaje_de_igv': '17.99', 'igv': 4.27, 'total': 28.0, 'moneda': '1', 'tipo_de_cambio': 1.0, 'id_tipo_gasto': 5, 'nom_tipo_gasto': 'Otros', 'id_proveedor': 1579, 'id_producto': 30919, 'nom_producto': 'SERVICIO DE MANTENIMIENTO', 'categoria_producto': 'EVENTOS', 'id_estado': 'paid', 'nombre_estado': 'Pagado', 'evento': {'id_evento': '', 'nom_evento': '', 'fecha_hora_ini_event': '', 'fecha_hora_fin_event': '', 'id_organizador': '', 'nom_organizador': '', 'tipo_organizador': ''}, 'id_cuenta': 877, 'nom_cuenta': '6329000 AsesorÃ­a y consultorÃ­a - Otros', 'distribucion_analitica': [[{'codigo': '', 'nom_distribucion': '', 'sub_categoria': '', 'porcentaje': '100.00'}]]}, {'codigo_producto': 2026, 'cantidad': '1', 'valor_unitario': 5.93, 'precio_unitario': 7.0, 'descuento': 0.0, 'subtotal': 5.93, 'porcentaje_de_igv': '18.04', 'igv': 1.0700000000000003, 'total': 7.0, 'moneda': '1', 'tipo_de_cambio': 1.0, 'id_tipo_gasto': 5, 'nom_tipo_gasto': 'Otros', 'id_proveedor': 1579, 'id_producto': 30920, 'nom_producto': 'SERVICIO DE MANTENIMIENTO', 'categoria_producto': 'EVENTOS', 'id_estado': 'paid', 'nombre_estado': 'Pagado', 'evento': {'id_evento': '', 'nom_evento': '', 'fecha_hora_ini_event': '', 'fecha_hora_fin_event': '', 'id_organizador': '', 'nom_organizador': '', 'tipo_organizador': ''}, 'id_cuenta': 877, 'nom_cuenta': '6329000 AsesorÃ­a y consultorÃ­a - Otros', 'distribucion_analitica': [[{'codigo': '', 'nom_distribucion': '', 'sub_categoria': '', 'porcentaje': '100.00'}]]}, {'codigo_producto': 2026, 'cantidad': '1', 'valor_unitario': 50.85, 'precio_unitario': 60.0, 'descuento': 0.0, 'subtotal': 50.85, 'porcentaje_de_igv': '17.99', 'igv': 9.149999999999999, 'total': 60.0, 'moneda': '1', 'tipo_de_cambio': 1.0, 'id_tipo_gasto': 5, 'nom_tipo_gasto': 'Otros', 'id_proveedor': 1579, 'id_producto': 30921, 'nom_producto': 'SERVICIO DE MANTENIMIENTO', 'categoria_producto': 'EVENTOS', 'id_estado': 'paid', 'nombre_estado': 'Pagado', 'evento': {'id_evento': '', 'nom_evento': '', 'fecha_hora_ini_event': '', 'fecha_hora_fin_event': '', 'id_organizador': '', 'nom_organizador': '', 'tipo_organizador': ''}, 'id_cuenta': 877, 'nom_cuenta': '6329000 AsesorÃ­a y consultorÃ­a - Otros', 'distribucion_analitica': [[{'codigo': '', 'nom_distribucion': '', 'sub_categoria': '', 'porcentaje': '100.00'}]]}, {'codigo_producto': 2026, 'cantidad': '1', 'valor_unitario': 22.88, 'precio_unitario': 27.0, 'descuento': 0.0, 'subtotal': 22.88, 'porcentaje_de_igv': '18.01', 'igv': 4.120000000000001, 'total': 27.0, 'moneda': '1', 'tipo_de_cambio': 1.0, 'id_tipo_gasto': 5, 'nom_tipo_gasto': 'Otros', 'id_proveedor': 1579, 'id_producto': 30922, 'nom_producto': 'SERVICIO DE MANTENIMIENTO', 'categoria_producto': 'EVENTOS', 'id_estado': 'paid', 'nombre_estado': 'Pagado', 'evento': {'id_evento': '', 'nom_evento': '', 'fecha_hora_ini_event': '', 'fecha_hora_fin_event': '', 'id_organizador': '', 'nom_organizador': '', 'tipo_organizador': ''}, 'id_cuenta': 877, 'nom_cuenta': '6329000 AsesorÃ­a y consultorÃ­a - Otros', 'distribucion_analitica': [[{'codigo': '', 'nom_distribucion': '', 'sub_categoria': '', 'porcentaje': '100.00'}]]}, {'codigo_producto': 2026, 'cantidad': '1', 'valor_unitario': 194.92, 'precio_unitario': 230.01, 'descuento': 0.0, 'subtotal': 194.92, 'porcentaje_de_igv': '18.00', 'igv': 35.09, 'total': 230.01, 'moneda': '1', 'tipo_de_cambio': 1.0, 'id_tipo_gasto': 2, 'nom_tipo_gasto': 'Servicios', 'id_proveedor': 1579, 'id_producto': 30923, 'nom_producto': 'SERVICIO DE MANTENIMIENTO', 'categoria_producto': 'EVENTOS', 'id_estado': 'paid', 'nombre_estado': 'Pagado', 'evento': {'id_evento': '', 'nom_evento': '', 'fecha_hora_ini_event': '', 'fecha_hora_fin_event': '', 'id_organizador': '', 'nom_organizador': '', 'tipo_organizador': ''}, 'id_cuenta': 877, 'nom_cuenta': '6329000 AsesorÃ­a y consultorÃ­a - Otros', 'distribucion_analitica': [[{'codigo': '', 'nom_distribucion': '', 'sub_categoria': '', 'porcentaje': '100.00'}]]}] | K20: 45939 | Q20: 2026 | R20: 1 | S20: 23.73 | T20: 28 | U20: 0 | V20: 23.73 | W20: 17.99 | X20: 4.27 | Y20: 28 | Z20: 1 | AA20: 1 | AB20: 5 | AC20: Otros | AD20: 1579 | AE20: 30919 | AF20: SERVICIO DE MANTENIMIENTO | AG20: EVENTOS | AH20: paid | AI20: Pagado | AJ20: 877 | AK20: 6329000 AsesorÃ­a y consultorÃ­a - Otros | AL20: [[{'codigo': '', 'nom_distribucion': '', 'sub_categoria': '', 'porcentaje': '100.00'}]] | AT20: =+CONCATENATE(A20,"-",B20) -> E001-00000492 | AU20: =+IF(Z20=1,V20,IF(Z20=2,V20*AA20)) -> 23.73 | AV20: =+IF(Z20=1,X20,IF(Z20=2,X20*AA20)) -> 4.27 | AW20: =+IF(Z20=1,Y20,IF(Z20=2,Y20*AA20)) -> 28
A21: E001 | B21: 00000492 | C21: COLABORATIVA S.A.C. | D21: 45939 | E21: 45957.445 | F21: EURO CARS PERU S.A.C. | H21: RUC | I21: 20608892215 | J21: [{'codigo_producto': 2026, 'cantidad': '1', 'valor_unitario': 186.44, 'precio_unitario': 220.0, 'descuento': 0.0, 'subtotal': 186.44, 'porcentaje_de_igv': '18.00', 'igv': 33.56, 'total': 220.0, 'moneda': '1', 'tipo_de_cambio': 1.0, 'id_tipo_gasto': 5, 'nom_tipo_gasto': 'Otros', 'id_proveedor': 1579, 'id_producto': 30915, 'nom_producto': 'SERVICIO DE MANTENIMIENTO', 'categoria_producto': 'EVENTOS', 'id_estado': 'paid', 'nombre_estado': 'Pagado', 'evento': {'id_evento': '', 'nom_evento': '', 'fecha_hora_ini_event': '', 'fecha_hora_fin_event': '', 'id_organizador': '', 'nom_organizador': '', 'tipo_organizador': ''}, 'id_cuenta': 877, 'nom_cuenta': '6329000 AsesorÃ­a y consultorÃ­a - Otros', 'distribucion_analitica': [[{'codigo': '', 'nom_distribucion': '', 'sub_categoria': '', 'porcentaje': '100.00'}]]}, {'codigo_producto': 2026, 'cantidad': '1', 'valor_unitario': 1.7, 'precio_unitario': 2.01, 'descuento': 0.0, 'subtotal': 1.7, 'porcentaje_de_igv': '18.24', 'igv': 0.30999999999999983, 'total': 2.01, 'moneda': '1', 'tipo_de_cambio': 1.0, 'id_tipo_gasto': 5, 'nom_tipo_gasto': 'Otros', 'id_proveedor': 1579, 'id_producto': 30916, 'nom_producto': 'SERVICIO DE MANTENIMIENTO', 'categoria_producto': 'EVENTOS', 'id_estado': 'paid', 'nombre_estado': 'Pagado', 'evento': {'id_evento': '', 'nom_evento': '', 'fecha_hora_ini_event': '', 'fecha_hora_fin_event': '', 'id_organizador': '', 'nom_organizador': '', 'tipo_organizador': ''}, 'id_cuenta': 877, 'nom_cuenta': '6329000 AsesorÃ­a y consultorÃ­a - Otros', 'distribucion_analitica': [[{'codigo': '', 'nom_distribucion': '', 'sub_categoria': '', 'porcentaje': '100.00'}]]}, {'codigo_producto': 2026, 'cantidad': '1', 'valor_unitario': 22.03, 'precio_unitario': 26.0, 'descuento': 0.0, 'subtotal': 22.03, 'porcentaje_de_igv': '18.02', 'igv': 3.969999999999999, 'total': 26.0, 'moneda': '1', 'tipo_de_cambio': 1.0, 'id_tipo_gasto': 5, 'nom_tipo_gasto': 'Otros', 'id_proveedor': 1579, 'id_producto': 30917, 'nom_producto': 'SERVICIO DE MANTENIMIENTO', 'categoria_producto': 'EVENTOS', 'id_estado': 'paid', 'nombre_estado': 'Pagado', 'evento': {'id_evento': '', 'nom_evento': '', 'fecha_hora_ini_event': '', 'fecha_hora_fin_event': '', 'id_organizador': '', 'nom_organizador': '', 'tipo_organizador': ''}, 'id_cuenta': 877, 'nom_cuenta': '6329000 AsesorÃ­a y consultorÃ­a - Otros', 'distribucion_analitica': [[{'codigo': '', 'nom_distribucion': '', 'sub_categoria': '', 'porcentaje': '100.00'}]]}, {'codigo_producto': 2026, 'cantidad': '1', 'valor_unitario': 42.37, 'precio_unitario': 50.0, 'descuento': 0.0, 'subtotal': 42.37, 'porcentaje_de_igv': '18.01', 'igv': 7.630000000000003, 'total': 50.0, 'moneda': '1', 'tipo_de_cambio': 1.0, 'id_tipo_gasto': 5, 'nom_tipo_gasto': 'Otros', 'id_proveedor': 1579, 'id_producto': 30918, 'nom_producto': 'SERVICIO DE MANTENIMIENTO', 'categoria_producto': 'EVENTOS', 'id_estado': 'paid', 'nombre_estado': 'Pagado', 'evento': {'id_evento': '', 'nom_evento': '', 'fecha_hora_ini_event': '', 'fecha_hora_fin_event': '', 'id_organizador': '', 'nom_organizador': '', 'tipo_organizador': ''}, 'id_cuenta': 877, 'nom_cuenta': '6329000 AsesorÃ­a y consultorÃ­a - Otros', 'distribucion_analitica': [[{'codigo': '', 'nom_distribucion': '', 'sub_categoria': '', 'porcentaje': '100.00'}]]}, {'codigo_producto': 2026, 'cantidad': '1', 'valor_unitario': 23.73, 'precio_unitario': 28.0, 'descuento': 0.0, 'subtotal': 23.73, 'porcentaje_de_igv': '17.99', 'igv': 4.27, 'total': 28.0, 'moneda': '1', 'tipo_de_cambio': 1.0, 'id_tipo_gasto': 5, 'nom_tipo_gasto': 'Otros', 'id_proveedor': 1579, 'id_producto': 30919, 'nom_producto': 'SERVICIO DE MANTENIMIENTO', 'categoria_producto': 'EVENTOS', 'id_estado': 'paid', 'nombre_estado': 'Pagado', 'evento': {'id_evento': '', 'nom_evento': '', 'fecha_hora_ini_event': '', 'fecha_hora_fin_event': '', 'id_organizador': '', 'nom_organizador': '', 'tipo_organizador': ''}, 'id_cuenta': 877, 'nom_cuenta': '6329000 AsesorÃ­a y consultorÃ­a - Otros', 'distribucion_analitica': [[{'codigo': '', 'nom_distribucion': '', 'sub_categoria': '', 'porcentaje': '100.00'}]]}, {'codigo_producto': 2026, 'cantidad': '1', 'valor_unitario': 5.93, 'precio_unitario': 7.0, 'descuento': 0.0, 'subtotal': 5.93, 'porcentaje_de_igv': '18.04', 'igv': 1.0700000000000003, 'total': 7.0, 'moneda': '1', 'tipo_de_cambio': 1.0, 'id_tipo_gasto': 5, 'nom_tipo_gasto': 'Otros', 'id_proveedor': 1579, 'id_producto': 30920, 'nom_producto': 'SERVICIO DE MANTENIMIENTO', 'categoria_producto': 'EVENTOS', 'id_estado': 'paid', 'nombre_estado': 'Pagado', 'evento': {'id_evento': '', 'nom_evento': '', 'fecha_hora_ini_event': '', 'fecha_hora_fin_event': '', 'id_organizador': '', 'nom_organizador': '', 'tipo_organizador': ''}, 'id_cuenta': 877, 'nom_cuenta': '6329000 AsesorÃ­a y consultorÃ­a - Otros', 'distribucion_analitica': [[{'codigo': '', 'nom_distribucion': '', 'sub_categoria': '', 'porcentaje': '100.00'}]]}, {'codigo_producto': 2026, 'cantidad': '1', 'valor_unitario': 50.85, 'precio_unitario': 60.0, 'descuento': 0.0, 'subtotal': 50.85, 'porcentaje_de_igv': '17.99', 'igv': 9.149999999999999, 'total': 60.0, 'moneda': '1', 'tipo_de_cambio': 1.0, 'id_tipo_gasto': 5, 'nom_tipo_gasto': 'Otros', 'id_proveedor': 1579, 'id_producto': 30921, 'nom_producto': 'SERVICIO DE MANTENIMIENTO', 'categoria_producto': 'EVENTOS', 'id_estado': 'paid', 'nombre_estado': 'Pagado', 'evento': {'id_evento': '', 'nom_evento': '', 'fecha_hora_ini_event': '', 'fecha_hora_fin_event': '', 'id_organizador': '', 'nom_organizador': '', 'tipo_organizador': ''}, 'id_cuenta': 877, 'nom_cuenta': '6329000 AsesorÃ­a y consultorÃ­a - Otros', 'distribucion_analitica': [[{'codigo': '', 'nom_distribucion': '', 'sub_categoria': '', 'porcentaje': '100.00'}]]}, {'codigo_producto': 2026, 'cantidad': '1', 'valor_unitario': 22.88, 'precio_unitario': 27.0, 'descuento': 0.0, 'subtotal': 22.88, 'porcentaje_de_igv': '18.01', 'igv': 4.120000000000001, 'total': 27.0, 'moneda': '1', 'tipo_de_cambio': 1.0, 'id_tipo_gasto': 5, 'nom_tipo_gasto': 'Otros', 'id_proveedor': 1579, 'id_producto': 30922, 'nom_producto': 'SERVICIO DE MANTENIMIENTO', 'categoria_producto': 'EVENTOS', 'id_estado': 'paid', 'nombre_estado': 'Pagado', 'evento': {'id_evento': '', 'nom_evento': '', 'fecha_hora_ini_event': '', 'fecha_hora_fin_event': '', 'id_organizador': '', 'nom_organizador': '', 'tipo_organizador': ''}, 'id_cuenta': 877, 'nom_cuenta': '6329000 AsesorÃ­a y consultorÃ­a - Otros', 'distribucion_analitica': [[{'codigo': '', 'nom_distribucion': '', 'sub_categoria': '', 'porcentaje': '100.00'}]]}, {'codigo_producto': 2026, 'cantidad': '1', 'valor_unitario': 194.92, 'precio_unitario': 230.01, 'descuento': 0.0, 'subtotal': 194.92, 'porcentaje_de_igv': '18.00', 'igv': 35.09, 'total': 230.01, 'moneda': '1', 'tipo_de_cambio': 1.0, 'id_tipo_gasto': 2, 'nom_tipo_gasto': 'Servicios', 'id_proveedor': 1579, 'id_producto': 30923, 'nom_producto': 'SERVICIO DE MANTENIMIENTO', 'categoria_producto': 'EVENTOS', 'id_estado': 'paid', 'nombre_estado': 'Pagado', 'evento': {'id_evento': '', 'nom_evento': '', 'fecha_hora_ini_event': '', 'fecha_hora_fin_event': '', 'id_organizador': '', 'nom_organizador': '', 'tipo_organizador': ''}, 'id_cuenta': 877, 'nom_cuenta': '6329000 AsesorÃ­a y consultorÃ­a - Otros', 'distribucion_analitica': [[{'codigo': '', 'nom_distribucion': '', 'sub_categoria': '', 'porcentaje': '100.00'}]]}] | K21: 45939 | Q21: 2026 | R21: 1 | S21: 5.93 | T21: 7 | U21: 0 | V21: 5.93 | W21: 18.04 | X21: 1.07 | Y21: 7 | Z21: 1 | AA21: 1 | AB21: 5 | AC21: Otros | AD21: 1579 | AE21: 30920 | AF21: SERVICIO DE MANTENIMIENTO | AG21: EVENTOS | AH21: paid | AI21: Pagado | AJ21: 877 | AK21: 6329000 AsesorÃ­a y consultorÃ­a - Otros | AL21: [[{'codigo': '', 'nom_distribucion': '', 'sub_categoria': '', 'porcentaje': '100.00'}]] | AT21: =+CONCATENATE(A21,"-",B21) -> E001-00000492 | AU21: =+IF(Z21=1,V21,IF(Z21=2,V21*AA21)) -> 5.93 | AV21: =+IF(Z21=1,X21,IF(Z21=2,X21*AA21)) -> 1.07 | AW21: =+IF(Z21=1,Y21,IF(Z21=2,Y21*AA21)) -> 7
... A28: E001 | B28: 00000128 | C28: COLABORATIVA S.A.C. | D28: 45937 | E28: 45957.71 | F28: MUÃ‘OZ VERANO JOHN BRACKSON | H28: RUC | I28: 10440668581 | J28: [{'codigo_producto': 2308, 'cantidad': '1', 'valor_unitario': 308.0, 'precio_unitario': 363.44, 'descuento': 0.0, 'subtotal': 308.0, 'porcentaje_de_igv': '18.00', 'igv': 55.44, 'total': 363.44, 'moneda': '1', 'tipo_de_cambio': 1.0, 'id_tipo_gasto': 5, 'nom_tipo_gasto': 'Otros', 'id_proveedor': 1389, 'id_producto': 30882, 'nom_producto': 'GASTOS COMPLEMENTARIOS', 'categoria_producto': 'EVENTOS', 'id_estado': 'paid', 'nombre_estado': 'Pagado', 'evento': {'id_evento': '', 'nom_evento': '', 'fecha_hora_ini_event': '', 'fecha_hora_fin_event': '', 'id_organizador': '', 'nom_organizador': '', 'tipo_organizador': ''}, 'id_cuenta': 6743, 'nom_cuenta': '6329102 SERVICIOS DIVERSOS', 'distribucion_analitica': [[{'codigo': 132, 'nom_distribucion': 'Validadores', 'sub_categoria': 'Gastos de Viaje', 'porcentaje': '100.00'}]]}] | K28: 45937 | Q28: 2308 | R28: 1 | S28: 308 | T28: 363.44 | U28: 0 | V28: 308 | W28: 18 | X28: 55.44 | Y28: 363.44 | Z28: 1 | AA28: 1 | AB28: 5 | AC28: Otros | AD28: 1389 | AE28: 30882 | AF28: GASTOS COMPLEMENTARIOS | AG28: EVENTOS | AH28: paid | AI28: Pagado | AJ28: 6743 | AK28: 6329102 SERVICIOS DIVERSOS | AL28: [[{'codigo': 132, 'nom_distribucion': 'Validadores', 'sub_categoria': 'Gastos de Viaje', 'porcentaje': '100.00'}]] | AT28: =+CONCATENATE(A28,"-",B28) -> E001-00000128 | AU28: =+IF(Z28=1,V28,IF(Z28=2,V28*AA28)) -> 308 | AV28: =+IF(Z28=1,X28,IF(Z28=2,X28*AA28)) -> 55.44 | AW28: =+IF(Z28=1,Y28,IF(Z28=2,Y28*AA28)) -> 363.44
A29: E001 | B29: 00000067 | C29: COLABORATIVA S.A.C. | D29: 45937 | E29: 45957.707 | F29: VENTURA SABINO MIGUEL ANGEL | H29: RUC | J29: [{'codigo_producto': 2307, 'cantidad': '1', 'valor_unitario': 880.0, 'precio_unitario': 880.0, 'descuento': 0.0, 'subtotal': 880.0, 'porcentaje_de_igv': '0.00', 'igv': 0.0, 'total': 880.0, 'moneda': '1', 'tipo_de_cambio': 1.0, 'id_tipo_gasto': 5, 'nom_tipo_gasto': 'Otros', 'id_proveedor': 1806, 'id_producto': 30880, 'nom_producto': 'TRABAJO DE GASFITERIA', 'categoria_producto': 'EVENTOS', 'id_estado': 'paid', 'nombre_estado': 'Pagado', 'evento': {'id_evento': '', 'nom_evento': '', 'fecha_hora_ini_event': '', 'fecha_hora_fin_event': '', 'id_organizador': '', 'nom_organizador': '', 'tipo_organizador': ''}, 'id_cuenta': 6743, 'nom_cuenta': '6329102 SERVICIOS DIVERSOS', 'distribucion_analitica': [[{'codigo': 138, 'nom_distribucion': 'Administrativo', 'sub_categoria': 'Acondicionamiento', 'porcentaje': '100.00'}]]}] | K29: 45937 | Q29: 2307 | R29: 1 | S29: 880 | T29: 880 | U29: 0 | V29: 880 | W29: 0 | X29: 0 | Y29: 880 | Z29: 1 | AA29: 1 | AB29: 5 | AC29: Otros | AD29: 1806 | AE29: 30880 | AF29: TRABAJO DE GASFITERIA | AG29: EVENTOS | AH29: paid | AI29: Pagado | AJ29: 6743 | AK29: 6329102 SERVICIOS DIVERSOS | AL29: [[{'codigo': 138, 'nom_distribucion': 'Administrativo', 'sub_categoria': 'Acondicionamiento', 'porcentaje': '100.00'}]] | AT29: =+CONCATENATE(A29,"-",B29) -> E001-00000067 | AU29: =+IF(Z29=1,V29,IF(Z29=2,V29*AA29)) -> 880 | AV29: =+IF(Z29=1,X29,IF(Z29=2,X29*AA29)) -> 0 | AW29: =+IF(Z29=1,Y29,IF(Z29=2,Y29*AA29)) -> 880
A30: E001 | B30: 00000016 | C30: COLABORATIVA S.A.C. | D30: 45943 | E30: 45957.616 | F30: SALVADOR ARNALDO REYES CHUECAS | H30: RUC | I30: 10722818593 | J30: [{'codigo_producto': 1851, 'cantidad': '1', 'valor_unitario': 600.0, 'precio_unitario': 600.0, 'descuento': 0.0, 'subtotal': 600.0, 'porcentaje_de_igv': '0.00', 'igv': 0.0, 'total': 600.0, 'moneda': '1', 'tipo_de_cambio': 1.0, 'id_tipo_gasto': 2, 'nom_tipo_gasto': 'Servicios', 'id_proveedor': 4421, 'id_producto': 31047, 'nom_producto': 'SERVICIOS', 'categoria_producto': 'EVENTOS', 'id_estado': 'paid', 'nombre_estado': 'Pagado', 'evento': {'id_evento': '', 'nom_evento': '', 'fecha_hora_ini_event': '', 'fecha_hora_fin_event': '', 'id_organizador': '', 'nom_organizador': '', 'tipo_organizador': ''}, 'id_cuenta': 6743, 'nom_cuenta': '6329102 SERVICIOS DIVERSOS', 'distribucion_analitica': [[{'codigo': 68, 'nom_distribucion': 'ATC', 'sub_categoria': 'Personal de apoyo', 'porcentaje': '100.00'}]]}] | K30: 45943 | Q30: 1851 | R30: 1 | S30: 600 | T30: 600 | U30: 0 | V30: 600 | W30: 0 | X30: 0 | Y30: 600 | Z30: 1 | AA30: 1 | AB30: 2 | AC30: Servicios | AD30: 4421 | AE30: 31047 | AF30: SERVICIOS | AG30: EVENTOS | AH30: paid | AI30: Pagado | AJ30: 6743 | AK30: 6329102 SERVICIOS DIVERSOS | AL30: [[{'codigo': 68, 'nom_distribucion': 'ATC', 'sub_categoria': 'Personal de apoyo', 'porcentaje': '100.00'}]] | AT30: =+CONCATENATE(A30,"-",B30) -> E001-00000016 | AU30: =+IF(Z30=1,V30,IF(Z30=2,V30*AA30)) -> 600 | AV30: =+IF(Z30=1,X30,IF(Z30=2,X30*AA30)) -> 0 | AW30: =+IF(Z30=1,Y30,IF(Z30=2,Y30*AA30)) -> 600
A31: F004 | B31: 00001283 | C31: COLABORATIVA S.A.C. | D31: 45940 | E31: 45957.399 | F31: ORIENTAL GOURMET S.A. | H31: RUC | I31: 20372634350 | J31: [{'codigo_producto': 1912, 'cantidad': '1', 'valor_unitario': 64.5, 'precio_unitario': 64.5, 'descuento': 0.0, 'subtotal': 64.5, 'porcentaje_de_igv': '0.00', 'igv': 0.0, 'total': 64.5, 'moneda': '1', 'tipo_de_cambio': 1.0, 'id_tipo_gasto': 5, 'nom_tipo_gasto': 'Otros', 'id_proveedor': 6005, 'id_producto': 30957, 'nom_producto': 'ALMUERZO', 'categoria_producto': 'EVENTOS', 'id_estado': 'paid', 'nombre_estado': 'Pagado', 'evento': {'id_evento': '', 'nom_evento': '', 'fecha_hora_ini_event': '', 'fecha_hora_fin_event': '', 'id_organizador': '', 'nom_organizador': '', 'tipo_organizador': ''}, 'id_cuenta': 6726, 'nom_cuenta': '6314100 AlimentaciÃ³n', 'distribucion_analitica': [[{'codigo': 145, 'nom_distribucion': 'Administrativo', 'sub_categoria': 'Gerencia', 'porcentaje': '100.00'}]]}] | K31: 45940 | Q31: 1912 | R31: 1 | S31: 64.5 | T31: 64.5 | U31: 0 | V31: 64.5 | W31: 0 | X31: 0 | Y31: 64.5 | Z31: 1 | AA31: 1 | AB31: 5 | AC31: Otros | AD31: 6005 | AE31: 30957 | AF31: ALMUERZO | AG31: EVENTOS | AH31: paid | AI31: Pagado | AJ31: 6726 | AK31: 6314100 AlimentaciÃ³n | AL31: [[{'codigo': 145, 'nom_distribucion': 'Administrativo', 'sub_categoria': 'Gerencia', 'porcentaje': '100.00'}]] | AT31: =+CONCATENATE(A31,"-",B31) -> F004-00001283 | AU31: =+IF(Z31=1,V31,IF(Z31=2,V31*AA31)) -> 64.5 | AV31: =+IF(Z31=1,X31,IF(Z31=2,X31*AA31)) -> 0 | AW31: =+IF(Z31=1,Y31,IF(Z31=2,Y31*AA31)) -> 64.5
A32: E001 | B32: 38 | C32: COLABORATIVA S.A.C. | D32: 45939 | E32: 45957.448 | F32: CARMEN CRUZ MILAGROS ZONALI | H32: RUC | I32: 10767791416 | J32: [{'codigo_producto': 2258, 'cantidad': '1', 'valor_unitario': 160.0, 'precio_unitario': 160.0, 'descuento': 0.0, 'subtotal': 160.0, 'porcentaje_de_igv': '0.00', 'igv': 0.0, 'total': 160.0, 'moneda': '1', 'tipo_de_cambio': 1.0, 'id_tipo_gasto': 2, 'nom_tipo_gasto': 'Servicios', 'id_proveedor': 1553, 'id_producto': 30930, 'nom_producto': 'SERV VALIDADORES ', 'categoria_producto': 'SERVICIOS', 'id_estado': 'paid', 'nombre_estado': 'Pagado', 'evento': {'id_evento': '', 'nom_evento': '', 'fecha_hora_ini_event': '', 'fecha_hora_fin_event': '', 'id_organizador': '', 'nom_organizador': '', 'tipo_organizador': ''}, 'id_cuenta': 877, 'nom_cuenta': '6329000 AsesorÃ­a y consultorÃ­a - Otros', 'distribucion_analitica': [[{'codigo': '', 'nom_distribucion': '', 'sub_categoria': '', 'porcentaje': '100.00'}]]}] | K32: 45939 | Q32: 2258 | R32: 1 | S32: 160 | T32: 160 | U32: 0 | V32: 160 | W32: 0 | X32: 0 | Y32: 160 | Z32: 1 | AA32: 1 | AB32: 2 | AC32: Servicios | AD32: 1553 | AE32: 30930 | AF32: SERV VALIDADORES | AG32: SERVICIOS | AH32: paid | AI32: Pagado | AJ32: 877 | AK32: 6329000 AsesorÃ­a y consultorÃ­a - Otros | AL32: [[{'codigo': '', 'nom_distribucion': '', 'sub_categoria': '', 'porcentaje': '100.00'}]] | AT32: =+CONCATENATE(A32,"-",B32) -> E001-38 | AU32: =+IF(Z32=1,V32,IF(Z32=2,V32*AA32)) -> 160 | AV32: =+IF(Z32=1,X32,IF(Z32=2,X32*AA32)) -> 0 | AW32: =+IF(Z32=1,Y32,IF(Z32=2,Y32*AA32)) -> 160
A33: F001 | B33: 00025751 | C33: COLABORATIVA S.A.C. | D33: 45936 | E33: 45957.375 | F33: TECNOLOGIA FLEXOGRAFICA S.A.C - TECFLEX | G33: Proveedor | H33: RUC | I33: 20430785266 | J33: [{'codigo_producto': 1966, 'cantidad': '5', 'valor_unitario': 41.8, 'precio_unitario': 49.324, 'descuento': 0.0, 'subtotal': 209.0, 'porcentaje_de_igv': '18.00', 'igv': 37.620000000000005, 'total': 246.62, 'moneda': '1', 'tipo_de_cambio': 1.0, 'id_tipo_gasto': 5, 'nom_tipo_gasto': 'Otros', 'id_proveedor': 470, 'id_producto': 30903, 'nom_producto': 'ETIQUETA', 'categoria_producto': 'EVENTOS', 'id_estado': 'paid', 'nombre_estado': 'Pagado', 'evento': {'id_evento': '', 'nom_evento': '', 'fecha_hora_ini_event': '', 'fecha_hora_fin_event': '', 'id_organizador': '', 'nom_organizador': '', 'tipo_organizador': ''}, 'id_cuenta': 877, 'nom_cuenta': '6329000 AsesorÃ­a y consultorÃ­a - Otros', 'distribucion_analitica': [[{'codigo': 83, 'nom_distribucion': 'Impresos', 'sub_categoria': 'Suministros Compra', 'porcentaje': '100.00'}]]}, {'codigo_producto': 1902, 'cantidad': '120', 'valor_unitario': 18.9, 'precio_unitario': 22.302, 'descuento': 0.0, 'subtotal': 2268.0, 'porcentaje_de_igv': '18.00', 'igv': 408.2399999999998, 'total': 2676.24, 'moneda': '1', 'tipo_de_cambio': 1.0, 'id_tipo_gasto': 5, 'nom_tipo_gasto': 'Otros', 'id_proveedor': 470, 'id_producto': 30904, 'nom_producto': 'Etiquetas de seguridad', 'categoria_producto': 'EVENTOS', 'id_estado': 'paid', 'nombre_estado': 'Pagado', 'evento': {'id_evento': '', 'nom_evento': '', 'fecha_hora_ini_event': '', 'fecha_hora_fin_event': '', 'id_organizador': '', 'nom_organizador': '', 'tipo_organizador': ''}, 'id_cuenta': 877, 'nom_cuenta': '6329000 AsesorÃ­a y consultorÃ­a - Otros', 'distribucion_analitica': [[{'codigo': 83, 'nom_distribucion': 'Impresos', 'sub_categoria': 'Suministros Compra', 'porcentaje': '100.00'}]]}] | K33: 45936 | Q33: 1966 | R33: 5 | S33: 41.8 | T33: 49.324 | U33: 0 | V33: 209 | W33: 18 | X33: 37.62 | Y33: 246.62 | Z33: 1 | AA33: 1 | AB33: 5 | AC33: Otros | AD33: 470 | AE33: 30903 | AF33: ETIQUETA | AG33: EVENTOS | AH33: paid | AI33: Pagado | AJ33: 877 | AK33: 6329000 AsesorÃ­a y consultorÃ­a - Otros | AL33: [[{'codigo': 83, 'nom_distribucion': 'Impresos', 'sub_categoria': 'Suministros Compra', 'porcentaje': '100.00'}]] | AT33: =+CONCATENATE(A33,"-",B33) -> F001-00025751 | AU33: =+IF(Z33=1,V33,IF(Z33=2,V33*AA33)) -> 209 | AV33: =+IF(Z33=1,X33,IF(Z33=2,X33*AA33)) -> 37.62 | AW33: =+IF(Z33=1,Y33,IF(Z33=2,Y33*AA33)) -> 246.62
A34: F001 | B34: 00025751 | C34: COLABORATIVA S.A.C. | D34: 45936 | E34: 45957.375 | F34: TECNOLOGIA FLEXOGRAFICA S.A.C - TECFLEX | G34: Proveedor | H34: RUC | I34: 20430785266 | J34: [{'codigo_producto': 1966, 'cantidad': '5', 'valor_unitario': 41.8, 'precio_unitario': 49.324, 'descuento': 0.0, 'subtotal': 209.0, 'porcentaje_de_igv': '18.00', 'igv': 37.620000000000005, 'total': 246.62, 'moneda': '1', 'tipo_de_cambio': 1.0, 'id_tipo_gasto': 5, 'nom_tipo_gasto': 'Otros', 'id_proveedor': 470, 'id_producto': 30903, 'nom_producto': 'ETIQUETA', 'categoria_producto': 'EVENTOS', 'id_estado': 'paid', 'nombre_estado': 'Pagado', 'evento': {'id_evento': '', 'nom_evento': '', 'fecha_hora_ini_event': '', 'fecha_hora_fin_event': '', 'id_organizador': '', 'nom_organizador': '', 'tipo_organizador': ''}, 'id_cuenta': 877, 'nom_cuenta': '6329000 AsesorÃ­a y consultorÃ­a - Otros', 'distribucion_analitica': [[{'codigo': 83, 'nom_distribucion': 'Impresos', 'sub_categoria': 'Suministros Compra', 'porcentaje': '100.00'}]]}, {'codigo_producto': 1902, 'cantidad': '120', 'valor_unitario': 18.9, 'precio_unitario': 22.302, 'descuento': 0.0, 'subtotal': 2268.0, 'porcentaje_de_igv': '18.00', 'igv': 408.2399999999998, 'total': 2676.24, 'moneda': '1', 'tipo_de_cambio': 1.0, 'id_tipo_gasto': 5, 'nom_tipo_gasto': 'Otros', 'id_proveedor': 470, 'id_producto': 30904, 'nom_producto': 'Etiquetas de seguridad', 'categoria_producto': 'EVENTOS', 'id_estado': 'paid', 'nombre_estado': 'Pagado', 'evento': {'id_evento': '', 'nom_evento': '', 'fecha_hora_ini_event': '', 'fecha_hora_fin_event': '', 'id_organizador': '', 'nom_organizador': '', 'tipo_organizador': ''}, 'id_cuenta': 877, 'nom_cuenta': '6329000 AsesorÃ­a y consultorÃ­a - Otros', 'distribucion_analitica': [[{'codigo': 83, 'nom_distribucion': 'Impresos', 'sub_categoria': 'Suministros Compra', 'porcentaje': '100.00'}]]}] | K34: 45936 | Q34: 1902 | R34: 120 | S34: 18.9 | T34: 22.302 | U34: 0 | V34: 2268 | W34: 18 | X34: 408.24 | Y34: 2676.24 | Z34: 1 | AA34: 1 | AB34: 5 | AC34: Otros | AD34: 470 | AE34: 30904 | AF34: Etiquetas de seguridad | AG34: EVENTOS | AH34: paid | AI34: Pagado | AJ34: 877 | AK34: 6329000 AsesorÃ­a y consultorÃ­a - Otros | AL34: [[{'codigo': 83, 'nom_distribucion': 'Impresos', 'sub_categoria': 'Suministros Compra', 'porcentaje': '100.00'}]] | AT34: =+CONCATENATE(A34,"-",B34) -> F001-00025751 | AU34: =+IF(Z34=1,V34,IF(Z34=2,V34*AA34)) -> 2268 | AV34: =+IF(Z34=1,X34,IF(Z34=2,X34*AA34)) -> 408.24 | AW34: =+IF(Z34=1,Y34,IF(Z34=2,Y34*AA34)) -> 2676.24
A35: 544 | B35: 4458714229 | C35: COLABORATIVA S.A.C. | D35: 45939 | E35: 45957.492 | F35: LATAM AIRLINES PERU S.A. | H35: RUC | I35: 20341841357 | J35: [{'codigo_producto': 2309, 'cantidad': '1', 'valor_unitario': 132.78, 'precio_unitario': 156.68, 'descuento': 0.0, 'subtotal': 132.78, 'porcentaje_de_igv': '18.00', 'igv': 23.900000000000006, 'total': 156.68, 'moneda': '1', 'tipo_de_cambio': 1.0, 'id_tipo_gasto': 5, 'nom_tipo_gasto': 'Otros', 'id_proveedor': 1406, 'id_producto': 30938, 'nom_producto': 'EQUIPAJE', 'categoria_producto': 'EVENTOS', 'id_estado': 'paid', 'nombre_estado': 'Pagado', 'evento': {'id_evento': '', 'nom_evento': '', 'fecha_hora_ini_event': '', 'fecha_hora_fin_event': '', 'id_organizador': '', 'nom_organizador': '', 'tipo_organizador': ''}, 'id_cuenta': 6727, 'nom_cuenta': '6315100 Otros gastos de viaje', 'distribucion_analitica': [[{'codigo': 132, 'nom_distribucion': 'Validadores', 'sub_categoria': 'Gastos de Viaje', 'porcentaje': '100.00'}]]}] | K35: 45939 | Q35: 2309 | R35: 1 | S35: 132.78 | T35: 156.68 | U35: 0 | V35: 132.78 | W35: 18 | X35: 23.9 | Y35: 156.68 | Z35: 1 | AA35: 1 | AB35: 5 | AC35: Otros | AD35: 1406 | AE35: 30938 | AF35: EQUIPAJE | AG35: EVENTOS | AH35: paid | AI35: Pagado | AJ35: 6727 | AK35: 6315100 Otros gastos de viaje | AL35: [[{'codigo': 132, 'nom_distribucion': 'Validadores', 'sub_categoria': 'Gastos de Viaje', 'porcentaje': '100.00'}]] | AT35: =+CONCATENATE(A35,"-",B35) -> 544-4458714229 | AU35: =+IF(Z35=1,V35,IF(Z35=2,V35*AA35)) -> 132.78 | AV35: =+IF(Z35=1,X35,IF(Z35=2,X35*AA35)) -> 23.9 | AW35: =+IF(Z35=1,Y35,IF(Z35=2,Y35*AA35)) -> 156.68
A36: FP03 | B36: 00001558 | C36: COLABORATIVA S.A.C. | D36: 45937 | E36: 45957.735 | F36: ROJAS SIESQUEN CARLOS EDGARDO | H36: RUC | I36: 10424656017 | J36: [{'codigo_producto': 1912, 'cantidad': '1', 'valor_unitario': 128.81, 'precio_unitario': 152.0, 'descuento': 0.0, 'subtotal': 128.81, 'porcentaje_de_igv': '18.00', 'igv': 23.189999999999998, 'total': 152.0, 'moneda': '1', 'tipo_de_cambio': 1.0, 'id_tipo_gasto': 5, 'nom_tipo_gasto': 'Otros', 'id_proveedor': 6269, 'id_producto': 30888, 'nom_producto': 'ALMUERZO', 'categoria_producto': 'EVENTOS', 'id_estado': 'paid', 'nombre_estado': 'Pagado', 'evento': {'id_evento': '', 'nom_evento': '', 'fecha_hora_ini_event': '', 'fecha_hora_fin_event': '', 'id_organizador': '', 'nom_organizador': '', 'tipo_organizador': ''}, 'id_cuenta': 6726, 'nom_cuenta': '6314100 AlimentaciÃ³n', 'distribucion_analitica': [[{'codigo': 132, 'nom_distribucion': 'Validadores', 'sub_categoria': 'Gastos de Viaje', 'porcentaje': '100.00'}]]}] | K36: 45937 | Q36: 1912 | R36: 1 | S36: 128.81 | T36: 152 | U36: 0 | V36: 128.81 | W36: 18 | X36: 23.19 | Y36: 152 | Z36: 1 | AA36: 1 | AB36: 5 | AC36: Otros | AD36: 6269 | AE36: 30888 | AF36: ALMUERZO | AG36: EVENTOS | AH36: paid | AI36: Pagado | AJ36: 6726 | AK36: 6314100 AlimentaciÃ³n | AL36: [[{'codigo': 132, 'nom_distribucion': 'Validadores', 'sub_categoria': 'Gastos de Viaje', 'porcentaje': '100.00'}]] | AT36: =+CONCATENATE(A36,"-",B36) -> FP03-00001558 | AU36: =+IF(Z36=1,V36,IF(Z36=2,V36*AA36)) -> 128.81 | AV36: =+IF(Z36=1,X36,IF(Z36=2,X36*AA36)) -> 23.19 | AW36: =+IF(Z36=1,Y36,IF(Z36=2,Y36*AA36)) -> 152
A37: FF13 | B37: 00000401 | C37: COLABORATIVA S.A.C. | D37: 45937 | E37: 45957.713 | F37: LATAM PERU S.A.C. | H37: RUC | I37: 20602737111 | J37: [{'codigo_producto': 2031, 'cantidad': '1', 'valor_unitario': 50.85, 'precio_unitario': 60.0, 'descuento': 0.0, 'subtotal': 50.85, 'porcentaje_de_igv': '17.99', 'igv': 9.149999999999999, 'total': 60.0, 'moneda': '1', 'tipo_de_cambio': 1.0, 'id_tipo_gasto': 5, 'nom_tipo_gasto': 'Otros', 'id_proveedor': 6268, 'id_producto': 30885, 'nom_producto': 'CINTA DE EMBALAJE', 'categoria_producto': 'EVENTOS', 'id_estado': 'paid', 'nombre_estado': 'Pagado', 'evento': {'id_evento': '', 'nom_evento': '', 'fecha_hora_ini_event': '', 'fecha_hora_fin_event': '', 'id_organizador': '', 'nom_organizador': '', 'tipo_organizador': ''}, 'id_cuenta': 6743, 'nom_cuenta': '6329102 SERVICIOS DIVERSOS', 'distribucion_analitica': [[{'codigo': 132, 'nom_distribucion': 'Validadores', 'sub_categoria': 'Gastos de Viaje', 'porcentaje': '100.00'}]]}] | K37: 45937 | Q37: 2031 | R37: 1 | S37: 50.85 | T37: 60 | U37: 0 | V37: 50.85 | W37: 17.99 | X37: 9.15 | Y37: 60 | Z37: 1 | AA37: 1 | AB37: 5 | AC37: Otros | AD37: 6268 | AE37: 30885 | AF37: CINTA DE EMBALAJE | AG37: EVENTOS | AH37: paid | AI37: Pagado | AJ37: 6743 | AK37: 6329102 SERVICIOS DIVERSOS | AL37: [[{'codigo': 132, 'nom_distribucion': 'Validadores', 'sub_categoria': 'Gastos de Viaje', 'porcentaje': '100.00'}]] | AT37: =+CONCATENATE(A37,"-",B37) -> FF13-00000401 | AU37: =+IF(Z37=1,V37,IF(Z37=2,V37*AA37)) -> 50.85 | AV37: =+IF(Z37=1,X37,IF(Z37=2,X37*AA37)) -> 9.15 | AW37: =+IF(Z37=1,Y37,IF(Z37=2,Y37*AA37)) -> 60
A38: E001 | B38: 00000004 | C38: COLABORATIVA S.A.C. | D38: 45937 | E38: 45957.583 | F38: SECLEN ZAMORA JAHAIRA VANESSITA | G38: Proveedor | H38: RUC | I38: 10483541991 | J38: [{'codigo_producto': 2258, 'cantidad': '2', 'valor_unitario': 110.0, 'precio_unitario': 110.0, 'descuento': 0.0, 'subtotal': 220.0, 'porcentaje_de_igv': '0.00', 'igv': 0.0, 'total': 220.0, 'moneda': '1', 'tipo_de_cambio': 1.0, 'id_tipo_gasto': 2, 'nom_tipo_gasto': 'Servicios', 'id_proveedor': 469, 'id_producto': 30857, 'nom_producto': 'SERV VALIDADORES ', 'categoria_producto': 'SERVICIOS', 'id_estado': 'paid', 'nombre_estado': 'Pagado', 'evento': {'id_evento': '', 'nom_evento': '', 'fecha_hora_ini_event': '', 'fecha_hora_fin_event': '', 'id_organizador': '', 'nom_organizador': '', 'tipo_organizador': ''}, 'id_cuenta': 6743, 'nom_cuenta': '6329102 SERVICIOS DIVERSOS', 'distribucion_analitica': [[{'codigo': 103, 'nom_distribucion': 'Validadores', 'sub_categoria': 'Personal temporal', 'porcentaje': '100.00'}]]}] | K38: 45937 | Q38: 2258 | R38: 2 | S38: 110 | T38: 110 | U38: 0 | V38: 220 | W38: 0 | X38: 0 | Y38: 220 | Z38: 1 | AA38: 1 | AB38: 2 | AC38: Servicios | AD38: 469 | AE38: 30857 | AF38: SERV VALIDADORES | AG38: SERVICIOS | AH38: paid | AI38: Pagado | AJ38: 6743 | AK38: 6329102 SERVICIOS DIVERSOS | AL38: [[{'codigo': 103, 'nom_distribucion': 'Validadores', 'sub_categoria': 'Personal temporal', 'porcentaje': '100.00'}]] | AT38: =+CONCATENATE(A38,"-",B38) -> E001-00000004 | AU38: =+IF(Z38=1,V38,IF(Z38=2,V38*AA38)) -> 220 | AV38: =+IF(Z38=1,X38,IF(Z38=2,X38*AA38)) -> 0 | AW38: =+IF(Z38=1,Y38,IF(Z38=2,Y38*AA38)) -> 220
A39: E001 | B39: 00000015 | C39: COLABORATIVA S.A.C. | D39: 45935 | E39: 45957.5 | F39: BRAVO MATOS RICARDO ALEJANDRO | H39: RUC | I39: 10746350975 | J39: [{'codigo_producto': 2258, 'cantidad': '1', 'valor_unitario': 120.0, 'precio_unitario': 120.0, 'descuento': 0.0, 'subtotal': 120.0, 'porcentaje_de_igv': '0.00', 'igv': 0.0, 'total': 120.0, 'moneda': '1', 'tipo_de_cambio': 1.0, 'id_tipo_gasto': 2, 'nom_tipo_gasto': 'Servicios', 'id_proveedor': 1430, 'id_producto': 30843, 'nom_producto': 'SERV VALIDADORES ', 'categoria_producto': 'SERVICIOS', 'id_estado': 'paid', 'nombre_estado': 'Pagado', 'evento': {'id_evento': '', 'nom_evento': '', 'fecha_hora_ini_event': '', 'fecha_hora_fin_event': '', 'id_organizador': '', 'nom_organizador': '', 'tipo_organizador': ''}, 'id_cuenta': 877, 'nom_cuenta': '6329000 AsesorÃ­a y consultorÃ­a - Otros', 'distribucion_analitica': [[{'codigo': '', 'nom_distribucion': '', 'sub_categoria': '', 'porcentaje': '100.00'}]]}] | K39: 45935 | Q39: 2258 | R39: 1 | S39: 120 | T39: 120 | U39: 0 | V39: 120 | W39: 0 | X39: 0 | Y39: 120 | Z39: 1 | AA39: 1 | AB39: 2 | AC39: Servicios | AD39: 1430 | AE39: 30843 | AF39: SERV VALIDADORES | AG39: SERVICIOS | AH39: paid | AI39: Pagado | AJ39: 877 | AK39: 6329000 AsesorÃ­a y consultorÃ­a - Otros | AL39: [[{'codigo': '', 'nom_distribucion': '', 'sub_categoria': '', 'porcentaje': '100.00'}]] | AT39: =+CONCATENATE(A39,"-",B39) -> E001-00000015 | AU39: =+IF(Z39=1,V39,IF(Z39=2,V39*AA39)) -> 120 | AV39: =+IF(Z39=1,X39,IF(Z39=2,X39*AA39)) -> 0 | AW39: =+IF(Z39=1,Y39,IF(Z39=2,Y39*AA39)) -> 120
A40: SB02 | B40: 0243453637 | C40: COLABORATIVA S.A.C. | D40: 45944 | E40: 45957.374 | F40: America MÃ³vil PerÃº S.A.C. | H40: RUC | I40: 20467534026 | J40: [{'codigo_producto': 1829, 'cantidad': '1', 'valor_unitario': 36.04, 'precio_unitario': 42.53, 'descuento': 0.0, 'subtotal': 36.04, 'porcentaje_de_igv': '18.01', 'igv': 6.490000000000002, 'total': 42.53, 'moneda': '1', 'tipo_de_cambio': 1.0, 'id_tipo_gasto': 2, 'nom_tipo_gasto': 'Servicios', 'id_proveedor': 2218, 'id_producto': 31094, 'nom_producto': 'SERVICIO DE COMUNICACIONES', 'categoria_producto': 'EVENTOS', 'id_estado': 'not_paid', 'nombre_estado': 'Sin pagar', 'evento': {'id_evento': '', 'nom_evento': '', 'fecha_hora_ini_event': '', 'fecha_hora_fin_event': '', 'id_organizador': '', 'nom_organizador': '', 'tipo_organizador': ''}, 'id_cuenta': 6960, 'nom_cuenta': '632902 Operativos', 'distribucion_analitica': [[{'codigo': 69, 'nom_distribucion': 'Comercial', 'sub_categoria': 'Otros', 'porcentaje': '100.00'}]]}] | K40: 45944 | Q40: 1829 | R40: 1 | S40: 36.04 | T40: 42.53 | U40: 0 | V40: 36.04 | W40: 18.01 | X40: 6.49 | Y40: 42.53 | Z40: 1 | AA40: 1 | AB40: 2 | AC40: Servicios | AD40: 2218 | AE40: 31094 | AF40: SERVICIO DE COMUNICACIONES | AG40: EVENTOS | AH40: not_paid | AI40: Sin pagar | AJ40: 6960 | AK40: 632902 Operativos | AL40: [[{'codigo': 69, 'nom_distribucion': 'Comercial', 'sub_categoria': 'Otros', 'porcentaje': '100.00'}]] | AT40: =+CONCATENATE(A40,"-",B40) -> SB02-0243453637 | AU40: =+IF(Z40=1,V40,IF(Z40=2,V40*AA40)) -> 36.04 | AV40: =+IF(Z40=1,X40,IF(Z40=2,X40*AA40)) -> 6.49 | AW40: =+IF(Z40=1,Y40,IF(Z40=2,Y40*AA40)) -> 42.53
A41: F001 | B41: 00009665 | C41: COLABORATIVA S.A.C. | D41: 45932 | E41: 45957.736 | F41: PRECINTOS PERU E.I.R.L | H41: RUC | I41: 20546099904 | J41: [{'codigo_producto': 2300, 'cantidad': '500', 'valor_unitario': 0.29662, 'precio_unitario': 0.35, 'descuento': 0.0, 'subtotal': 148.31, 'porcentaje_de_igv': '18.00', 'igv': 26.689999999999998, 'total': 175.0, 'moneda': '1', 'tipo_de_cambio': 1.0, 'id_tipo_gasto': 5, 'nom_tipo_gasto': 'Otros', 'id_proveedor': 1400, 'id_producto': 30798, 'nom_producto': 'BOLETO PREMIUM COSTESIA GENERAL', 'categoria_producto': 'EVENTOS', 'id_estado': 'paid', 'nombre_estado': 'Pagado', 'evento': {'id_evento': '', 'nom_evento': '', 'fecha_hora_ini_event': '', 'fecha_hora_fin_event': '', 'id_organizador': '', 'nom_organizador': '', 'tipo_organizador': ''}, 'id_cuenta': 6962, 'nom_cuenta': '602112 Insumos', 'distribucion_analitica': [[{'codigo': 83, 'nom_distribucion': 'Impresos', 'sub_categoria': 'Suministros Compra', 'porcentaje': '100.00'}]]}, {'codigo_producto': 2301, 'cantidad': '500', 'valor_unitario': 0.29662, 'precio_unitario': 0.35, 'descuento': 0.0, 'subtotal': 148.31, 'porcentaje_de_igv': '18.00', 'igv': 26.689999999999998, 'total': 175.0, 'moneda': '1', 'tipo_de_cambio': 1.0, 'id_tipo_gasto': 5, 'nom_tipo_gasto': 'Otros', 'id_proveedor': 1400, 'id_producto': 30799, 'nom_producto': 'BOLETO PREMIUM COSTESIA VIP', 'categoria_producto': 'EVENTOS', 'id_estado': 'paid', 'nombre_estado': 'Pagado', 'evento': {'id_evento': '', 'nom_evento': '', 'fecha_hora_ini_event': '', 'fecha_hora_fin_event': '', 'id_organizador': '', 'nom_organizador': '', 'tipo_organizador': ''}, 'id_cuenta': 6962, 'nom_cuenta': '602112 Insumos', 'distribucion_analitica': [[{'codigo': 83, 'nom_distribucion': 'Impresos', 'sub_categoria': 'Suministros Compra', 'porcentaje': '100.00'}]]}, {'codigo_producto': 2302, 'cantidad': '400', 'valor_unitario': 0.161025, 'precio_unitario': 0.19, 'descuento': 0.0, 'subtotal': 64.41, 'porcentaje_de_igv': '17.99', 'igv': 11.590000000000003, 'total': 76.0, 'moneda': '1', 'tipo_de_cambio': 1.0, 'id_tipo_gasto': 5, 'nom_tipo_gasto': 'Otros', 'id_proveedor': 1400, 'id_producto': 30800, 'nom_producto': 'BRAZALETE ZONA FUNDADORES', 'categoria_producto': 'EVENTOS', 'id_estado': 'paid', 'nombre_estado': 'Pagado', 'evento': {'id_evento': '', 'nom_evento': '', 'fecha_hora_ini_event': '', 'fecha_hora_fin_event': '', 'id_organizador': '', 'nom_organizador': '', 'tipo_organizador': ''}, 'id_cuenta': 6962, 'nom_cuenta': '602112 Insumos', 'distribucion_analitica': [[{'codigo': 83, 'nom_distribucion': 'Impresos', 'sub_categoria': 'Suministros Compra', 'porcentaje': '100.00'}]]}, {'codigo_producto': 2303, 'cantidad': '4000', 'valor_unitario': 0.155085, 'precio_unitario': 0.183, 'descuento': 0.0, 'subtotal': 620.34, 'porcentaje_de_igv': '18.00', 'igv': 111.65999999999997, 'total': 732.0, 'moneda': '1', 'tipo_de_cambio': 1.0, 'id_tipo_gasto': 5, 'nom_tipo_gasto': 'Otros', 'id_proveedor': 1400, 'id_producto': 30801, 'nom_producto': 'BRAZALETE ZONA FAMILIA HU', 'categoria_producto': 'EVENTOS', 'id_estado': 'paid', 'nombre_estado': 'Pagado', 'evento': {'id_evento': '', 'nom_evento': '', 'fecha_hora_ini_event': '', 'fecha_hora_fin_event': '', 'id_organizador': '', 'nom_organizador': '', 'tipo_organizador': ''}, 'id_cuenta': 6962, 'nom_cuenta': '602112 Insumos', 'distribucion_analitica': [[{'codigo': 83, 'nom_distribucion': 'Impresos', 'sub_categoria': 'Suministros Compra', 'porcentaje': '100.00'}]]}, {'codigo_producto': 2265, 'cantidad': '600', 'valor_unitario': 0.16101666666666667, 'precio_unitario': 0.19, 'descuento': 0.0, 'subtotal': 96.61, 'porcentaje_de_igv': '18.00', 'igv': 17.39, 'total': 114.0, 'moneda': '1', 'tipo_de_cambio': 1.0, 'id_tipo_gasto': 5, 'nom_tipo_gasto': 'Otros', 'id_proveedor': 1400, 'id_producto': 30802, 'nom_producto': 'BRAZALETES VIP ', 'categoria_producto': 'MERCADERIA', 'id_estado': 'paid', 'nombre_estado': 'Pagado', 'evento': {'id_evento': '', 'nom_evento': '', 'fecha_hora_ini_event': '', 'fecha_hora_fin_event': '', 'id_organizador': '', 'nom_organizador': '', 'tipo_organizador': ''}, 'id_cuenta': 6962, 'nom_cuenta': '602112 Insumos', 'distribucion_analitica': [[{'codigo': 83, 'nom_distribucion': 'Impresos', 'sub_categoria': 'Suministros Compra', 'porcentaje': '100.00'}]]}, {'codigo_producto': 2304, 'cantidad': '190', 'valor_unitario': 0.15510526315789472, 'precio_unitario': 0.18300000000000002, 'descuento': 0.0, 'subtotal': 29.47, 'porcentaje_de_igv': '17.98', 'igv': 5.300000000000004, 'total': 34.77, 'moneda': '1', 'tipo_de_cambio': 1.0, 'id_tipo_gasto': 5, 'nom_tipo_gasto': 'Otros', 'id_proveedor': 1400, 'id_producto': 30803, 'nom_producto': 'BRAZALETES ZONA HALLOBOX', 'categoria_producto': 'EVENTOS', 'id_estado': 'paid', 'nombre_estado': 'Pagado', 'evento': {'id_evento': '', 'nom_evento': '', 'fecha_hora_ini_event': '', 'fecha_hora_fin_event': '', 'id_organizador': '', 'nom_organizador': '', 'tipo_organizador': ''}, 'id_cuenta': 6962, 'nom_cuenta': '602112 Insumos', 'distribucion_analitica': [[{'codigo': 83, 'nom_distribucion': 'Impresos', 'sub_categoria': 'Suministros Compra', 'porcentaje': '100.00'}]]}, {'codigo_producto': 2265, 'cantidad': '810', 'valor_unitario': 0.15508641975308643, 'precio_unitario': 0.183, 'descuento': 0.0, 'subtotal': 125.62, 'porcentaje_de_igv': '18.00', 'igv': 22.609999999999985, 'total': 148.23, 'moneda': '1', 'tipo_de_cambio': 1.0, 'id_tipo_gasto': 5, 'nom_tipo_gasto': 'Otros', 'id_proveedor': 1400, 'id_producto': 30804, 'nom_producto': 'BRAZALETES VIP ', 'categoria_producto': 'MERCADERIA', 'id_estado': 'paid', 'nombre_estado': 'Pagado', 'evento': {'id_evento': '', 'nom_evento': '', 'fecha_hora_ini_event': '', 'fecha_hora_fin_event': '', 'id_organizador': '', 'nom_organizador': '', 'tipo_organizador': ''}, 'id_cuenta': 6962, 'nom_cuenta': '602112 Insumos', 'distribucion_analitica': [[{'codigo': 83, 'nom_distribucion': 'Impresos', 'sub_categoria': 'Suministros Compra', 'porcentaje': '100.00'}]]}, {'codigo_producto': 2265, 'cantidad': '1200', 'valor_unitario': 0.15508333333333332, 'precio_unitario': 0.183, 'descuento': 0.0, 'subtotal': 186.1, 'porcentaje_de_igv': '18.00', 'igv': 33.5, 'total': 219.6, 'moneda': '1', 'tipo_de_cambio': 1.0, 'id_tipo_gasto': 5, 'nom_tipo_gasto': 'Otros', 'id_proveedor': 1400, 'id_producto': 30805, 'nom_producto': 'BRAZALETES VIP ', 'categoria_producto': 'MERCADERIA', 'id_estado': 'paid', 'nombre_estado': 'Pagado', 'evento': {'id_evento': '', 'nom_evento': '', 'fecha_hora_ini_event': '', 'fecha_hora_fin_event': '', 'id_organizador': '', 'nom_organizador': '', 'tipo_organizador': ''}, 'id_cuenta': 6962, 'nom_cuenta': '602112 Insumos', 'distribucion_analitica': [[{'codigo': 83, 'nom_distribucion': 'Impresos', 'sub_categoria': 'Suministros Compra', 'porcentaje': '100.00'}]]}, {'codigo_producto': 2265, 'cantidad': '800', 'valor_unitario': 0.1550875, 'precio_unitario': 0.183, 'descuento': 0.0, 'subtotal': 124.07, 'porcentaje_de_igv': '18.00', 'igv': 22.330000000000013, 'total': 146.4, 'moneda': '1', 'tipo_de_cambio': 1.0, 'id_tipo_gasto': 5, 'nom_tipo_gasto': 'Otros', 'id_proveedor': 1400, 'id_producto': 30806, 'nom_producto': 'BRAZALETES VIP ', 'categoria_producto': 'MERCADERIA', 'id_estado': 'paid', 'nombre_estado': 'Pagado', 'evento': {'id_evento': '', 'nom_evento': '', 'fecha_hora_ini_event': '', 'fecha_hora_fin_event': '', 'id_organizador': '', 'nom_organizador': '', 'tipo_organizador': ''}, 'id_cuenta': 6962, 'nom_cuenta': '602112 Insumos', 'distribucion_analitica': [[{'codigo': 83, 'nom_distribucion': 'Impresos', 'sub_categoria': 'Suministros Compra', 'porcentaje': '100.00'}]]}, {'codigo_producto': 2265, 'cantidad': '1500', 'valor_unitario': 0.15508666666666665, 'precio_unitario': 0.183, 'descuento': 0.0, 'subtotal': 232.63, 'porcentaje_de_igv': '18.00', 'igv': 41.870000000000005, 'total': 274.5, 'moneda': '1', 'tipo_de_cambio': 1.0, 'id_tipo_gasto': 5, 'nom_tipo_gasto': 'Otros', 'id_proveedor': 1400, 'id_producto': 30807, 'nom_producto': 'BRAZALETES VIP ', 'categoria_producto': 'MERCADERIA', 'id_estado': 'paid', 'nombre_estado': 'Pagado', 'evento': {'id_evento': '', 'nom_evento': '', 'fecha_hora_ini_event': '', 'fecha_hora_fin_event': '', 'id_organizador': '', 'nom_organizador': '', 'tipo_organizador': ''}, 'id_cuenta': 6962, 'nom_cuenta': '602112 Insumos', 'distribucion_analitica': [[{'codigo': 83, 'nom_distribucion': 'Impresos', 'sub_categoria': 'Suministros Compra', 'porcentaje': '100.00'}]]}, {'codigo_producto': 2306, 'cantidad': '250', 'valor_unitario': 0.42372000000000004, 'precio_unitario': 0.5, 'descuento': 0.0, 'subtotal': 105.93, 'porcentaje_de_igv': '18.00', 'igv': 19.069999999999993, 'total': 125.0, 'moneda': '1', 'tipo_de_cambio': 1.0, 'id_tipo_gasto': 5, 'nom_tipo_gasto': 'Otros', 'id_proveedor': 1400, 'id_producto': 30808, 'nom_producto': 'BRAZALETES FULL ACCESS', 'categoria_producto': 'EVENTOS', 'id_estado': 'paid', 'nombre_estado': 'Pagado', 'evento': {'id_evento': '', 'nom_evento': '', 'fecha_hora_ini_event': '', 'fecha_hora_fin_event': '', 'id_organizador': '', 'nom_organizador': '', 'tipo_organizador': ''}, 'id_cuenta': 6962, 'nom_cuenta': '602112 Insumos', 'distribucion_analitica': [[{'codigo': 83, 'nom_distribucion': 'Impresos', 'sub_categoria': 'Suministros Compra', 'porcentaje': '100.00'}]]}, {'codigo_producto': 2265, 'cantidad': '250', 'valor_unitario': 0.48304, 'precio_unitario': 0.57, 'descuento': 0.0, 'subtotal': 120.76, 'porcentaje_de_igv': '18.00', 'igv': 21.739999999999995, 'total': 142.5, 'moneda': '1', 'tipo_de_cambio': 1.0, 'id_tipo_gasto': 5, 'nom_tipo_gasto': 'Otros', 'id_proveedor': 1400, 'id_producto': 30809, 'nom_producto': 'BRAZALETES VIP ', 'categoria_producto': 'MERCADERIA', 'id_estado': 'paid', 'nombre_estado': 'Pagado', 'evento': {'id_evento': '', 'nom_evento': '', 'fecha_hora_ini_event': '', 'fecha_hora_fin_event': '', 'id_organizador': '', 'nom_organizador': '', 'tipo_organizador': ''}, 'id_cuenta': 6962, 'nom_cuenta': '602112 Insumos', 'distribucion_analitica': [[{'codigo': 83, 'nom_distribucion': 'Impresos', 'sub_categoria': 'Suministros Compra', 'porcentaje': '100.00'}]]}] | K41: 45932 | Q41: 2300 | R41: 500 | S41: 0.29662 | T41: 0.35 | U41: 0 | V41: 148.31 | W41: 18 | X41: 26.69 | Y41: 175 | Z41: 1 | AA41: 1 | AB41: 5 | AC41: Otros | AD41: 1400 | AE41: 30798 | AF41: BOLETO PREMIUM COSTESIA GENERAL | AG41: EVENTOS | AH41: paid | AI41: Pagado | AJ41: 6962 | AK41: 602112 Insumos | AL41: [[{'codigo': 83, 'nom_distribucion': 'Impresos', 'sub_categoria': 'Suministros Compra', 'porcentaje': '100.00'}]] | AT41: =+CONCATENATE(A41,"-",B41) -> F001-00009665 | AU41: =+IF(Z41=1,V41,IF(Z41=2,V41*AA41)) -> 148.31 | AV41: =+IF(Z41=1,X41,IF(Z41=2,X41*AA41)) -> 26.69 | AW41: =+IF(Z41=1,Y41,IF(Z41=2,Y41*AA41)) -> 175
